Workbook

Sheet Projection P&L
A1: Compte de résultat VPRDS | B1: Année 2025 | C1: Année 2026 | D1: Année 2027 | F1: Données marge de production | G1: 2024 | H1: 2025 | I1: 2026 | J1: 2027
A3: Chiffre d'affaires travaux | B3: ='Suivi 31.12.25'!AK62/1000 -> 2424.7343 | C3: =+I19 -> 2686.5571 | D3: =+J19 -> 3097.5 | F3: Nombre de chantiers en cours au 31/12/N-1 réceptionnés en N | G3: =COUNT('Suivi 31.12.2023'!AP3:AP11) -> 8 | H3: 14 | I3: =+H5 -> 14 | J3: =+I5 -> 15 | L3: Ne pas modifier = formules
F4: Nombre de chantiers ouverts et réceptionnés en N | G4: 2 | H4: ='Suivi 31.12.25'!B46 -> 6 | I4: 10 | J4: 10 | L4: A renseigner
F5: Nombre de chantiers encours au 31/12/N | G5: 14 | H5: 14 | I5: 15 | J5: 20
A6: Charges variables sur chantiers | B6: =+B3-B7 -> 1988.5093 | C6: =+C3-C7 -> 2186.933 | D6: =+D3-D7 -> 2478
A7: Marge de production | B7: ='Suivi 31.12.25'!AH62/1000 -> 436.22501 | C7: =+I20 -> 499.62413 | D7: =+J20 -> 619.5 | F7: PV HT moyen (y compris case 0 et net de SASA) chantiers en cours au 31/12/N-1 | G7: =(SUM('SUIVI 31.12.24'!AH29:AH36)/COUNT('SUIVI 31.12.24'!AH29:AH36))/1000 -> 121.94844 | H7: =+G9 -> 120.10867 | I7: =+H9 -> 126.67346 | J7: =+I9 -> 118
A8: % de marge de production | B8: =+B7/B3 -> 0.17990631 | C8: =+C7/C3 -> 0.1859719 | D8: =+D7/D3 -> 0.2 | F8: PV HT moyen (y compris case 0 et net de SASA) chantiers ouverts et réceptionnés en N | G8: =+SUM('SUIVI 31.12.24'!AJ37:AJ38)/'Projection P&L'!G4/1000 -> 114.28727 | H8: =+SUM('Suivi 31.12.25'!AK40:AK45)/'Suivi 31.12.25'!B46/1000 -> 100.42831 | I8: 118 | J8: 118
F9: PV HT moyen (y compris case 0 et net de SASA) chantiers encours au 31/12/N | G9: =(SUM('SUIVI 31.12.24 ALTONEO'!AI3:AI27)/'Projection P&L'!G5)/1000 -> 120.10867 | H9: =+SUM('Suivi 31.12.25'!AI3:AI38)/'Suivi 31.12.25'!B39/1000 -> 126.67346 | I9: 118 | J9: 118
A10: Autres produits (subvention)
F11: Taux de marge moyen chantiers en cours au 31/12/N-1 | G11: =SUM('SUIVI 31.12.24'!AG29:AG36)/SUM('SUIVI 31.12.24'!AJ29:AJ36) -> 0.20165494 | H11: =SUM('Suivi 31.12.25'!AG47:AG60)/SUM('Suivi 31.12.25'!AJ47:AJ60) -> 0.20952266 | I11: =+H13 -> 0.16458152 | J11: =+I13 -> 0.2
A12: Coût de strucutre (masse salariale + charges fixes) | B12: =+B18+B15 -> 414.26811 | C12: =+C18+C15 -> 438.6 | D12: =+D18+D15 -> 526.8 | F12: Taux de marge moyen chantiers ouverts et réceptionnés en N | G12: =+('SUIVI 31.12.24'!AE37+'SUIVI 31.12.24'!AE38)/('SUIVI 31.12.24'!AH37+'SUIVI 31.12.24'!AH38) -> 0.22646675 | H12: =SUM('Suivi 31.12.25'!AF40:AF45)/SUM('Suivi 31.12.25'!AI40:AI45) -> 0.20117384 | I12: 0.2 | J12: 0.2
A13: % du CA | B13: =+B12/(B3) -> 0.17085093 | C13: =+C12/(C3) -> 0.16325728 | D13: =+D12/(D3) -> 0.17007264 | F13: Taux de marge moyen chantiers encours au 31/12/N | G13: =SUM('SUIVI 31.12.24 ALTONEO'!AF3:AF27)/SUM('SUIVI 31.12.24 ALTONEO'!AI3:AI27) -> 0.20283615 | H13: =SUM('Suivi 31.12.25'!AF3:AF38)/SUM('Suivi 31.12.25'!AI3:AI38) -> 0.16458152 | I13: 0.2 | J13: 0.2
A15: Masse salariale (y compris taxes rattachées) | B15: =+H57 -> 214.26811 | C15: =+I57 -> 211.2 | D15: =+J57 -> 276.66 | F15: Taux restant d'avancement des chantiers en cours au 31/12/N-1 à constater en N | G15: =+SUM('SUIVI 31.12.24'!AJ29:AJ36)/SUM('SUIVI 31.12.24'!AH29:AH36) -> 0.70183871 | H15: =(1-G16) -> 0.61863825 | I15: =(1-H16) -> 0.6 | J15: =(1-I16) -> 0.75
B16: =+B15/B3 -> 0.088367664 | C16: =+C15/C3 -> 0.078613628 | D16: =+D15/D3 -> 0.089317191 | F16: Taux d'avancement des chantiers en cours au 31/12/N | G16: =SUMPRODUCT('SUIVI 31.12.24'!E3:E27,'SUIVI 31.12.24'!AH3:AH27)/SUM('SUIVI 31.12.24'!AH3:AH27) -> 0.38136175 | H16: 0.4 | I16: 0.25 | J16: 0.25 | L16: Pour le moment même avancement moyen sur les encours à la fin de chaque année. Peut être modifié à la main ou s'aider des suivi 2025 et années suivantes
A18: Frais généraux | B18: 200 | C18: =SUM(C19:C27) -> 227.4 | D18: =SUM(D19:D27) -> 250.14
A19: Achats non stockés (eau, électricité, fournitures) | B19: 8 | C19: 8.8 | D19: =C19*(1+$J$23) -> 9.68 | F19: Soit un Chiffre d'affaires | G19: =+G3*G7*G15+G5*G9*G16+G4*G8 -> 1554.5476 | H19: =+H3*H7*H15+H5*H9*H16+H4*H8 -> 2352.1947 | I19: =+I3*I7*I15+I5*I9*I16+I4*I8 -> 2686.5571 | J19: =+J3*J7*J15+J5*J9*J16+J4*J8 -> 3097.5
A20: Assurances | B20: 4 | C20: 4.4 | D20: =C20*(1+$J$23) -> 4.84 | F20: Soit une marge de production | G20: =+G3*G7*G15*G11+G4*G8*G12+G5*G9*G13*G16-4 -> 315.91102 | H20: =+H3*H7*H15*H11+H4*H8*H12+H5*H9*H13*H16 -> 455.92738 | I20: =+I3*I7*I15*I11+I4*I8*I12+I5*I9*I13*I16 -> 499.62413 | J20: =+J3*J7*J15*J11+J4*J8*J12+J5*J9*J13*J16 -> 619.5
A21: Maintenance et entretien | B21: 12 | C21: 12 | D21: =C21*(1+$J$23) -> 13.2 | F21: % de marge de production net | G21: =+G20/G19 -> 0.20321734 | H21: =+H20/H19 -> 0.19383063 | I21: =+I20/I19 -> 0.1859719 | J21: =+J20/J19 -> 0.2
A22: Locations immobilières | B22: 20 | C22: 20 | D22: =C22*(1+$J$23) -> 22
A23: Locations mobilières (y compris véhicules) | B23: 20 | C23: 20 | D23: =C23*(1+$J$23) -> 22 | F23: % de variation frais généraux (si baisse mettre - devant le %) versus N-1 | G23: =+(#REF!-#REF!)/#REF! -> #REF! | H23: 0.1 | I23: 0.1 | J23: 0.1
A24: Marketing et Communication (hors redevances de Pub Mikit) | B24: 78 | C24: 80 | D24: =C24*(1+$J$23) -> 88
A25: Honoraires divers | B25: 28 | C25: 30 | D25: =C25*(1+$J$23) -> 33 | F25: Masse salariale (mettre les montants en € et non K€)
A26: Voyages et déplacements (dont carburant) | B26: 50 | C26: 50 | D26: =C26*(1+$J$23) -> 55
A27: Téléphonie, frais postaux et frais bancaires | B27: 2 | C27: 2.2 | D27: =C27*(1+$J$23) -> 2.42 | F27: Salarié 1 salaire Brut mensuel moyen y compris primes | G27: 2800 | H27: 4000 | I27: 5900 | J27: 2800
F28: Salarié 1 montant charges patronales | G28: =G27*0.45 -> 1260 | H28: =H27*0.45 -> 1800 | I28: 0 | J28: =J27*0.45 -> 1260
A29: Autres impôts et taxes | B29: 2 | C29: 3 | D29: 4 | F29: Nombre de mois de présence sur l'année | G29: 4 | H29: 12 | I29: 12 | J29: 12
F30: coûts salarié 1 (VP) | G30: 17090 | H30: 70800 | I30: =+(I27+I28)*I29 -> 70800 | J30: =+(J27+J28)*J29 -> 48720
A31: Amortissements et provisions | B31: 9 | C31: 9 | D31: 9
F32: Salarié 2 salaire Brut mensuel moyen y compris prime | G32: 3200 | H32: 3500 | I32: 5000 | J32: 4200
A33: Résultat d'exploitation | B33: =B7-B12-B29-B31+B10-2 -> 8.9569009 | C33: =C7-C12-C29-C31+C10-2 -> 47.024134 | D33: =D7-D12-D29-D31+D10-2 -> 77.7 | F33: Salarié 2 montant charges patronales | G33: =G32*0.45 -> 1440 | H33: =H32*0.45 -> 1575 | I33: =I32*0.45 -> 2250 | J33: =J32*0.45 -> 1890
F34: Nombre de mois de présence sur l'année | G34: 12 | H34: 12 | I34: 0 | J34: 12
A35: Résultat financier | B35: -2 | C35: -2 | D35: -2 | F35: coûts salarié 2 (AL com) | G35: 51181.47 | H35: 62111.17 | I35: =+(I32+I33)*I34 -> 0 | J35: =+(J32+J33)*J34 -> 73080
A37: Résultat exceptionnel | F37: Salarié 3 salaire Brut mensuel moyen y compris prime | G37: 2500 | H37: 2900 | I37: 3500 | J37: 4200
F38: Salarié 3 montant charges patronales | G38: =G37*0.45 -> 1125 | H38: =H37*0.45 -> 1305 | I38: =I37*0.45 -> 1575 | J38: =J37*0.45 -> 1890
A39: Impôt sur les sociétés | B39: =+B50 -> 0.80966071 | C39: =+C50 -> 7.0060335 | D39: =+D50 -> 14.675 | F39: Nombre de mois de présence sur l'année | G39: 3 | H39: 12 | I39: 12 | J39: 12
F40: coûts salarié 3 (NB com) | G40: 11209.74 | H40: 64522.88 | I40: =+(I37+I38)*I39 -> 60900 | J40: =+(J37+J38)*J39 -> 73080
A41: Résultat net | B41: =+B35+B37-B39+B33 -> 6.1472402 | C41: =+C35+C37-C39+C33 -> 38.018101 | D41: =+D35+D37-D39+D33 -> 61.025
F42: Salarié 4 salaire Brut mensuel moyen y compris pime | H42: 2500 | I42: 3500 | J42: 4700
F43: Salarié 4 montant charges patronales | G43: =G42*0.45 -> 0 | H43: =H42*0.45 -> 1125 | I43: =I42*0.45 -> 1575 | J43: =J42*0.45 -> 2115
F44: Nombre de mois de présence sur l'année | G44: 0 | H44: 6 | I44: 12 | J44: 12
F45: coûts salarié 4 (RB com) | G45: =+(G42+G43)*G44 -> 0 | H45: 10676.75 | I45: =+(I42+I43)*I44 -> 60900 | J45: =+(J42+J43)*J44 -> 81780
A46: Déficit reportable | B46: 0 | C46: =IF(B48<0,B48,0) -> 0 | D46: =IF(C48<0,C48,0) -> 0
A47: Résultat avant impot | B47: =+B33+B35+B37 -> 6.9569009 | C47: =+C33+C35+C37 -> 45.024134 | D47: =+D33+D35+D37 -> 75.7 | F47: Salarié 5 salaire Brut mensuel moyen y compris prime | H47: 1200 | I47: 1500
A48: Base imposable | B48: =+B47+B46 -> 6.9569009 | C48: =+C47+C46 -> 45.024134 | D48: =+D47+D46 -> 75.7 | F48: Salarié 5 montant charges patronales | G48: =G46*0.45 -> 0 | H48: =H46*0.45 -> 0 | I48: 50 | J48: =J46*0.45 -> 0
F49: Nombre de mois de présence sur l'année | H49: 4 | I49: 12
A50: IS | B50: 0.80966071 | C50: =+C51+C52 -> 7.0060335 | D50: =+D51+D52 -> 14.675 | F50: coûts salarié 5 (JJ adv) | G50: =+(G47+G48)*G49 -> 0 | H50: 6157.31 | I50: =+(I47+I48)*I49 -> 18600 | J50: =+(J47+J48)*J49 -> 0
A51: 0.15 | B51: 0.80966071 | C51: =IF(C48>42.5,42.5*$A$51,C48*$A$51) -> 6.375 | D51: =IF(D48>42.5,42.5*$A$51,D48*$A$51) -> 6.375
A52: 0.25 | B52: 0 | C52: =+IF(C48>42.5,(C48-42.5)*$A$52,0) -> 0.63103353 | D52: =+IF(D48>42.5,(D48-42.5)*$A$52,0) -> 8.3 | F52: Salarié 6 salaire Brut moyen y compris prime
F53: Salarié 6 montant charges patronales | G53: =G52*0.45 -> 0 | H53: =H52*0.45 -> 0 | I53: =I52*0.45 -> 0 | J53: =J52*0.45 -> 0
F54: Nombre de mois de présence sur l'année
F55: coûts salarié 6 | G55: =+(G52+G53)*G54 -> 0 | H55: =+(H52+H53)*H54 -> 0 | I55: =+(I52+I53)*I54 -> 0 | J55: =+(J52+J53)*J54 -> 0
F57: TOTAL MASSE SALARIALE | G57: =+(G55+G50+G45+G40+G35+G30)/1000 -> 79.48121 | H57: =+(H55+H50+H45+H40+H35+H30)/1000 -> 214.26811 | I57: =+(I55+I50+I45+I40+I35+I30)/1000 -> 211.2 | J57: =+(J55+J50+J45+J40+J35+J30)/1000 -> 276.66

Sheet Suivi 2026
F1: Données prévisionnelles ou connues (à mettre à jour) | O1: Factures en compta (à mettre à jour) | U1: cut-off Chiffre d'affaires | Y1: Cut-off charges | AF1: Marges | AI1: Chiffre d'affaires HT | AL1: Frais de dossiers HT | AO1: Reste à comptabiliser | AQ1: % de marge nette | AR1: Solde compte de charges
A2: Étape ↑ | B2: Nom du projet | C2: Facture vente finale faite | D2: Statut chantier | E2: % Avancement | F2: Prix convenu (chiffre d'affaires) HT | G2: Montant avenants HT | H2: Prix actualisé HT net de SASA | I2: SASA dans le projet HT | J2: Redevances Mikit | K2: Redevances Pub | L2: Honoraires MIKIT | M2: Sous-traitance MKT | N2: Honoraires courtage HT | O2: SASA HT | P2: Redevance MIKIT | Q2: Redevance Pub MIKIT | R2: Honoraires MKT | S2: Sous-traitance MKT | T2: Honoraires courtage HT | U2: FAE CA | V2: FAE dossiers assurance | W2: FAE SASA | X2: AAE SASA | Y2: Redevance MIKIT 6% FNP | Z2: Redevance MIKIT CCA | AA2: Redevance pub MIKIT 2.5% FNP | AB2: Redevance pub MIKIT CCA | AC2: Honoraires MIKIT FNP | AD2: Sous-traitance FNP MKT | AE2: Frais courtage CCA | AF2: Marge totale chantier HT | AG2: Marges constatées N-1 | AH2: Marges 2026 HT | AI2: CA Total HT | AJ2: CA constaté N-1 | AK2: CA 2026 HT | AL2: CA Total HT | AM2: CA constaté N-1 | AN2: CA 2024 HT | AO2: CA à comptabiliser € HT | AP2: marge à comptabiliser € HT | AR2: SS MKT | AS2: SS MKT N-1 | AT2: SS MKT N | AU2: Hono MKT | AV2: Hono MKT N-1 | AW2: Hono MKT N | AX2: Fond Mikit | AY2: Fond Mikit N-1 | AZ2: Fond Mikit N | BA2: Pub Mikit | BB2: Pub Mikit N-1 | BC2: Pub Mikit N | BD2: Commissions | BE2: Commissions N-1 | BF2: Commissions N
B3: Projet Beilvert / Voguet Vivoin | C3: non | D3: 1.1 Administratif validé prêt à ouvrir | E3: =VLOOKUP(D3,'% avancement'!$A$4:$B$17,2,FALSE()) -> 0.25 | F3: 125666.67 | G3: 7500 | H3: =F3+G3-I3 -> 128166.67 | I3: 5000 | J3: =(F3+G3-I3)*0.06 -> 7690 | K3: =(F3+G3-I3)*0.025 -> 3204.1667 | L3: 7828.15 | M3: =(F3+G3)*0.62 -> 82563.333 | N3: 6000 | U3: =IF(C3="oui","",(H3+I3)*E3) -> 33291.667 | W3: =IF(O3="",0,(1-E3)*O3) -> 0 | X3: =IF(O3="",I3*(E3),0) -> 1250 | Y3: =IF(P3="",+H3*6%*E3,0) -> 1922.5 | Z3: =IF(P3="",0,P3*(1-E3)) -> 0 | AA3: =IF(Q3="",+H3*2.5%*E3,0) -> 801.04167 | AB3: =IF(Q3="",0,Q3*(1-E3)) -> 0 | AC3: =IF(R3="",+L3*E3,(1-E3)*R3) -> 1957.0375 | AD3: =IF(S3="",M3*E3,S3*E3) -> 20640.833 | AF3: =IF(E3="",0,+H3-J3-K3-L3-M3-N3) -> 20881.017 | AG3: =IFERROR((VLOOKUP(B3,'Suivi 31.12.25'!$B$1:$BF$38,33,FALSE())),0) -> 5220.2542 | AH3: =AF3*E3-AG3 -> 0 | AI3: =IF(E3="",0,H3) -> 128166.67 | AJ3: =IFERROR((VLOOKUP(B3,'Suivi 31.12.25'!$B$1:$BF$38,36,FALSE())),0) -> 32041.667 | AK3: =AI3*E3-AJ3 -> 0 | AO3: =IF(E3=0,0,AI3-AJ3-AK3) -> 96125 | AP3: =IF(E3=0,0,AF3-AG3-AH3) -> 15660.763 | AQ3: =IF(E3="","",+AF3/AI3) -> 0.16292081 | AR3: =IF(S3="",M3*E3,S3*E3) -> 20640.833 | AS3: =IFERROR((VLOOKUP(B3,'SUIVI 31.12.24 ALTONEO'!$B$1:$BF$38,45,FALSE())),0) -> 0 | AT3: =+AR3-AS3 -> 20640.833 | AU3: =+L3*E3 -> 1957.0375 | AV3: =IFERROR((VLOOKUP(B3,'SUIVI 31.12.24 ALTONEO'!$B$1:$BF$38,48,FALSE())),0) -> 0 | AW3: =+AU3-AV3 -> 1957.0375 | AX3: =IF(P3="",J3*E3,P3-Z3) -> 1922.5 | AY3: =IFERROR((VLOOKUP(B3,'SUIVI 31.12.24 ALTONEO'!$B$1:$BF$38,51,FALSE())),0) -> 0 | AZ3: =+AX3-AY3 -> 1922.5 | BA3: =IF(Q3="",K3*E3,Q3-AB3) -> 801.04167 | BB3: =IFERROR((VLOOKUP(B3,'SUIVI 31.12.24 ALTONEO'!$B$1:$BF$38,54,FALSE())),0) -> 0 | BC3: =+BA3-BB3 -> 801.04167 | BD3: =+E3*N3 -> 1500 | BE3: =IFERROR((VLOOKUP(B3,'SUIVI 31.12.24 ALTONEO'!$B$1:$BF$38,57,FALSE())),0) -> 0
B4: Projet Moulineuf / Jouie Rouessé-Vassé | C4: non | D4: 1.1 Administratif validé prêt à ouvrir | E4: =VLOOKUP(D4,'% avancement'!$A$4:$B$17,2,FALSE()) -> 0.25 | F4: 146083.33 | G4: 7500 | H4: =F4+G4-I4 -> 148583.33 | I4: 5000 | J4: =(F4+G4-I4)*0.06 -> 8915 | K4: =(F4+G4-I4)*0.025 -> 3714.5833 | L4: 7828.15 | M4: =(F4+G4)*0.62 -> 95221.667 | N4: 6000 | U4: =IF(C4="oui","",(H4+I4)*E4) -> 38395.833 | W4: =IF(O4="",0,(1-E4)*O4) -> 0 | X4: =IF(O4="",I4*(E4),0) -> 1250 | Y4: =IF(P4="",+H4*6%*E4,0) -> 2228.75 | Z4: =IF(P4="",0,P4*(1-E4)) -> 0 | AA4: =IF(Q4="",+H4*2.5%*E4,0) -> 928.64583 | AB4: =IF(Q4="",0,Q4*(1-E4)) -> 0 | AC4: =IF(R4="",+L4*E4,(1-E4)*R4) -> 1957.0375 | AD4: =IF(S4="",M4*E4,S4*E4) -> 23805.417 | AF4: =IF(E4="",0,+H4-J4-K4-L4-M4-N4) -> 26903.933 | AG4: =IFERROR((VLOOKUP(B4,'Suivi 31.12.25'!$B$1:$BF$38,33,FALSE())),0) -> 0 | AH4: =AF4*E4-AG4 -> 6725.9833 | AI4: =IF(E4="",0,H4) -> 148583.33 | AJ4: =IFERROR((VLOOKUP(B4,'Suivi 31.12.25'!$B$1:$BF$38,36,FALSE())),0) -> 0 | AK4: =AI4*E4-AJ4 -> 37145.833 | AO4: =IF(E4=0,0,AI4-AJ4-AK4) -> 111437.5 | AP4: =IF(E4=0,0,AF4-AG4-AH4) -> 20177.95 | AQ4: =IF(E4="","",+AF4/AI4) -> 0.18106966 | AR4: =IF(S4="",M4*E4,S4*E4) -> 23805.417 | AS4: =IFERROR((VLOOKUP(B4,'SUIVI 31.12.24 ALTONEO'!$B$1:$BF$38,45,FALSE())),0) -> 0 | AT4: =+AR4-AS4 -> 23805.417 | AU4: =+L4*E4 -> 1957.0375 | AV4: =IFERROR((VLOOKUP(B4,'SUIVI 31.12.24 ALTONEO'!$B$1:$BF$38,48,FALSE())),0) -> 0 | AW4: =+AU4-AV4 -> 1957.0375 | AX4: =IF(P4="",J4*E4,P4-Z4) -> 2228.75 | AY4: =IFERROR((VLOOKUP(B4,'SUIVI 31.12.24 ALTONEO'!$B$1:$BF$38,51,FALSE())),0) -> 0 | AZ4: =+AX4-AY4 -> 2228.75 | BA4: =IF(Q4="",K4*E4,Q4-AB4) -> 928.64583 | BB4: =IFERROR((VLOOKUP(B4,'SUIVI 31.12.24 ALTONEO'!$B$1:$BF$38,54,FALSE())),0) -> 0 | BC4: =+BA4-BB4 -> 928.64583 | BD4: =+E4*N4 -> 1500 | BE4: =IFERROR((VLOOKUP(B4,'SUIVI 31.12.24 ALTONEO'!$B$1:$BF$38,57,FALSE())),0) -> 0
B5: Projet Charlong / Vivoin | C5: non | D5: 1.1 Administratif validé prêt à ouvrir | E5: =VLOOKUP(D5,'% avancement'!$A$4:$B$17,2,FALSE()) -> 0.25 | F5: 110916.67 | G5: 7500 | H5: =F5+G5-I5 -> 113416.67 | I5: 5000 | J5: =(F5+G5-I5)*0.06 -> 6805 | K5: =(F5+G5-I5)*0.025 -> 2835.4167 | L5: 7828.15 | M5: =(F5+G5)*0.62 -> 73418.333 | N5: 6000 | U5: =IF(C5="oui","",(H5+I5)*E5) -> 29604.167 | W5: =IF(O5="",0,(1-E5)*O5) -> 0 | X5: =IF(O5="",I5*(E5),0) -> 1250 | Y5: =IF(P5="",+H5*6%*E5,0) -> 1701.25 | Z5: =IF(P5="",0,P5*(1-E5)) -> 0 | AA5: =IF(Q5="",+H5*2.5%*E5,0) -> 708.85417 | AB5: =IF(Q5="",0,Q5*(1-E5)) -> 0 | AC5: =IF(R5="",+L5*E5,(1-E5)*R5) -> 1957.0375 | AD5: =IF(S5="",M5*E5,S5*E5) -> 18354.583 | AF5: =IF(E5="",0,+H5-J5-K5-L5-M5-N5) -> 16529.767 | AG5: =IFERROR((VLOOKUP(B5,'Suivi 31.12.25'!$B$1:$BF$38,33,FALSE())),0) -> 0 | AH5: =AF5*E5-AG5 -> 4132.4417 | AI5: =IF(E5="",0,H5) -> 113416.67 | AJ5: =IFERROR((VLOOKUP(B5,'Suivi 31.12.25'!$B$1:$BF$38,36,FALSE())),0) -> 0 | AK5: =AI5*E5-AJ5 -> 28354.167 | AO5: =IF(E5=0,0,AI5-AJ5-AK5) -> 85062.5 | AP5: =IF(E5=0,0,AF5-AG5-AH5) -> 12397.325 | AQ5: =IF(E5="","",+AF5/AI5) -> 0.14574372 | AR5: =IF(S5="",M5*E5,S5*E5) -> 18354.583 | AS5: =IFERROR((VLOOKUP(B5,'SUIVI 31.12.24 ALTONEO'!$B$1:$BF$38,45,FALSE())),0) -> 0 | AT5: =+AR5-AS5 -> 18354.583 | AU5: =+L5*E5 -> 1957.0375 | AV5: =IFERROR((VLOOKUP(B5,'SUIVI 31.12.24 ALTONEO'!$B$1:$BF$38,48,FALSE())),0) -> 0 | AW5: =+AU5-AV5 -> 1957.0375 | AX5: =IF(P5="",J5*E5,P5-Z5) -> 1701.25 | AY5: =IFERROR((VLOOKUP(B5,'SUIVI 31.12.24 ALTONEO'!$B$1:$BF$38,51,FALSE())),0) -> 0 | AZ5: =+AX5-AY5 -> 1701.25 | BA5: =IF(Q5="",K5*E5,Q5-AB5) -> 708.85417 | BB5: =IFERROR((VLOOKUP(B5,'SUIVI 31.12.24 ALTONEO'!$B$1:$BF$38,54,FALSE())),0) -> 0 | BC5: =+BA5-BB5 -> 708.85417 | BD5: =+E5*N5 -> 1500 | BE5: =IFERROR((VLOOKUP(B5,'SUIVI 31.12.24 ALTONEO'!$B$1:$BF$38,57,FALSE())),0) -> 0
B6: Projet Macé / Vion | C6: non | D6: 1.1 Administratif validé prêt à ouvrir | E6: =VLOOKUP(D6,'% avancement'!$A$4:$B$17,2,FALSE()) -> 0.25 | F6: 98166.667 | G6: 7500 | H6: =F6+G6-I6 -> 100666.67 | I6: 5000 | J6: =(F6+G6-I6)*0.06 -> 6040 | K6: =(F6+G6-I6)*0.025 -> 2516.6667 | L6: 7828.15 | M6: =(F6+G6)*0.62 -> 65513.333 | N6: 6000 | U6: =IF(C6="oui","",(H6+I6)*E6) -> 26416.667 | W6: =IF(O6="",0,(1-E6)*O6) -> 0 | X6: =IF(O6="",I6*(E6),0) -> 1250 | Y6: =IF(P6="",+H6*6%*E6,0) -> 1510 | Z6: =IF(P6="",0,P6*(1-E6)) -> 0 | AA6: =IF(Q6="",+H6*2.5%*E6,0) -> 629.16667 | AB6: =IF(Q6="",0,Q6*(1-E6)) -> 0 | AC6: =IF(R6="",+L6*E6,(1-E6)*R6) -> 1957.0375 | AD6: =IF(S6="",M6*E6,S6*E6) -> 16378.333 | AF6: =IF(E6="",0,+H6-J6-K6-L6-M6-N6) -> 12768.517 | AG6: =IFERROR((VLOOKUP(B6,'Suivi 31.12.25'!$B$1:$BF$38,33,FALSE())),0) -> 0 | AH6: =AF6*E6-AG6 -> 3192.1292 | AI6: =IF(E6="",0,H6) -> 100666.67 | AJ6: =IFERROR((VLOOKUP(B6,'Suivi 31.12.25'!$B$1:$BF$38,36,FALSE())),0) -> 0 | AK6: =AI6*E6-AJ6 -> 25166.667 | AO6: =IF(E6=0,0,AI6-AJ6-AK6) -> 75500 | AP6: =IF(E6=0,0,AF6-AG6-AH6) -> 9576.3875 | AQ6: =IF(E6="","",+AF6/AI6) -> 0.12683957 | AR6: =IF(S6="",M6*E6,S6*E6) -> 16378.333 | AS6: =IFERROR((VLOOKUP(B6,'SUIVI 31.12.24 ALTONEO'!$B$1:$BF$38,45,FALSE())),0) -> 0 | AT6: =+AR6-AS6 -> 16378.333 | AU6: =+L6*E6 -> 1957.0375 | AV6: =IFERROR((VLOOKUP(B6,'SUIVI 31.12.24 ALTONEO'!$B$1:$BF$38,48,FALSE())),0) -> 0 | AW6: =+AU6-AV6 -> 1957.0375 | AX6: =IF(P6="",J6*E6,P6-Z6) -> 1510 | AY6: =IFERROR((VLOOKUP(B6,'SUIVI 31.12.24 ALTONEO'!$B$1:$BF$38,51,FALSE())),0) -> 0 | AZ6: =+AX6-AY6 -> 1510 | BA6: =IF(Q6="",K6*E6,Q6-AB6) -> 629.16667 | BB6: =IFERROR((VLOOKUP(B6,'SUIVI 31.12.24 ALTONEO'!$B$1:$BF$38,54,FALSE())),0) -> 0 | BC6: =+BA6-BB6 -> 629.16667 | BD6: =+E6*N6 -> 1500 | BE6: =IFERROR((VLOOKUP(B6,'SUIVI 31.12.24 ALTONEO'!$B$1:$BF$38,57,FALSE())),0) -> 0
B7: Projet Serafin / Serafin Changé | C7: non | D7: 1.1 Administratif validé prêt à ouvrir | E7: =VLOOKUP(D7,'% avancement'!$A$4:$B$17,2,FALSE()) -> 0.25 | F7: 111416.67 | G7: 7500 | H7: =F7+G7-I7 -> 113916.67 | I7: 5000 | J7: =(F7+G7-I7)*0.06 -> 6835 | K7: =(F7+G7-I7)*0.025 -> 2847.9167 | L7: 7828.15 | M7: =(F7+G7)*0.62 -> 73728.333 | N7: 6000 | U7: =IF(C7="oui","",(H7+I7)*E7) -> 29729.167 | W7: =IF(O7="",0,(1-E7)*O7) -> 0 | X7: =IF(O7="",I7*(E7),0) -> 1250 | Y7: =IF(P7="",+H7*6%*E7,0) -> 1708.75 | Z7: =IF(P7="",0,P7*(1-E7)) -> 0 | AA7: =IF(Q7="",+H7*2.5%*E7,0) -> 711.97917 | AB7: =IF(Q7="",0,Q7*(1-E7)) -> 0 | AC7: =IF(R7="",+L7*E7,(1-E7)*R7) -> 1957.0375 | AD7: =IF(S7="",M7*E7,S7*E7) -> 18432.083 | AF7: =IF(E7="",0,+H7-J7-K7-L7-M7-N7) -> 16677.267 | AG7: =IFERROR((VLOOKUP(B7,'Suivi 31.12.25'!$B$1:$BF$38,33,FALSE())),0) -> 0 | AH7: =AF7*E7-AG7 -> 4169.3167 | AI7: =IF(E7="",0,H7) -> 113916.67 | AJ7: =IFERROR((VLOOKUP(B7,'Suivi 31.12.25'!$B$1:$BF$38,36,FALSE())),0) -> 0 | AK7: =AI7*E7-AJ7 -> 28479.167 | AO7: =IF(E7=0,0,AI7-AJ7-AK7) -> 85437.5 | AP7: =IF(E7=0,0,AF7-AG7-AH7) -> 12507.95 | AQ7: =IF(E7="","",+AF7/AI7) -> 0.14639883 | AR7: =IF(S7="",M7*E7,S7*E7) -> 18432.083 | AS7: =IFERROR((VLOOKUP(B7,'SUIVI 31.12.24 ALTONEO'!$B$1:$BF$38,45,FALSE())),0) -> 0 | AT7: =+AR7-AS7 -> 18432.083 | AU7: =+L7*E7 -> 1957.0375 | AV7: =IFERROR((VLOOKUP(B7,'SUIVI 31.12.24 ALTONEO'!$B$1:$BF$38,48,FALSE())),0) -> 0 | AW7: =+AU7-AV7 -> 1957.0375 | AX7: =IF(P7="",J7*E7,P7-Z7) -> 1708.75 | AY7: =IFERROR((VLOOKUP(B7,'SUIVI 31.12.24 ALTONEO'!$B$1:$BF$38,51,FALSE())),0) -> 0 | AZ7: =+AX7-AY7 -> 1708.75 | BA7: =IF(Q7="",K7*E7,Q7-AB7) -> 711.97917 | BB7: =IFERROR((VLOOKUP(B7,'SUIVI 31.12.24 ALTONEO'!$B$1:$BF$38,54,FALSE())),0) -> 0 | BC7: =+BA7-BB7 -> 711.97917 | BD7: =+E7*N7 -> 1500 | BE7: =IFERROR((VLOOKUP(B7,'SUIVI 31.12.24 ALTONEO'!$B$1:$BF$38,57,FALSE())),0) -> 0
B8: Projet Tekougom / Bonnétable | C8: non | D8: 1.1 Administratif validé prêt à ouvrir | E8: =VLOOKUP(D8,'% avancement'!$A$4:$B$17,2,FALSE()) -> 0.25 | F8: 115666.67 | G8: 7500 | H8: =F8+G8-I8 -> 118166.67 | I8: 5000 | J8: =(F8+G8-I8)*0.06 -> 7090 | K8: =(F8+G8-I8)*0.025 -> 2954.1667 | L8: 7828.15 | M8: =(F8+G8)*0.62 -> 76363.333 | N8: 6000 | U8: =IF(C8="oui","",(H8+I8)*E8) -> 30791.667 | W8: =IF(O8="",0,(1-E8)*O8) -> 0 | X8: =IF(O8="",I8*(E8),0) -> 1250 | Y8: =IF(P8="",+H8*6%*E8,0) -> 1772.5 | Z8: =IF(P8="",0,P8*(1-E8)) -> 0 | AA8: =IF(Q8="",+H8*2.5%*E8,0) -> 738.54167 | AB8: =IF(Q8="",0,Q8*(1-E8)) -> 0 | AC8: =IF(R8="",+L8*E8,(1-E8)*R8) -> 1957.0375 | AD8: =IF(S8="",M8*E8,S8*E8) -> 19090.833 | AF8: =IF(E8="",0,+H8-J8-K8-L8-M8-N8) -> 17931.017 | AG8: =IFERROR((VLOOKUP(B8,'Suivi 31.12.25'!$B$1:$BF$38,33,FALSE())),0) -> 0 | AH8: =AF8*E8-AG8 -> 4482.7542 | AI8: =IF(E8="",0,H8) -> 118166.67 | AJ8: =IFERROR((VLOOKUP(B8,'Suivi 31.12.25'!$B$1:$BF$38,36,FALSE())),0) -> 0 | AK8: =AI8*E8-AJ8 -> 29541.667 | AO8: =IF(E8=0,0,AI8-AJ8-AK8) -> 88625 | AP8: =IF(E8=0,0,AF8-AG8-AH8) -> 13448.263 | AQ8: =IF(E8="","",+AF8/AI8) -> 0.15174344 | AR8: =IF(S8="",M8*E8,S8*E8) -> 19090.833 | AS8: =IFERROR((VLOOKUP(B8,'SUIVI 31.12.24 ALTONEO'!$B$1:$BF$38,45,FALSE())),0) -> 0 | AT8: =+AR8-AS8 -> 19090.833 | AU8: =+L8*E8 -> 1957.0375 | AV8: =IFERROR((VLOOKUP(B8,'SUIVI 31.12.24 ALTONEO'!$B$1:$BF$38,48,FALSE())),0) -> 0 | AW8: =+AU8-AV8 -> 1957.0375 | AX8: =IF(P8="",J8*E8,P8-Z8) -> 1772.5 | AY8: =IFERROR((VLOOKUP(B8,'SUIVI 31.12.24 ALTONEO'!$B$1:$BF$38,51,FALSE())),0) -> 0 | AZ8: =+AX8-AY8 -> 1772.5 | BA8: =IF(Q8="",K8*E8,Q8-AB8) -> 738.54167 | BB8: =IFERROR((VLOOKUP(B8,'SUIVI 31.12.24 ALTONEO'!$B$1:$BF$38,54,FALSE())),0) -> 0 | BC8: =+BA8-BB8 -> 738.54167 | BD8: =+E8*N8 -> 1500 | BE8: =IFERROR((VLOOKUP(B8,'SUIVI 31.12.24 ALTONEO'!$B$1:$BF$38,57,FALSE())),0) -> 0
B9: Projet Attoumani / Attoumani Voivres Lès Le Mans | C9: non | D9: 1.1 Administratif validé prêt à ouvrir | E9: =VLOOKUP(D9,'% avancement'!$A$4:$B$17,2,FALSE()) -> 0.25 | F9: 142000 | G9: 7500 | H9: =F9+G9-I9 -> 144500 | I9: 5000 | J9: =(F9+G9-I9)*0.06 -> 8670 | K9: =(F9+G9-I9)*0.025 -> 3612.5 | L9: 7828.15 | M9: =(F9+G9)*0.62 -> 92690 | N9: 6000 | U9: =IF(C9="oui","",(H9+I9)*E9) -> 37375 | W9: =IF(O9="",0,(1-E9)*O9) -> 0 | X9: =IF(O9="",I9*(E9),0) -> 1250 | Y9: =IF(P9="",+H9*6%*E9,0) -> 2167.5 | Z9: =IF(P9="",0,P9*(1-E9)) -> 0 | AA9: =IF(Q9="",+H9*2.5%*E9,0) -> 903.125 | AB9: =IF(Q9="",0,Q9*(1-E9)) -> 0 | AC9: =IF(R9="",+L9*E9,(1-E9)*R9) -> 1957.0375 | AD9: =IF(S9="",M9*E9,S9*E9) -> 23172.5 | AF9: =IF(E9="",0,+H9-J9-K9-L9-M9-N9) -> 25699.35 | AG9: =IFERROR((VLOOKUP(B9,'Suivi 31.12.25'!$B$1:$BF$38,33,FALSE())),0) -> 0 | AH9: =AF9*E9-AG9 -> 6424.8375 | AI9: =IF(E9="",0,H9) -> 144500 | AJ9: =IFERROR((VLOOKUP(B9,'Suivi 31.12.25'!$B$1:$BF$38,36,FALSE())),0) -> 0 | AK9: =AI9*E9-AJ9 -> 36125 | AO9: =IF(E9=0,0,AI9-AJ9-AK9) -> 108375 | AP9: =IF(E9=0,0,AF9-AG9-AH9) -> 19274.513 | AQ9: =IF(E9="","",+AF9/AI9) -> 0.17785017 | AR9: =IF(S9="",M9*E9,S9*E9) -> 23172.5 | AS9: =IFERROR((VLOOKUP(B9,'SUIVI 31.12.24 ALTONEO'!$B$1:$BF$38,45,FALSE())),0) -> 0 | AT9: =+AR9-AS9 -> 23172.5 | AU9: =+L9*E9 -> 1957.0375 | AV9: =IFERROR((VLOOKUP(B9,'SUIVI 31.12.24 ALTONEO'!$B$1:$BF$38,48,FALSE())),0) -> 0 | AW9: =+AU9-AV9 -> 1957.0375 | AX9: =IF(P9="",J9*E9,P9-Z9) -> 2167.5 | AY9: =IFERROR((VLOOKUP(B9,'SUIVI 31.12.24 ALTONEO'!$B$1:$BF$38,51,FALSE())),0) -> 0 | AZ9: =+AX9-AY9 -> 2167.5 | BA9: =IF(Q9="",K9*E9,Q9-AB9) -> 903.125 | BB9: =IFERROR((VLOOKUP(B9,'SUIVI 31.12.24 ALTONEO'!$B$1:$BF$38,54,FALSE())),0) -> 0 | BC9: =+BA9-BB9 -> 903.125 | BD9: =+E9*N9 -> 1500 | BE9: =IFERROR((VLOOKUP(B9,'SUIVI 31.12.24 ALTONEO'!$B$1:$BF$38,57,FALSE())),0) -> 0
B10: Projet Millard / Lebeau Crosmières | C10: non | D10: 1.1 Administratif validé prêt à ouvrir | E10: =VLOOKUP(D10,'% avancement'!$A$4:$B$17,2,FALSE()) -> 0.25 | F10: 124000 | G10: 7500 | H10: =F10+G10-I10 -> 126500 | I10: 5000 | J10: =(F10+G10-I10)*0.06 -> 7590 | K10: =(F10+G10-I10)*0.025 -> 3162.5 | L10: 7828.15 | M10: =(F10+G10)*0.62 -> 81530 | N10: 6000 | U10: =IF(C10="oui","",(H10+I10)*E10) -> 32875 | W10: =IF(O10="",0,(1-E10)*O10) -> 0 | X10: =IF(O10="",I10*(E10),0) -> 1250 | Y10: =IF(P10="",+H10*6%*E10,0) -> 1897.5 | Z10: =IF(P10="",0,P10*(1-E10)) -> 0 | AA10: =IF(Q10="",+H10*2.5%*E10,0) -> 790.625 | AB10: =IF(Q10="",0,Q10*(1-E10)) -> 0 | AC10: =IF(R10="",+L10*E10,(1-E10)*R10) -> 1957.0375 | AD10: =IF(S10="",M10*E10,S10*E10) -> 20382.5 | AF10: =IF(E10="",0,+H10-J10-K10-L10-M10-N10) -> 20389.35 | AG10: =IFERROR((VLOOKUP(B10,'Suivi 31.12.25'!$B$1:$BF$38,33,FALSE())),0) -> 0 | AH10: =AF10*E10-AG10 -> 5097.3375 | AI10: =IF(E10="",0,H10) -> 126500 | AJ10: =IFERROR((VLOOKUP(B10,'Suivi 31.12.25'!$B$1:$BF$38,36,FALSE())),0) -> 0 | AK10: =AI10*E10-AJ10 -> 31625 | AO10: =IF(E10=0,0,AI10-AJ10-AK10) -> 94875 | AP10: =IF(E10=0,0,AF10-AG10-AH10) -> 15292.013 | AQ10: =IF(E10="","",+AF10/AI10) -> 0.16118063 | AR10: =IF(S10="",M10*E10,S10*E10) -> 20382.5 | AS10: =IFERROR((VLOOKUP(B10,'SUIVI 31.12.24 ALTONEO'!$B$1:$BF$38,45,FALSE())),0) -> 0 | AT10: =+AR10-AS10 -> 20382.5 | AU10: =+L10*E10 -> 1957.0375 | AV10: =IFERROR((VLOOKUP(B10,'SUIVI 31.12.24 ALTONEO'!$B$1:$BF$38,48,FALSE())),0) -> 0 | AW10: =+AU10-AV10 -> 1957.0375 | AX10: =IF(P10="",J10*E10,P10-Z10) -> 1897.5 | AY10: =IFERROR((VLOOKUP(B10,'SUIVI 31.12.24 ALTONEO'!$B$1:$BF$38,51,FALSE())),0) -> 0 | AZ10: =+AX10-AY10 -> 1897.5 | BA10: =IF(Q10="",K10*E10,Q10-AB10) -> 790.625 | BB10: =IFERROR((VLOOKUP(B10,'SUIVI 31.12.24 ALTONEO'!$B$1:$BF$38,54,FALSE())),0) -> 0 | BC10: =+BA10-BB10 -> 790.625 | BD10: =+E10*N10 -> 1500 | BE10: =IFERROR((VLOOKUP(B10,'SUIVI 31.12.24 ALTONEO'!$B$1:$BF$38,57,FALSE())),0) -> 0
B11: Projet Touati / Touati Fyé | C11: non | D11: 1.1 Administratif validé prêt à ouvrir | E11: =VLOOKUP(D11,'% avancement'!$A$4:$B$17,2,FALSE()) -> 0.25 | F11: 125416.67 | G11: 7500 | H11: =F11+G11-I11 -> 127916.67 | I11: 5000 | J11: =(F11+G11-I11)*0.06 -> 7675 | K11: =(F11+G11-I11)*0.025 -> 3197.9167 | L11: 7828.15 | M11: =(F11+G11)*0.62 -> 82408.333 | N11: 6000 | U11: =IF(C11="oui","",(H11+I11)*E11) -> 33229.167 | W11: =IF(O11="",0,(1-E11)*O11) -> 0 | X11: =IF(O11="",I11*(E11),0) -> 1250 | Y11: =IF(P11="",+H11*6%*E11,0) -> 1918.75 | Z11: =IF(P11="",0,P11*(1-E11)) -> 0 | AA11: =IF(Q11="",+H11*2.5%*E11,0) -> 799.47917 | AB11: =IF(Q11="",0,Q11*(1-E11)) -> 0 | AC11: =IF(R11="",+L11*E11,(1-E11)*R11) -> 1957.0375 | AD11: =IF(S11="",M11*E11,S11*E11) -> 20602.083 | AF11: =IF(E11="",0,+H11-J11-K11-L11-M11-N11) -> 20807.267 | AG11: =IFERROR((VLOOKUP(B11,'Suivi 31.12.25'!$B$1:$BF$38,33,FALSE())),0) -> 5201.8167 | AH11: =AF11*E11-AG11 -> 0 | AI11: =IF(E11="",0,H11) -> 127916.67 | AJ11: =IFERROR((VLOOKUP(B11,'Suivi 31.12.25'!$B$1:$BF$38,36,FALSE())),0) -> 31979.167 | AK11: =AI11*E11-AJ11 -> 0 | AO11: =IF(E11=0,0,AI11-AJ11-AK11) -> 95937.5 | AP11: =IF(E11=0,0,AF11-AG11-AH11) -> 15605.45 | AQ11: =IF(E11="","",+AF11/AI11) -> 0.16266267 | AR11: =IF(S11="",M11*E11,S11*E11) -> 20602.083 | AS11: =IFERROR((VLOOKUP(B11,'SUIVI 31.12.24 ALTONEO'!$B$1:$BF$38,45,FALSE())),0) -> 0 | AT11: =+AR11-AS11 -> 20602.083 | AU11: =+L11*E11 -> 1957.0375 | AV11: =IFERROR((VLOOKUP(B11,'SUIVI 31.12.24 ALTONEO'!$B$1:$BF$38,48,FALSE())),0) -> 0 | AW11: =+AU11-AV11 -> 1957.0375 | AX11: =IF(P11="",J11*E11,P11-Z11) -> 1918.75 | AY11: =IFERROR((VLOOKUP(B11,'SUIVI 31.12.24 ALTONEO'!$B$1:$BF$38,51,FALSE())),0) -> 0 | AZ11: =+AX11-AY11 -> 1918.75 | BA11: =IF(Q11="",K11*E11,Q11-AB11) -> 799.47917 | BB11: =IFERROR((VLOOKUP(B11,'SUIVI 31.12.24 ALTONEO'!$B$1:$BF$38,54,FALSE())),0) -> 0 | BC11: =+BA11-BB11 -> 799.47917 | BD11: =+E11*N11 -> 1500 | BE11: =IFERROR((VLOOKUP(B11,'SUIVI 31.12.24 ALTONEO'!$B$1:$BF$38,57,FALSE())),0) -> 0
B12: Projet Chevereau / Pichard Allonnes | C12: non | D12: 1.1 Administratif validé prêt à ouvrir | E12: =VLOOKUP(D12,'% avancement'!$A$4:$B$17,2,FALSE()) -> 0.25 | F12: 113166.67 | G12: 7500 | H12: =F12+G12-I12 -> 115666.67 | I12: 5000 | J12: =(F12+G12-I12)*0.06 -> 6940 | K12: =(F12+G12-I12)*0.025 -> 2891.6667 | L12: 7828.15 | M12: =(F12+G12)*0.62 -> 74813.333 | N12: 6000 | U12: =IF(C12="oui","",(H12+I12)*E12) -> 30166.667 | W12: =IF(O12="",0,(1-E12)*O12) -> 0 | X12: =IF(O12="",I12*(E12),0) -> 1250 | Y12: =IF(P12="",+H12*6%*E12,0) -> 1735 | Z12: =IF(P12="",0,P12*(1-E12)) -> 0 | AA12: =IF(Q12="",+H12*2.5%*E12,0) -> 722.91667 | AB12: =IF(Q12="",0,Q12*(1-E12)) -> 0 | AC12: =IF(R12="",+L12*E12,(1-E12)*R12) -> 1957.0375 | AD12: =IF(S12="",M12*E12,S12*E12) -> 18703.333 | AF12: =IF(E12="",0,+H12-J12-K12-L12-M12-N12) -> 17193.517 | AG12: =IFERROR((VLOOKUP(B12,'Suivi 31.12.25'!$B$1:$BF$38,33,FALSE())),0) -> 4298.3792 | AH12: =AF12*E12-AG12 -> 0 | AI12: =IF(E12="",0,H12) -> 115666.67 | AJ12: =IFERROR((VLOOKUP(B12,'Suivi 31.12.25'!$B$1:$BF$38,36,FALSE())),0) -> 28916.667 | AK12: =AI12*E12-AJ12 -> 0 | AO12: =IF(E12=0,0,AI12-AJ12-AK12) -> 86750 | AP12: =IF(E12=0,0,AF12-AG12-AH12) -> 12895.138 | AQ12: =IF(E12="","",+AF12/AI12) -> 0.14864712 | AR12: =IF(S12="",M12*E12,S12*E12) -> 18703.333 | AS12: =IFERROR((VLOOKUP(B12,'SUIVI 31.12.24 ALTONEO'!$B$1:$BF$38,45,FALSE())),0) -> 0 | AT12: =+AR12-AS12 -> 18703.333 | AU12: =+L12*E12 -> 1957.0375 | AV12: =IFERROR((VLOOKUP(B12,'SUIVI 31.12.24 ALTONEO'!$B$1:$BF$38,48,FALSE())),0) -> 0 | AW12: =+AU12-AV12 -> 1957.0375 | AX12: =IF(P12="",J12*E12,P12-Z12) -> 1735 | AY12: =IFERROR((VLOOKUP(B12,'SUIVI 31.12.24 ALTONEO'!$B$1:$BF$38,51,FALSE())),0) -> 0 | AZ12: =+AX12-AY12 -> 1735 | BA12: =IF(Q12="",K12*E12,Q12-AB12) -> 722.91667 | BB12: =IFERROR((VLOOKUP(B12,'SUIVI 31.12.24 ALTONEO'!$B$1:$BF$38,54,FALSE())),0) -> 0 | BC12: =+BA12-BB12 -> 722.91667 | BD12: =+E12*N12 -> 1500 | BE12: =IFERROR((VLOOKUP(B12,'SUIVI 31.12.24 ALTONEO'!$B$1:$BF$38,57,FALSE())),0) -> 0
B13: Projet Mançon / Ceton | C13: non | D13: 1.1 Administratif validé prêt à ouvrir | E13: =VLOOKUP(D13,'% avancement'!$A$4:$B$17,2,FALSE()) -> 0.25 | F13: 126583.33 | G13: 7500 | H13: =F13+G13-I13 -> 129083.33 | I13: 5000 | J13: =(F13+G13-I13)*0.06 -> 7745 | K13: =(F13+G13-I13)*0.025 -> 3227.0833 | L13: 7828.15 | M13: =(F13+G13)*0.62 -> 83131.667 | N13: 6000 | U13: =IF(C13="oui","",(H13+I13)*E13) -> 33520.833 | W13: =IF(O13="",0,(1-E13)*O13) -> 0 | X13: =IF(O13="",I13*(E13),0) -> 1250 | Y13: =IF(P13="",+H13*6%*E13,0) -> 1936.25 | Z13: =IF(P13="",0,P13*(1-E13)) -> 0 | AA13: =IF(Q13="",+H13*2.5%*E13,0) -> 806.77083 | AB13: =IF(Q13="",0,Q13*(1-E13)) -> 0 | AC13: =IF(R13="",+L13*E13,(1-E13)*R13) -> 1957.0375 | AD13: =IF(S13="",M13*E13,S13*E13) -> 20782.917 | AF13: =IF(E13="",0,+H13-J13-K13-L13-M13-N13) -> 21151.433 | AG13: =IFERROR((VLOOKUP(B13,'Suivi 31.12.25'!$B$1:$BF$38,33,FALSE())),0) -> 5287.8583 | AH13: =AF13*E13-AG13 -> 0 | AI13: =IF(E13="",0,H13) -> 129083.33 | AJ13: =IFERROR((VLOOKUP(B13,'Suivi 31.12.25'!$B$1:$BF$38,36,FALSE())),0) -> 32270.833 | AK13: =AI13*E13-AJ13 -> 0 | AO13: =IF(E13=0,0,AI13-AJ13-AK13) -> 96812.5 | AP13: =IF(E13=0,0,AF13-AG13-AH13) -> 15863.575 | AQ13: =IF(E13="","",+AF13/AI13) -> 0.16385875 | AR13: =IF(S13="",M13*E13,S13*E13) -> 20782.917 | AS13: =IFERROR((VLOOKUP(B13,'SUIVI 31.12.24 ALTONEO'!$B$1:$BF$38,45,FALSE())),0) -> 0 | AT13: =+AR13-AS13 -> 20782.917 | AU13: =+L13*E13 -> 1957.0375 | AV13: =IFERROR((VLOOKUP(B13,'SUIVI 31.12.24 ALTONEO'!$B$1:$BF$38,48,FALSE())),0) -> 0 | AW13: =+AU13-AV13 -> 1957.0375 | AX13: =IF(P13="",J13*E13,P13-Z13) -> 1936.25 | AY13: =IFERROR((VLOOKUP(B13,'SUIVI 31.12.24 ALTONEO'!$B$1:$BF$38,51,FALSE())),0) -> 0 | AZ13: =+AX13-AY13 -> 1936.25 | BA13: =IF(Q13="",K13*E13,Q13-AB13) -> 806.77083 | BB13: =IFERROR((VLOOKUP(B13,'SUIVI 31.12.24 ALTONEO'!$B$1:$BF$38,54,FALSE())),0) -> 0 | BC13: =+BA13-BB13 -> 806.77083 | BD13: =+E13*N13 -> 1500 | BE13: =IFERROR((VLOOKUP(B13,'SUIVI 31.12.24 ALTONEO'!$B$1:$BF$38,57,FALSE())),0) -> 0
B14: Projet Delaunay / Blet Vaas | C14: non | D14: 1.1 Administratif validé prêt à ouvrir | E14: =VLOOKUP(D14,'% avancement'!$A$4:$B$17,2,FALSE()) -> 0.25 | F14: 115583.33 | G14: 7500 | H14: =F14+G14-I14 -> 118083.33 | I14: 5000 | J14: =(F14+G14-I14)*0.06 -> 7085 | K14: =(F14+G14-I14)*0.025 -> 2952.0833 | L14: 7828.15 | M14: =(F14+G14)*0.62 -> 76311.667 | N14: 6000 | U14: =IF(C14="oui","",(H14+I14)*E14) -> 30770.833 | W14: =IF(O14="",0,(1-E14)*O14) -> 0 | X14: =IF(O14="",I14*(E14),0) -> 1250 | Y14: =IF(P14="",+H14*6%*E14,0) -> 1771.25 | Z14: =IF(P14="",0,P14*(1-E14)) -> 0 | AA14: =IF(Q14="",+H14*2.5%*E14,0) -> 738.02083 | AB14: =IF(Q14="",0,Q14*(1-E14)) -> 0 | AC14: =IF(R14="",+L14*E14,(1-E14)*R14) -> 1957.0375 | AD14: =IF(S14="",M14*E14,S14*E14) -> 19077.917 | AF14: =IF(E14="",0,+H14-J14-K14-L14-M14-N14) -> 17906.433 | AG14: =IFERROR((VLOOKUP(B14,'Suivi 31.12.25'!$B$1:$BF$38,33,FALSE())),0) -> 4476.6083 | AH14: =AF14*E14-AG14 -> 0 | AI14: =IF(E14="",0,H14) -> 118083.33 | AJ14: =IFERROR((VLOOKUP(B14,'Suivi 31.12.25'!$B$1:$BF$38,36,FALSE())),0) -> 29520.833 | AK14: =AI14*E14-AJ14 -> 0 | AO14: =IF(E14=0,0,AI14-AJ14-AK14) -> 88562.5 | AP14: =IF(E14=0,0,AF14-AG14-AH14) -> 13429.825 | AQ14: =IF(E14="","",+AF14/AI14) -> 0.15164234 | AR14: =IF(S14="",M14*E14,S14*E14) -> 19077.917 | AS14: =IFERROR((VLOOKUP(B14,'SUIVI 31.12.24 ALTONEO'!$B$1:$BF$38,45,FALSE())),0) -> 0 | AT14: =+AR14-AS14 -> 19077.917 | AU14: =+L14*E14 -> 1957.0375 | AV14: =IFERROR((VLOOKUP(B14,'SUIVI 31.12.24 ALTONEO'!$B$1:$BF$38,48,FALSE())),0) -> 0 | AW14: =+AU14-AV14 -> 1957.0375 | AX14: =IF(P14="",J14*E14,P14-Z14) -> 1771.25 | AY14: =IFERROR((VLOOKUP(B14,'SUIVI 31.12.24 ALTONEO'!$B$1:$BF$38,51,FALSE())),0) -> 0 | AZ14: =+AX14-AY14 -> 1771.25 | BA14: =IF(Q14="",K14*E14,Q14-AB14) -> 738.02083 | BB14: =IFERROR((VLOOKUP(B14,'SUIVI 31.12.24 ALTONEO'!$B$1:$BF$38,54,FALSE())),0) -> 0 | BC14: =+BA14-BB14 -> 738.02083 | BD14: =+E14*N14 -> 1500 | BE14: =IFERROR((VLOOKUP(B14,'SUIVI 31.12.24 ALTONEO'!$B$1:$BF$38,57,FALSE())),0) -> 0
B15: Projet Partaud / Partaud Mulsanne | C15: non | D15: 6. Mise hors d'eau | E15: =VLOOKUP(D15,'% avancement'!$A$4:$B$17,2,FALSE()) -> 0.8 | F15: 108166.67 | G15: 9098.33 | H15: =F15+G15-I15 -> 112265 | I15: 5000 | J15: 7297.23 | K15: 2806.63 | L15: 7828.15 | M15: 71608.43 | N15: 6000 | O15: 5000 | P15: 7297.23 | Q15: 2806.63 | R15: 7828.15 | S15: =M15 -> 71608.43 | T15: 6000 | U15: =IF(C15="oui","",(H15+I15)*E15) -> 93812 | W15: =IF(O15="",0,(1-E15)*O15) -> 1000 | X15: =IF(O15="",I15*(E15),0) -> 0 | Y15: =IF(P15="",+H15*6%*E15,0) -> 0 | Z15: =IF(P15="",0,P15*(1-E15)) -> 1459.446 | AA15: =IF(Q15="",+H15*2.5%*E15,0) -> 0 | AB15: =IF(Q15="",0,Q15*(1-E15)) -> 561.326 | AC15: =IF(R15="",+L15*E15,(1-E15)*R15) -> 1565.63 | AD15: =IF(S15="",M15*E15,S15*E15) -> 57286.744 | AF15: =IF(E15="",0,+H15-J15-K15-L15-M15-N15) -> 16724.56 | AG15: =IFERROR((VLOOKUP(B15,'Suivi 31.12.25'!$B$1:$BF$38,33,FALSE())),0) -> 6609.824 | AH15: =AF15*E15-AG15 -> 6769.824 | AI15: =IF(E15="",0,H15) -> 112265 | AJ15: =IFERROR((VLOOKUP(B15,'Suivi 31.12.25'!$B$1:$BF$38,36,FALSE())),0) -> 44906 | AK15: =AI15*E15-AJ15 -> 44906 | AO15: =IF(E15=0,0,AI15-AJ15-AK15) -> 22453 | AP15: =IF(E15=0,0,AF15-AG15-AH15) -> 3344.912 | AQ15: =IF(E15="","",+AF15/AI15) -> 0.14897395 | AR15: =IF(S15="",M15*E15,S15*E15) -> 57286.744 | AS15: =IFERROR((VLOOKUP(B15,'SUIVI 31.12.24 ALTONEO'!$B$1:$BF$38,45,FALSE())),0) -> 0 | AT15: =+AR15-AS15 -> 57286.744 | AU15: =+L15*E15 -> 6262.52 | AV15: =IFERROR((VLOOKUP(B15,'SUIVI 31.12.24 ALTONEO'!$B$1:$BF$38,48,FALSE())),0) -> 0 | AW15: =+AU15-AV15 -> 6262.52 | AX15: =IF(P15="",J15*E15,P15-Z15) -> 5837.784 | AY15: =IFERROR((VLOOKUP(B15,'SUIVI 31.12.24 ALTONEO'!$B$1:$BF$38,51,FALSE())),0) -> 0 | AZ15: =+AX15-AY15 -> 5837.784 | BA15: =IF(Q15="",K15*E15,Q15-AB15) -> 2245.304 | BB15: =IFERROR((VLOOKUP(B15,'SUIVI 31.12.24 ALTONEO'!$B$1:$BF$38,54,FALSE())),0) -> 0 | BC15: =+BA15-BB15 -> 2245.304 | BD15: =+E15*N15 -> 4800 | BE15: =IFERROR((VLOOKUP(B15,'SUIVI 31.12.24 ALTONEO'!$B$1:$BF$38,57,FALSE())),0) -> 0
B16: Projet Protin / Subranne St Jean de la Motte | C16: non | D16: 6. Mise hors d'eau | E16: =VLOOKUP(D16,'% avancement'!$A$5:$B$17,2,FALSE()) -> 0.8 | F16: 148500 | G16: 8587.5 | H16: =F16+G16-I16 -> 152087.5 | I16: 5000 | J16: 9885.69 | K16: 3802.19 | L16: 7828.15 | M16: 102704.28 | N16: 6000 | O16: 5000 | P16: 9885.6917 | Q16: 3802.1917 | R16: 7828.15 | S16: =M16 -> 102704.28 | T16: 6000 | U16: =IF(C16="oui","",(H16+I16)*E16) -> 125670 | W16: =IF(O16="",0,(1-E16)*O16) -> 1000 | X16: =IF(O16="",I16*(E16),0) -> 0 | Y16: =IF(P16="",+H16*6%*E16,0) -> 0 | Z16: =IF(P16="",0,P16*(1-E16)) -> 1977.1383 | AA16: =IF(Q16="",+H16*2.5%*E16,0) -> 0 | AB16: =IF(Q16="",0,Q16*(1-E16)) -> 760.43833 | AC16: =IF(R16="",+L16*E16,(1-E16)*R16) -> 1565.63 | AD16: =IF(S16="",M16*E16,S16*E16) -> 82163.424 | AF16: =IF(E16="",0,+H16-J16-K16-L16-M16-N16) -> 21867.19 | AG16: =IFERROR((VLOOKUP(B16,'Suivi 31.12.25'!$B$1:$BF$38,33,FALSE())),0) -> 13045.24 | AH16: =AF16*E16-AG16 -> 4448.512 | AI16: =IF(E16="",0,H16) -> 152087.5 | AJ16: =IFERROR((VLOOKUP(B16,'Suivi 31.12.25'!$B$1:$BF$38,36,FALSE())),0) -> 91252.5 | AK16: =AI16*E16-AJ16 -> 30417.5 | AO16: =IF(E16=0,0,AI16-AJ16-AK16) -> 30417.5 | AP16: =IF(E16=0,0,AF16-AG16-AH16) -> 4373.438 | AQ16: =IF(E16="","",+AF16/AI16) -> 0.14378032 | AR16: =IF(S16="",M16*E16,S16*E16) -> 82163.424 | AS16: =IFERROR((VLOOKUP(B16,'SUIVI 31.12.24 ALTONEO'!$B$1:$BF$38,45,FALSE())),0) -> 0 | AT16: =+AR16-AS16 -> 82163.424 | AU16: =+L16*E16 -> 6262.52 | AV16: =IFERROR((VLOOKUP(B16,'SUIVI 31.12.24 ALTONEO'!$B$1:$BF$38,48,FALSE())),0) -> 0 | AW16: =+AU16-AV16 -> 6262.52 | AX16: =IF(P16="",J16*E16,P16-Z16) -> 7908.5533 | AY16: =IFERROR((VLOOKUP(B16,'SUIVI 31.12.24 ALTONEO'!$B$1:$BF$38,51,FALSE())),0) -> 0 | AZ16: =+AX16-AY16 -> 7908.5533 | BA16: =IF(Q16="",K16*E16,Q16-AB16) -> 3041.7533 | BB16: =IFERROR((VLOOKUP(B16,'SUIVI 31.12.24 ALTONEO'!$B$1:$BF$38,54,FALSE())),0) -> 0 | BC16: =+BA16-BB16 -> 3041.7533 | BD16: =+E16*N16 -> 4800 | BE16: =IFERROR((VLOOKUP(B16,'SUIVI 31.12.24 ALTONEO'!$B$1:$BF$38,57,FALSE())),0) -> 0
B17: Projet Chafiol / Chafiol Ecommoy | C17: non | D17: 9. Réception | E17: =VLOOKUP(D17,'% avancement'!$A$5:$B$17,2,FALSE()) -> 1 | F17: 121500 | G17: 10128.33 | H17: =F17+G17-I17 -> 126628.33 | I17: 5000 | J17: 8149.59 | K17: 3134.46 | L17: 7828.15 | M17: 72850.86 | N17: 6000 | O17: 5000 | P17: =J17 -> 8149.59 | Q17: =K17 -> 3134.46 | R17: =L17 -> 7828.15 | S17: =M17 -> 72850.86 | T17: 6000 | U17: =IF(C17="oui","",(H17+I17)*E17) -> 131628.33 | W17: =IF(O17="",0,(1-E17)*O17) -> 0 | X17: =IF(O17="",I17*(E17),0) -> 0 | Y17: =IF(P17="",+H17*6%*E17,0) -> 0 | Z17: =IF(P17="",0,P17*(1-E17)) -> 0 | AA17: =IF(Q17="",+H17*2.5%*E17,0) -> 0 | AB17: =IF(Q17="",0,Q17*(1-E17)) -> 0 | AC17: =IF(R17="",+L17*E17,(1-E17)*R17) -> 0 | AD17: =IF(S17="",M17*E17,S17*E17) -> 72850.86 | AF17: =IF(E17="",0,+H17-J17-K17-L17-M17-N17) -> 28665.27 | AG17: =IFERROR((VLOOKUP(B17,'Suivi 31.12.25'!$B$1:$BF$38,33,FALSE())),0) -> 21849.371 | AH17: =AF17*E17-AG17 -> 6815.8993 | AI17: =IF(E17="",0,H17) -> 126628.33 | AJ17: =IFERROR((VLOOKUP(B17,'Suivi 31.12.25'!$B$1:$BF$38,36,FALSE())),0) -> 100302.67 | AK17: =AI17*E17-AJ17 -> 26325.663 | AO17: =IF(E17=0,0,AI17-AJ17-AK17) -> 0 | AP17: =IF(E17=0,0,AF17-AG17-AH17) -> 0 | AQ17: =IF(E17="","",+AF17/AI17) -> 0.22637328 | AR17: =IF(S17="",M17*E17,S17*E17) -> 72850.86 | AS17: =IFERROR((VLOOKUP(B17,'SUIVI 31.12.24 ALTONEO'!$B$1:$BF$38,45,FALSE())),0) -> 0 | AT17: =+AR17-AS17 -> 72850.86 | AU17: =+L17*E17 -> 7828.15 | AV17: =IFERROR((VLOOKUP(B17,'SUIVI 31.12.24 ALTONEO'!$B$1:$BF$38,48,FALSE())),0) -> 0 | AW17: =+AU17-AV17 -> 7828.15 | AX17: =IF(P17="",J17*E17,P17-Z17) -> 8149.59 | AY17: =IFERROR((VLOOKUP(B17,'SUIVI 31.12.24 ALTONEO'!$B$1:$BF$38,51,FALSE())),0) -> 0 | AZ17: =+AX17-AY17 -> 8149.59 | BA17: =IF(Q17="",K17*E17,Q17-AB17) -> 3134.46 | BB17: =IFERROR((VLOOKUP(B17,'SUIVI 31.12.24 ALTONEO'!$B$1:$BF$38,54,FALSE())),0) -> 0 | BC17: =+BA17-BB17 -> 3134.46 | BD17: =+E17*N17 -> 6000 | BE17: =IFERROR((VLOOKUP(B17,'SUIVI 31.12.24 ALTONEO'!$B$1:$BF$38,57,FALSE())),0) -> 0
B18: Projet Bigaret / Cheniour St Jean de la Motte | C18: non | D18: 6. Mise hors d'eau | E18: =VLOOKUP(D18,'% avancement'!$A$5:$B$17,2,FALSE()) -> 0.8 | F18: 129333.33 | G18: 8556.67 | H18: =F18+G18-I18 -> 132890 | I18: 5000 | J18: 8637.85 | K18: 3322.25 | L18: 7828.15 | M18: 84311.97 | N18: 6000 | O18: 5000 | P18: =10365.42/1.2 -> 8637.85 | Q18: =3986.7/1.2 -> 3322.25 | R18: 7828.15 | S18: =M18 -> 84311.97 | T18: 6000 | U18: =IF(C18="oui","",(H18+I18)*E18) -> 110312 | W18: =IF(O18="",0,(1-E18)*O18) -> 1000 | X18: =IF(O18="",I18*(E18),0) -> 0 | Y18: =IF(P18="",+H18*6%*E18,0) -> 0 | Z18: =IF(P18="",0,P18*(1-E18)) -> 1727.57 | AA18: =IF(Q18="",+H18*2.5%*E18,0) -> 0 | AB18: =IF(Q18="",0,Q18*(1-E18)) -> 664.45 | AC18: =IF(R18="",+L18*E18,(1-E18)*R18) -> 1565.63 | AD18: =IF(S18="",M18*E18,S18*E18) -> 67449.576 | AF18: =IF(E18="",0,+H18-J18-K18-L18-M18-N18) -> 22789.78 | AG18: =IFERROR((VLOOKUP(B18,'Suivi 31.12.25'!$B$1:$BF$38,33,FALSE())),0) -> 13673.868 | AH18: =AF18*E18-AG18 -> 4557.956 | AI18: =IF(E18="",0,H18) -> 132890 | AJ18: =IFERROR((VLOOKUP(B18,'Suivi 31.12.25'!$B$1:$BF$38,36,FALSE())),0) -> 79734 | AK18: =AI18*E18-AJ18 -> 26578 | AO18: =IF(E18=0,0,AI18-AJ18-AK18) -> 26578 | AP18: =IF(E18=0,0,AF18-AG18-AH18) -> 4557.956 | AQ18: =IF(E18="","",+AF18/AI18) -> 0.17149357 | AR18: =IF(S18="",M18*E18,S18*E18) -> 67449.576 | AS18: =IFERROR((VLOOKUP(B18,'SUIVI 31.12.24 ALTONEO'!$B$1:$BF$38,45,FALSE())),0) -> 0 | AT18: =+AR18-AS18 -> 67449.576 | AU18: =+L18*E18 -> 6262.52 | AV18: =IFERROR((VLOOKUP(B18,'SUIVI 31.12.24 ALTONEO'!$B$1:$BF$38,48,FALSE())),0) -> 0 | AW18: =+AU18-AV18 -> 6262.52 | AX18: =IF(P18="",J18*E18,P18-Z18) -> 6910.28 | AY18: =IFERROR((VLOOKUP(B18,'SUIVI 31.12.24 ALTONEO'!$B$1:$BF$38,51,FALSE())),0) -> 0 | AZ18: =+AX18-AY18 -> 6910.28 | BA18: =IF(Q18="",K18*E18,Q18-AB18) -> 2657.8 | BB18: =IFERROR((VLOOKUP(B18,'SUIVI 31.12.24 ALTONEO'!$B$1:$BF$38,54,FALSE())),0) -> 0 | BC18: =+BA18-BB18 -> 2657.8 | BD18: =+E18*N18 -> 4800 | BE18: =IFERROR((VLOOKUP(B18,'SUIVI 31.12.24 ALTONEO'!$B$1:$BF$38,57,FALSE())),0) -> 0
B19: Projet VIPA Immo / Allonnes | C19: non | D19: 1.1 Administratif validé prêt à ouvrir | E19: =VLOOKUP(D19,'% avancement'!$A$5:$B$17,2,FALSE()) -> 0.25 | F19: =133500/1.2 -> 111250 | G19: =8900/1.2 -> 7416.6667 | H19: =F19+G19-I19 -> 118666.67 | I19: 0 | J19: 7713.33 | K19: 2966.66 | L19: 8062.99 | M19: 92253.04 | N19: 3800 | O19: 0 | P19: =J19 -> 7713.33 | Q19: =K19 -> 2966.66 | R19: =L19 -> 8062.99 | S19: =M19 -> 92253.04 | T19: 3800 | U19: =IF(C19="oui","",(H19+I19)*E19) -> 29666.667 | W19: =IF(O19="",0,(1-E19)*O19) -> 0 | X19: =IF(O19="",I19*(E19),0) -> 0 | Y19: =IF(P19="",+H19*6%*E19,0) -> 0 | Z19: =IF(P19="",0,P19*(1-E19)) -> 5784.9975 | AA19: =IF(Q19="",+H19*2.5%*E19,0) -> 0 | AB19: =IF(Q19="",0,Q19*(1-E19)) -> 2224.995 | AC19: =IF(R19="",+L19*E19,(1-E19)*R19) -> 6047.2425 | AD19: =IF(S19="",M19*E19,S19*E19) -> 23063.26 | AF19: =IF(E19="",0,+H19-J19-K19-L19-M19-N19) -> 3870.6467 | AG19: =IFERROR((VLOOKUP(B19,'Suivi 31.12.25'!$B$1:$BF$38,33,FALSE())),0) -> 0 | AH19: =AF19*E19-AG19 -> 967.66167 | AI19: =IF(E19="",0,H19) -> 118666.67 | AJ19: =IFERROR((VLOOKUP(B19,'Suivi 31.12.25'!$B$1:$BF$38,36,FALSE())),0) -> 0 | AK19: =AI19*E19-AJ19 -> 29666.667 | AO19: =IF(E19=0,0,AI19-AJ19-AK19) -> 89000 | AP19: =IF(E19=0,0,AF19-AG19-AH19) -> 2902.985 | AQ19: =IF(E19="","",+AF19/AI19) -> 0.032617809 | AR19: =IF(S19="",M19*E19,S19*E19) -> 23063.26 | AS19: =IFERROR((VLOOKUP(B19,'SUIVI 31.12.24 ALTONEO'!$B$1:$BF$38,45,FALSE())),0) -> 0 | AT19: =+AR19-AS19 -> 23063.26 | AU19: =+L19*E19 -> 2015.7475 | AV19: =IFERROR((VLOOKUP(B19,'SUIVI 31.12.24 ALTONEO'!$B$1:$BF$38,48,FALSE())),0) -> 0 | AW19: =+AU19-AV19 -> 2015.7475 | AX19: =IF(P19="",J19*E19,P19-Z19) -> 1928.3325 | AY19: =IFERROR((VLOOKUP(B19,'SUIVI 31.12.24 ALTONEO'!$B$1:$BF$38,51,FALSE())),0) -> 0 | AZ19: =+AX19-AY19 -> 1928.3325 | BA19: =IF(Q19="",K19*E19,Q19-AB19) -> 741.665 | BB19: =IFERROR((VLOOKUP(B19,'SUIVI 31.12.24 ALTONEO'!$B$1:$BF$38,54,FALSE())),0) -> 0 | BC19: =+BA19-BB19 -> 741.665 | BD19: =+E19*N19 -> 950 | BE19: =IFERROR((VLOOKUP(B19,'SUIVI 31.12.24 ALTONEO'!$B$1:$BF$38,57,FALSE())),0) -> 0
B20: Projet Cardoso / Ryckewaert Epuisay | C20: non | D20: 6. Mise hors d'eau | E20: =VLOOKUP(D20,'% avancement'!$A$5:$B$17,2,FALSE()) -> 0.8 | F20: 127750 | G20: 11092.5 | H20: =F20+G20-I20 -> 133842.5 | I20: 5000 | J20: 8659.14 | K20: 3330.44 | L20: 7828.15 | M20: 83839.7 | N20: 6000 | O20: 5000 | P20: =J20 -> 8659.14 | Q20: =K20 -> 3330.44 | R20: =L20 -> 7828.15 | S20: =M20 -> 83839.7 | T20: 6000 | U20: =IF(C20="oui","",(H20+I20)*E20) -> 111074 | W20: =IF(O20="",0,(1-E20)*O20) -> 1000 | X20: =IF(O20="",I20*(E20),0) -> 0 | Y20: =IF(P20="",+H20*6%*E20,0) -> 0 | Z20: =IF(P20="",0,P20*(1-E20)) -> 1731.828 | AA20: =IF(Q20="",+H20*2.5%*E20,0) -> 0 | AB20: =IF(Q20="",0,Q20*(1-E20)) -> 666.088 | AC20: =IF(R20="",+L20*E20,(1-E20)*R20) -> 1565.63 | AD20: =IF(S20="",M20*E20,S20*E20) -> 67071.76 | AF20: =IF(E20="",0,+H20-J20-K20-L20-M20-N20) -> 24185.07 | AG20: =IFERROR((VLOOKUP(B20,'Suivi 31.12.25'!$B$1:$BF$38,33,FALSE())),0) -> 14798.082 | AH20: =AF20*E20-AG20 -> 4549.974 | AI20: =IF(E20="",0,H20) -> 133842.5 | AJ20: =IFERROR((VLOOKUP(B20,'Suivi 31.12.25'!$B$1:$BF$38,36,FALSE())),0) -> 79930.5 | AK20: =AI20*E20-AJ20 -> 27143.5 | AO20: =IF(E20=0,0,AI20-AJ20-AK20) -> 26768.5 | AP20: =IF(E20=0,0,AF20-AG20-AH20) -> 4837.014 | AQ20: =IF(E20="","",+AF20/AI20) -> 0.18069798 | AR20: =IF(S20="",M20*E20,S20*E20) -> 67071.76 | AS20: =IFERROR((VLOOKUP(B20,'SUIVI 31.12.24 ALTONEO'!$B$1:$BF$38,45,FALSE())),0) -> 0 | AT20: =+AR20-AS20 -> 67071.76 | AU20: =+L20*E20 -> 6262.52 | AV20: =IFERROR((VLOOKUP(B20,'SUIVI 31.12.24 ALTONEO'!$B$1:$BF$38,48,FALSE())),0) -> 0 | AW20: =+AU20-AV20 -> 6262.52 | AX20: =IF(P20="",J20*E20,P20-Z20) -> 6927.312 | AY20: =IFERROR((VLOOKUP(B20,'SUIVI 31.12.24 ALTONEO'!$B$1:$BF$38,51,FALSE())),0) -> 0 | AZ20: =+AX20-AY20 -> 6927.312 | BA20: =IF(Q20="",K20*E20,Q20-AB20) -> 2664.352 | BB20: =IFERROR((VLOOKUP(B20,'SUIVI 31.12.24 ALTONEO'!$B$1:$BF$38,54,FALSE())),0) -> 0 | BC20: =+BA20-BB20 -> 2664.352 | BD20: =+E20*N20 -> 4800 | BE20: =IFERROR((VLOOKUP(B20,'SUIVI 31.12.24 ALTONEO'!$B$1:$BF$38,57,FALSE())),0) -> 0
B21: Projet Journaux / Thinard Meurcé | C21: non | D21: 5. Achèvement des murs | E21: =VLOOKUP(D21,'% avancement'!$A$5:$B$17,2,FALSE()) -> 0.6 | F21: 116416.67 | G21: 20345 | H21: =F21+G21-I21 -> 131761.67 | I21: 5000 | J21: 8564.51 | K21: 3294.04 | L21: 7828.15 | M21: 82927.75 | N21: 6000 | O21: 5000 | P21: 8564.5083 | Q21: 3294.0417 | R21: 7828.15 | S21: =M21 -> 82927.75 | T21: 6000 | U21: =IF(C21="oui","",(H21+I21)*E21) -> 82057.002 | W21: =IF(O21="",0,(1-E21)*O21) -> 2000 | X21: =IF(O21="",I21*(E21),0) -> 0 | Y21: =IF(P21="",+H21*6%*E21,0) -> 0 | Z21: =IF(P21="",0,P21*(1-E21)) -> 3425.8033 | AA21: =IF(Q21="",+H21*2.5%*E21,0) -> 0 | AB21: =IF(Q21="",0,Q21*(1-E21)) -> 1317.6167 | AC21: =IF(R21="",+L21*E21,(1-E21)*R21) -> 3131.26 | AD21: =IF(S21="",M21*E21,S21*E21) -> 49756.65 | AF21: =IF(E21="",0,+H21-J21-K21-L21-M21-N21) -> 23147.22 | AG21: =IFERROR((VLOOKUP(B21,'Suivi 31.12.25'!$B$1:$BF$38,33,FALSE())),0) -> 14388.61 | AH21: =AF21*E21-AG21 -> -500.278 | AI21: =IF(E21="",0,H21) -> 131761.67 | AJ21: =IFERROR((VLOOKUP(B21,'Suivi 31.12.25'!$B$1:$BF$38,36,FALSE())),0) -> 79057 | AK21: =AI21*E21-AJ21 -> 0.001998 | AO21: =IF(E21=0,0,AI21-AJ21-AK21) -> 52704.668 | AP21: =IF(E21=0,0,AF21-AG21-AH21) -> 9258.888 | AQ21: =IF(E21="","",+AF21/AI21) -> 0.17567491 | AR21: =IF(S21="",M21*E21,S21*E21) -> 49756.65 | AS21: =IFERROR((VLOOKUP(B21,'SUIVI 31.12.24 ALTONEO'!$B$1:$BF$38,45,FALSE())),0) -> 0 | AT21: =+AR21-AS21 -> 49756.65 | AU21: =+L21*E21 -> 4696.89 | AV21: =IFERROR((VLOOKUP(B21,'SUIVI 31.12.24 ALTONEO'!$B$1:$BF$38,48,FALSE())),0) -> 0 | AW21: =+AU21-AV21 -> 4696.89 | AX21: =IF(P21="",J21*E21,P21-Z21) -> 5138.705 | AY21: =IFERROR((VLOOKUP(B21,'SUIVI 31.12.24 ALTONEO'!$B$1:$BF$38,51,FALSE())),0) -> 0 | AZ21: =+AX21-AY21 -> 5138.705 | BA21: =IF(Q21="",K21*E21,Q21-AB21) -> 1976.425 | BB21: =IFERROR((VLOOKUP(B21,'SUIVI 31.12.24 ALTONEO'!$B$1:$BF$38,54,FALSE())),0) -> 0 | BC21: =+BA21-BB21 -> 1976.425 | BD21: =+E21*N21 -> 3600 | BE21: =IFERROR((VLOOKUP(B21,'SUIVI 31.12.24 ALTONEO'!$B$1:$BF$38,57,FALSE())),0) -> 0
B22: Projet Moreau / Moreau Montfort Le Gesnois | C22: non | D22: 6. Mise hors d'eau | E22: =VLOOKUP(D22,'% avancement'!$A$5:$B$17,2,FALSE()) -> 0.8 | F22: 142333.33 | G22: 9400 | H22: =F22+G22-I22 -> 146733.33 | I22: 5000 | J22: 9537.67 | K22: 3668.33 | L22: 7828.15 | M22: 97088.35 | N22: 6000 | O22: 5000 | P22: 9537.6667 | Q22: 3668.3333 | R22: 7828.15 | S22: =M22 -> 97088.35 | T22: 6000 | U22: =IF(C22="oui","",(H22+I22)*E22) -> 121386.66 | W22: =IF(O22="",0,(1-E22)*O22) -> 1000 | X22: =IF(O22="",I22*(E22),0) -> 0 | Y22: =IF(P22="",+H22*6%*E22,0) -> 0 | Z22: =IF(P22="",0,P22*(1-E22)) -> 1907.5333 | AA22: =IF(Q22="",+H22*2.5%*E22,0) -> 0 | AB22: =IF(Q22="",0,Q22*(1-E22)) -> 733.66667 | AC22: =IF(R22="",+L22*E22,(1-E22)*R22) -> 1565.63 | AD22: =IF(S22="",M22*E22,S22*E22) -> 77670.68 | AF22: =IF(E22="",0,+H22-J22-K22-L22-M22-N22) -> 22610.83 | AG22: =IFERROR((VLOOKUP(B22,'Suivi 31.12.25'!$B$1:$BF$38,33,FALSE())),0) -> 9864.28 | AH22: =AF22*E22-AG22 -> 8224.384 | AI22: =IF(E22="",0,H22) -> 146733.33 | AJ22: =IFERROR((VLOOKUP(B22,'Suivi 31.12.25'!$B$1:$BF$38,36,FALSE())),0) -> 58693.2 | AK22: =AI22*E22-AJ22 -> 58693.464 | AO22: =IF(E22=0,0,AI22-AJ22-AK22) -> 29346.666 | AP22: =IF(E22=0,0,AF22-AG22-AH22) -> 4522.166 | AQ22: =IF(E22="","",+AF22/AI22) -> 0.15409471 | AR22: =IF(S22="",M22*E22,S22*E22) -> 77670.68 | AS22: =IFERROR((VLOOKUP(B22,'SUIVI 31.12.24 ALTONEO'!$B$1:$BF$38,45,FALSE())),0) -> 0 | AT22: =+AR22-AS22 -> 77670.68 | AU22: =+L22*E22 -> 6262.52 | AV22: =IFERROR((VLOOKUP(B22,'SUIVI 31.12.24 ALTONEO'!$B$1:$BF$38,48,FALSE())),0) -> 0 | AW22: =+AU22-AV22 -> 6262.52 | AX22: =IF(P22="",J22*E22,P22-Z22) -> 7630.1333 | AY22: =IFERROR((VLOOKUP(B22,'SUIVI 31.12.24 ALTONEO'!$B$1:$BF$38,51,FALSE())),0) -> 0 | AZ22: =+AX22-AY22 -> 7630.1333 | BA22: =IF(Q22="",K22*E22,Q22-AB22) -> 2934.6667 | BB22: =IFERROR((VLOOKUP(B22,'SUIVI 31.12.24 ALTONEO'!$B$1:$BF$38,54,FALSE())),0) -> 0 | BC22: =+BA22-BB22 -> 2934.6667 | BD22: =+E22*N22 -> 4800 | BE22: =IFERROR((VLOOKUP(B22,'SUIVI 31.12.24 ALTONEO'!$B$1:$BF$38,57,FALSE())),0) -> 0
B23: Projet Toin / Brault Saint Remy De Sillé | C23: non | D23: 5. Achèvement des murs | E23: =VLOOKUP(D23,'% avancement'!$A$5:$B$17,2,FALSE()) -> 0.6 | F23: 109333.33 | G23: 12078.33 | H23: =F23+G23-I23 -> 116411.66 | I23: 5000 | J23: 7566.76 | K23: 2910.29 | L23: 8062.99 | M23: 70311.97 | N23: 6000 | O23: 5000 | P23: =J23 -> 7566.76 | Q23: =K23 -> 2910.29 | R23: =L23 -> 8062.99 | S23: =M23 -> 70311.97 | T23: 6000 | U23: =IF(C23="oui","",(H23+I23)*E23) -> 72846.996 | W23: =IF(O23="",0,(1-E23)*O23) -> 2000 | X23: =IF(O23="",I23*(E23),0) -> 0 | Y23: =IF(P23="",+H23*6%*E23,0) -> 0 | Z23: =IF(P23="",0,P23*(1-E23)) -> 3026.704 | AA23: =IF(Q23="",+H23*2.5%*E23,0) -> 0 | AB23: =IF(Q23="",0,Q23*(1-E23)) -> 1164.116 | AC23: =IF(R23="",+L23*E23,(1-E23)*R23) -> 3225.196 | AD23: =IF(S23="",M23*E23,S23*E23) -> 42187.182 | AF23: =IF(E23="",0,+H23-J23-K23-L23-M23-N23) -> 21559.65 | AG23: =IFERROR((VLOOKUP(B23,'Suivi 31.12.25'!$B$1:$BF$38,33,FALSE())),0) -> 5561.0992 | AH23: =AF23*E23-AG23 -> 7374.6908 | AI23: =IF(E23="",0,H23) -> 116411.66 | AJ23: =IFERROR((VLOOKUP(B23,'Suivi 31.12.25'!$B$1:$BF$38,36,FALSE())),0) -> 29102.917 | AK23: =AI23*E23-AJ23 -> 40744.079 | AO23: =IF(E23=0,0,AI23-AJ23-AK23) -> 46564.664 | AP23: =IF(E23=0,0,AF23-AG23-AH23) -> 8623.86 | AQ23: =IF(E23="","",+AF23/AI23) -> 0.18520181 | AR23: =IF(S23="",M23*E23,S23*E23) -> 42187.182 | AS23: =IFERROR((VLOOKUP(B23,'SUIVI 31.12.24 ALTONEO'!$B$1:$BF$38,45,FALSE())),0) -> 0 | AT23: =+AR23-AS23 -> 42187.182 | AU23: =+L23*E23 -> 4837.794 | AV23: =IFERROR((VLOOKUP(B23,'SUIVI 31.12.24 ALTONEO'!$B$1:$BF$38,48,FALSE())),0) -> 0 | AW23: =+AU23-AV23 -> 4837.794 | AX23: =IF(P23="",J23*E23,P23-Z23) -> 4540.056 | AY23: =IFERROR((VLOOKUP(B23,'SUIVI 31.12.24 ALTONEO'!$B$1:$BF$38,51,FALSE())),0) -> 0 | AZ23: =+AX23-AY23 -> 4540.056 | BA23: =IF(Q23="",K23*E23,Q23-AB23) -> 1746.174 | BB23: =IFERROR((VLOOKUP(B23,'SUIVI 31.12.24 ALTONEO'!$B$1:$BF$38,54,FALSE())),0) -> 0 | BC23: =+BA23-BB23 -> 1746.174 | BD23: =+E23*N23 -> 3600 | BE23: =IFERROR((VLOOKUP(B23,'SUIVI 31.12.24 ALTONEO'!$B$1:$BF$38,57,FALSE())),0) -> 0
B24: =+ROWS(B3:B23) -> 21 | AO24: =IF(E24=0,0,AI24-AJ24-AK24) -> 0 | AP24: =IF(E24=0,0,AF24-AG24-AH24) -> 0
B25: Projet Ikia / La Ferté Bernard | C25: non | D25: 5. Achèvement des murs | E25: =VLOOKUP(D25,'% avancement'!$A$5:$B$17,2,FALSE()) -> 0.6 | F25: 98333.33 | G25: 6287.5 | H25: =F25+G25-I25 -> 99620.83 | I25: 5000 | J25: 6475.35 | K25: 2490.52 | L25: 8062.99 | M25: 59029.86 | N25: 6000 | O25: 5000 | T25: 6000 | U25: =IF(C25="oui","",(H25+I25)*E25) -> 62772.498 | W25: =IF(O25="",0,(1-E25)*O25) -> 2000 | X25: =IF(O25="",I25*(E25),0) -> 0 | Y25: =IF(P25="",+H25*6%*E25,0) -> 3586.3499 | Z25: =IF(P25="",0,P25*(1-E25)) -> 0 | AA25: =IF(Q25="",+H25*2.5%*E25,0) -> 1494.3125 | AB25: =IF(Q25="",0,Q25*(1-E25)) -> 0 | AC25: =IF(R25="",+L25*E25,(1-E25)*R25) -> 4837.794 | AD25: =IF(S25="",M25*E25,S25*E25) -> 35417.916 | AF25: =IF(E25="",0,+H25-J25-K25-L25-M25-N25) -> 17562.11 | AG25: =IFERROR((VLOOKUP(B25,'Suivi 31.12.25'!$B$1:$BF$38,33,FALSE())),0) -> 0 | AH25: =AF25*E25-AG25 -> 10537.266 | AI25: =IF(E25="",0,H25) -> 99620.83 | AJ25: =IFERROR((VLOOKUP(B25,'Suivi 31.12.25'!$B$40:$BF$50,36,FALSE())),0) -> 24905.208 | AK25: =AI25*E25-AJ25 -> 34867.29 | AO25: =IF(E25=0,0,AI25-AJ25-AK25) -> 39848.332 | AP25: =IF(E25=0,0,AF25-AG25-AH25) -> 7024.844 | AQ25: =IF(E25="","",+AF25/AI25) -> 0.17628954 | AR25: =IF(S25="",M25*E25,S25*E25) -> 35417.916 | AS25: =IFERROR((VLOOKUP(B25,'SUIVI 31.12.24 ALTONEO'!$B$1:$BF$38,45,FALSE())),0) -> 0 | AT25: =+AR25-AS25 -> 35417.916 | AU25: =+L25*E25 -> 4837.794 | AV25: =IFERROR((VLOOKUP(B25,'SUIVI 31.12.24 ALTONEO'!$B$1:$BF$38,48,FALSE())),0) -> 0 | AW25: =+AU25-AV25 -> 4837.794 | AX25: =IF(P25="",J25*E25,P25-Z25) -> 3885.21 | AY25: =IFERROR((VLOOKUP(B25,'SUIVI 31.12.24 ALTONEO'!$B$1:$BF$38,51,FALSE())),0) -> 0 | AZ25: =+AX25-AY25 -> 3885.21 | BA25: =IF(Q25="",K25*E25,Q25-AB25) -> 1494.312 | BB25: =IFERROR((VLOOKUP(B25,'SUIVI 31.12.24 ALTONEO'!$B$1:$BF$38,54,FALSE())),0) -> 0 | BC25: =+BA25-BB25 -> 1494.312 | BD25: =+E25*N25 -> 3600 | BE25: =IFERROR((VLOOKUP(B25,'SUIVI 31.12.24 ALTONEO'!$B$1:$BF$38,57,FALSE())),0) -> 0
B26: =+ROWS(B25:B25) -> 1 | AP26: =IF(E26=0,0,AF26-AG26-AH26) -> 0
B27: Projet Hugou / Hugou Villiers sur Loir | C27: non | D27: 7. Livraison de kits et ravalement | E27: =VLOOKUP(D27,'% avancement'!$A$5:$B$17,2,FALSE()) -> 0.95 | F27: 137916.67 | G27: 6700 | H27: =F27+G27-I27 -> 139616.67 | I27: 5000 | J27: 8377 | K27: 3490.42 | L27: 7828.15 | M27: 98793.9 | N27: 6000 | O27: 5000 | P27: 8377 | Q27: 3490.42 | T27: 6000 | U27: =IF(C27="oui","",(H27+I27)*E27) -> 137385.84 | W27: =IF(O27="",0,(1-E27)*O27) -> 250 | X27: =IF(O27="",I27*(E27),0) -> 0 | Y27: =IF(P27="",+H27*6%*E27,0) -> 0 | Z27: =IF(P27="",0,P27*(1-E27)) -> 418.85 | AA27: =IF(Q27="",+H27*2.5%*E27,0) -> 0 | AB27: =IF(Q27="",0,Q27*(1-E27)) -> 174.521 | AC27: =IF(R27="",+L27*E27,(1-E27)*R27) -> 7436.7425 | AD27: =IF(S27="",M27*E27,S27*E27) -> 93854.205 | AF27: =IF(E27="",0,+H27-J27-K27-L27-M27-N27) -> 15127.2 | AG27: =IFERROR((VLOOKUP(B27,'SUIVI 31.12.24 ALTONEO'!$B$1:$BF$38,33,FALSE())),0) -> 5997.0533 | AH27: =AF27*E27-AG27 -> 8373.7867 | AI27: =IF(E27="",0,H27) -> 139616.67 | AJ27: =IFERROR((VLOOKUP(B27,'SUIVI 31.12.24 ALTONEO'!$B$1:$BF$38,36,FALSE())),0) -> 27583.333 | AK27: =AI27*E27-AJ27 -> 105052.5 | AO27: =AI27-AJ27-AK27 -> 6980.8335 | AP27: =IF(E27=0,0,AF27-AG27-AH27) -> 756.36 | AQ27: =IF(E27="","",+AF27/AI27) -> 0.10834809 | AR27: =IF(S27="",M27*E27,S27*E27) -> 93854.205 | AS27: =IFERROR((VLOOKUP(B27,'SUIVI 31.12.24 ALTONEO'!$B$1:$BF$38,45,FALSE())),0) -> 17721.667 | AT27: =+AR27-AS27 -> 76132.538 | AU27: =+L27*E27 -> 7436.7425 | AV27: =IFERROR((VLOOKUP(B27,'SUIVI 31.12.24 ALTONEO'!$B$1:$BF$38,48,FALSE())),0) -> 1520.03 | AW27: =+AU27-AV27 -> 5916.7125 | AX27: =IF(P27="",J27*E27,P27-Z27) -> 7958.15 | AY27: =IFERROR((VLOOKUP(B27,'SUIVI 31.12.24 ALTONEO'!$B$1:$BF$38,51,FALSE())),0) -> 1655 | AZ27: =+AX27-AY27 -> 6303.15 | BA27: =IF(Q27="",K27*E27,Q27-AB27) -> 3315.899 | BB27: =IFERROR((VLOOKUP(B27,'SUIVI 31.12.24 ALTONEO'!$B$1:$BF$38,54,FALSE())),0) -> 689.58333 | BC27: =+BA27-BB27 -> 2626.3157 | BD27: =+E27*N27 -> 5700 | BE27: =IFERROR((VLOOKUP(B27,'SUIVI 31.12.24 ALTONEO'!$B$1:$BF$38,57,FALSE())),0) -> 0
A28: Sous-total | B28: =ROWS(B27:B27) -> 1
A29: Total | B29: =B26+B28 -> 2 | U29: =SUM(U3:U27) -> 1464778.7 | V29: =SUM(V3:V27) -> 0 | W29: =SUM(W3:W27) -> 11250 | X29: =SUM(X3:X27) -> 15000 | Y29: =SUM(Y3:Y27) -> 25856.35 | Z29: =SUM(Z3:Z27) -> 21459.87 | AA29: =SUM(AA3:AA27) -> 10773.479 | AB29: =SUM(AB3:AB27) -> 8267.2177 | ... AP29: =SUM(AP3:AP27) -> 226331.57 | AQ29: =+AF29/AI29 -> 0.15644855 | AR29: =SUM(AR3:AR27) -> 908195.59 | AS29: 174896.44 | AT29: =SUM(AT3:AT27) -> 890473.92 | AU29: =SUM(AU3:AU27) -> 86450.168 | AV29: =SUM(AV3:AV27) -> 1520.03 | AW29: =SUM(AW3:AW27) -> 84930.138 | AX29: =SUM(AX3:AX27) -> 89084.106 | AY29: =SUM(AY3:AY27) -> 1655 | AZ29: =SUM(AZ3:AZ28) -> 87429.106 | BA29: =SUM(BA3:BA28) -> 35231.978 | BB29: =SUM(BB3:BB27) -> 689.58333 | BC29: =SUM(BC3:BC28) -> 34542.394 | BD29: =SUM(BD3:BD28) -> 65450 | BE29: =SUM(BE3:BE28) -> 0 | BF29: =SUM(BF3:BF28) -> 0
AF30: =AF29-AG29-AH29 -> 226331.57 | AI30: =AI29-AJ29-AK29 -> 1484162.2 | AL30: =AF30-('Projection P&L'!B12*1000*1.1) -> -229363.35

Sheet Suivi 31.12.25
F1: Données prévisionnelles ou connues (à mettre à jour) | O1: Factures en compta (à mettre à jour) | U1: cut-off Chiffre d'affaires | Y1: Cut-off charges | AF1: Marges | AI1: Chiffre d'affaires HT | AL1: Frais de dossiers HT | AO1: Reste à comptabiliser | AQ1: % de marge nette | AR1: Solde compte de charges
A2: Étape ↑ | B2: Nom du projet | C2: Facture vente finale faite | D2: Statut chantier | E2: % Avancement | F2: Prix convenu (chiffre d'affaires) HT | G2: Montant avenants HT | H2: Prix actualisé HT net de SASA | I2: SASA dans le projet HT | J2: Redevances fondations | K2: Redevances Pub | L2: Honoraires MIKIT | M2: Sous-traitance MKT | N2: Honoraires courtage HT | O2: SASA HT | P2: Redevance MIKIT | Q2: Redevance Pub MIKIT | R2: Honoraires MKT | S2: Sous-traitance MKT | T2: Honoraires courtage HT | U2: FAE CA | V2: FAE dossiers assurance | W2: FAE SASA | X2: AAE SASA | Y2: Redevance MIKIT 6% FNP | Z2: Redevance MIKIT CCA | AA2: Redevance pub MIKIT 2.5% FNP | AB2: Redevance pub MIKIT CCA | AC2: Honoraires MIKIT FNP | AD2: Sous-traitance FNP MKT | AE2: Frais courtage CCA | AF2: Marge totale chantier HT | AG2: Marges constatées N-1 | AH2: Marges 2025 HT | AI2: CA Total HT | AJ2: CA constaté N-1 | AK2: CA 2025 HT | AL2: CA Total HT | AM2: CA constaté N-1 | AN2: CA 2024 HT | AO2: CA à comptabiliser € HT | AP2: marge à comptabiliser € HT | AR2: SS MKT | AS2: SS MKT N-1 | AT2: SS MKT N | AU2: Hono MKT | AV2: Hono MKT N-1 | AW2: Hono MKT N | AX2: Fond Mikit | AY2: Fond Mikit N-1 | AZ2: Fond Mikit N | BA2: Pub Mikit | BB2: Pub Mikit N-1 | BC2: Pub Mikit N | BD2: Commissions | BE2: Commissions N-1 | BF2: Commissions N
B3: Projet Péan / Lochet Saint Jean de la Motte | C3: non | D3: Ne pas prendre en compte | E3: =VLOOKUP(D3,'% avancement'!$A$4:$B$17,2,FALSE()) -> 0 | F3: 95666.667 | G3: 7500 | H3: =F3+G3-I3 -> 98166.667 | I3: 5000 | J3: =(F3+G3-I3)*0.06 -> 5890 | K3: =(F3+G3-I3)*0.025 -> 2454.1667 | L3: 7828.15 | M3: =(F3+G3)*0.62 -> 63963.333 | N3: 6000 | U3: =IF(C3="oui","",(H3+I3)*E3) -> 0 | W3: =IF(O3="",0,(1-E3)*O3) -> 0 | X3: =IF(O3="",I3*(E3),0) -> 0 | Y3: =IF(P3="",+H3*6%*E3,0) -> 0 | Z3: =IF(P3="",0,P3*(1-E3)) -> 0 | AA3: =IF(Q3="",+H3*2.5%*E3,0) -> 0 | AB3: =IF(Q3="",0,Q3*(1-E3)) -> 0 | AC3: =IF(R3="",+L3*E3,(1-E3)*R3) -> 0 | AD3: =IF(S3="",M3*E3,S3*E3) -> 0 | AF3: =IF(E3="",0,+H3-J3-K3-L3-M3-N3) -> 12031.017 | AG3: =IFERROR((VLOOKUP(B3,'SUIVI 31.12.24 ALTONEO'!$B$1:$BF$38,33,FALSE())),0) -> 0 | AH3: =AF3*E3-AG3 -> 0 | AI3: =IF(E3="",0,H3) -> 98166.667 | AJ3: =IFERROR((VLOOKUP(B3,'SUIVI 31.12.24 ALTONEO'!$B$1:$BF$38,36,FALSE())),0) -> 0 | AK3: =AI3*E3-AJ3 -> 0 | AO3: =IF(E3=0,0,AI3-AJ3-AK3) -> 0 | AP3: =IF(E3=0,0,AF3-AG3-AH3) -> 0 | AQ3: =IF(E3="","",+AF3/AI3) -> 0.12255705 | AR3: =IF(S3="",M3*E3,S3*E3) -> 0 | AS3: =IFERROR((VLOOKUP(B3,'SUIVI 31.12.24 ALTONEO'!$B$1:$BF$38,45,FALSE())),0) -> 0 | AT3: =+AR3-AS3 -> 0 | AU3: =+L3*E3 -> 0 | AV3: =IFERROR((VLOOKUP(B3,'SUIVI 31.12.24 ALTONEO'!$B$1:$BF$38,48,FALSE())),0) -> 0 | AW3: =+AU3-AV3 -> 0 | AX3: =IF(P3="",J3*E3,P3-Z3) -> 0 | AY3: =IFERROR((VLOOKUP(B3,'SUIVI 31.12.24 ALTONEO'!$B$1:$BF$38,51,FALSE())),0) -> 0 | AZ3: =+AX3-AY3 -> 0 | BA3: =IF(Q3="",K3*E3,Q3-AB3) -> 0 | BB3: =IFERROR((VLOOKUP(B3,'SUIVI 31.12.24 ALTONEO'!$B$1:$BF$38,54,FALSE())),0) -> 0 | BC3: =+BA3-BB3 -> 0 | BD3: =+E3*N3 -> 0 | BE3: =IFERROR((VLOOKUP(B3,'SUIVI 31.12.24 ALTONEO'!$B$1:$BF$38,57,FALSE())),0) -> 0
B4: Projet Forgerou / Montaillé | C4: non | D4: Ne pas prendre en compte | E4: =VLOOKUP(D4,'% avancement'!$A$4:$B$17,2,FALSE()) -> 0 | F4: 108416.67 | G4: 7500 | H4: =F4+G4-I4 -> 110916.67 | I4: 5000 | J4: =(F4+G4-I4)*0.06 -> 6655 | K4: =(F4+G4-I4)*0.025 -> 2772.9167 | L4: 7828.15 | M4: =(F4+G4)*0.62 -> 71868.333 | N4: 6000 | U4: =IF(C4="oui","",(H4+I4)*E4) -> 0 | W4: =IF(O4="",0,(1-E4)*O4) -> 0 | X4: =IF(O4="",I4*(E4),0) -> 0 | Y4: =IF(P4="",+H4*6%*E4,0) -> 0 | Z4: =IF(P4="",0,P4*(1-E4)) -> 0 | AA4: =IF(Q4="",+H4*2.5%*E4,0) -> 0 | AB4: =IF(Q4="",0,Q4*(1-E4)) -> 0 | AC4: =IF(R4="",+L4*E4,(1-E4)*R4) -> 0 | AD4: =IF(S4="",M4*E4,S4*E4) -> 0 | AF4: =IF(E4="",0,+H4-J4-K4-L4-M4-N4) -> 15792.267 | AG4: =IFERROR((VLOOKUP(B4,'SUIVI 31.12.24 ALTONEO'!$B$1:$BF$38,33,FALSE())),0) -> 0 | AH4: =AF4*E4-AG4 -> 0 | AI4: =IF(E4="",0,H4) -> 110916.67 | AJ4: =IFERROR((VLOOKUP(B4,'SUIVI 31.12.24 ALTONEO'!$B$1:$BF$38,36,FALSE())),0) -> 0 | AK4: =AI4*E4-AJ4 -> 0 | AO4: =IF(E4=0,0,AI4-AJ4-AK4) -> 0 | AP4: =IF(E4=0,0,AF4-AG4-AH4) -> 0 | AQ4: =IF(E4="","",+AF4/AI4) -> 0.14237956 | AR4: =IF(S4="",M4*E4,S4*E4) -> 0 | AS4: =IFERROR((VLOOKUP(B4,'SUIVI 31.12.24 ALTONEO'!$B$1:$BF$38,45,FALSE())),0) -> 0 | AT4: =+AR4-AS4 -> 0 | AU4: =+L4*E4 -> 0 | AV4: =IFERROR((VLOOKUP(B4,'SUIVI 31.12.24 ALTONEO'!$B$1:$BF$38,48,FALSE())),0) -> 0 | AW4: =+AU4-AV4 -> 0 | AX4: =IF(P4="",J4*E4,P4-Z4) -> 0 | AY4: =IFERROR((VLOOKUP(B4,'SUIVI 31.12.24 ALTONEO'!$B$1:$BF$38,51,FALSE())),0) -> 0 | AZ4: =+AX4-AY4 -> 0 | BA4: =IF(Q4="",K4*E4,Q4-AB4) -> 0 | BB4: =IFERROR((VLOOKUP(B4,'SUIVI 31.12.24 ALTONEO'!$B$1:$BF$38,54,FALSE())),0) -> 0 | BC4: =+BA4-BB4 -> 0 | BD4: =+E4*N4 -> 0 | BE4: =IFERROR((VLOOKUP(B4,'SUIVI 31.12.24 ALTONEO'!$B$1:$BF$38,57,FALSE())),0) -> 0
B5: Projet Beilvert / Voguet Vivoin | C5: non | D5: 1.1 Administratif validé prêt à ouvrir | E5: =VLOOKUP(D5,'% avancement'!$A$4:$B$17,2,FALSE()) -> 0.25 | F5: 125666.67 | G5: 7500 | H5: =F5+G5-I5 -> 128166.67 | I5: 5000 | J5: =(F5+G5-I5)*0.06 -> 7690 | K5: =(F5+G5-I5)*0.025 -> 3204.1667 | L5: 7828.15 | M5: =(F5+G5)*0.62 -> 82563.333 | N5: 6000 | U5: =IF(C5="oui","",(H5+I5)*E5) -> 33291.667 | W5: =IF(O5="",0,(1-E5)*O5) -> 0 | X5: =IF(O5="",I5*(E5),0) -> 1250 | Y5: =IF(P5="",+H5*6%*E5,0) -> 1922.5 | Z5: =IF(P5="",0,P5*(1-E5)) -> 0 | AA5: =IF(Q5="",+H5*2.5%*E5,0) -> 801.04167 | AB5: =IF(Q5="",0,Q5*(1-E5)) -> 0 | AC5: =IF(R5="",+L5*E5,(1-E5)*R5) -> 1957.0375 | AD5: =IF(S5="",M5*E5,S5*E5) -> 20640.833 | AF5: =IF(E5="",0,+H5-J5-K5-L5-M5-N5) -> 20881.017 | AG5: =IFERROR((VLOOKUP(B5,'SUIVI 31.12.24 ALTONEO'!$B$1:$BF$38,33,FALSE())),0) -> 0 | AH5: =AF5*E5-AG5 -> 5220.2542 | AI5: =IF(E5="",0,H5) -> 128166.67 | AJ5: =IFERROR((VLOOKUP(B5,'SUIVI 31.12.24 ALTONEO'!$B$1:$BF$38,36,FALSE())),0) -> 0 | AK5: =AI5*E5-AJ5 -> 32041.667 | AO5: =IF(E5=0,0,AI5-AJ5-AK5) -> 96125 | AP5: =IF(E5=0,0,AF5-AG5-AH5) -> 15660.763 | AQ5: =IF(E5="","",+AF5/AI5) -> 0.16292081 | AR5: =IF(S5="",M5*E5,S5*E5) -> 20640.833 | AS5: =IFERROR((VLOOKUP(B5,'SUIVI 31.12.24 ALTONEO'!$B$1:$BF$38,45,FALSE())),0) -> 0 | AT5: =+AR5-AS5 -> 20640.833 | AU5: =+L5*E5 -> 1957.0375 | AV5: =IFERROR((VLOOKUP(B5,'SUIVI 31.12.24 ALTONEO'!$B$1:$BF$38,48,FALSE())),0) -> 0 | AW5: =+AU5-AV5 -> 1957.0375 | AX5: =IF(P5="",J5*E5,P5-Z5) -> 1922.5 | AY5: =IFERROR((VLOOKUP(B5,'SUIVI 31.12.24 ALTONEO'!$B$1:$BF$38,51,FALSE())),0) -> 0 | AZ5: =+AX5-AY5 -> 1922.5 | BA5: =IF(Q5="",K5*E5,Q5-AB5) -> 801.04167 | BB5: =IFERROR((VLOOKUP(B5,'SUIVI 31.12.24 ALTONEO'!$B$1:$BF$38,54,FALSE())),0) -> 0 | BC5: =+BA5-BB5 -> 801.04167 | BD5: =+E5*N5 -> 1500 | BE5: =IFERROR((VLOOKUP(B5,'SUIVI 31.12.24 ALTONEO'!$B$1:$BF$38,57,FALSE())),0) -> 0
B6: Projet Moulineuf / Jouie Rouessé-Vassé | C6: non | D6: Ne pas prendre en compte | E6: =VLOOKUP(D6,'% avancement'!$A$4:$B$17,2,FALSE()) -> 0 | F6: 146083.33 | G6: 7500 | H6: =F6+G6-I6 -> 148583.33 | I6: 5000 | J6: =(F6+G6-I6)*0.06 -> 8915 | K6: =(F6+G6-I6)*0.025 -> 3714.5833 | L6: 7828.15 | M6: =(F6+G6)*0.62 -> 95221.667 | N6: 6000 | U6: =IF(C6="oui","",(H6+I6)*E6) -> 0 | W6: =IF(O6="",0,(1-E6)*O6) -> 0 | X6: =IF(O6="",I6*(E6),0) -> 0 | Y6: =IF(P6="",+H6*6%*E6,0) -> 0 | Z6: =IF(P6="",0,P6*(1-E6)) -> 0 | AA6: =IF(Q6="",+H6*2.5%*E6,0) -> 0 | AB6: =IF(Q6="",0,Q6*(1-E6)) -> 0 | AC6: =IF(R6="",+L6*E6,(1-E6)*R6) -> 0 | AD6: =IF(S6="",M6*E6,S6*E6) -> 0 | AF6: =IF(E6="",0,+H6-J6-K6-L6-M6-N6) -> 26903.933 | AG6: =IFERROR((VLOOKUP(B6,'SUIVI 31.12.24 ALTONEO'!$B$1:$BF$38,33,FALSE())),0) -> 0 | AH6: =AF6*E6-AG6 -> 0 | AI6: =IF(E6="",0,H6) -> 148583.33 | AJ6: =IFERROR((VLOOKUP(B6,'SUIVI 31.12.24 ALTONEO'!$B$1:$BF$38,36,FALSE())),0) -> 0 | AK6: =AI6*E6-AJ6 -> 0 | AO6: =IF(E6=0,0,AI6-AJ6-AK6) -> 0 | AP6: =IF(E6=0,0,AF6-AG6-AH6) -> 0 | AQ6: =IF(E6="","",+AF6/AI6) -> 0.18106966 | AR6: =IF(S6="",M6*E6,S6*E6) -> 0 | AS6: =IFERROR((VLOOKUP(B6,'SUIVI 31.12.24 ALTONEO'!$B$1:$BF$38,45,FALSE())),0) -> 0 | AT6: =+AR6-AS6 -> 0 | AU6: =+L6*E6 -> 0 | AV6: =IFERROR((VLOOKUP(B6,'SUIVI 31.12.24 ALTONEO'!$B$1:$BF$38,48,FALSE())),0) -> 0 | AW6: =+AU6-AV6 -> 0 | AX6: =IF(P6="",J6*E6,P6-Z6) -> 0 | AY6: =IFERROR((VLOOKUP(B6,'SUIVI 31.12.24 ALTONEO'!$B$1:$BF$38,51,FALSE())),0) -> 0 | AZ6: =+AX6-AY6 -> 0 | BA6: =IF(Q6="",K6*E6,Q6-AB6) -> 0 | BB6: =IFERROR((VLOOKUP(B6,'SUIVI 31.12.24 ALTONEO'!$B$1:$BF$38,54,FALSE())),0) -> 0 | BC6: =+BA6-BB6 -> 0 | BD6: =+E6*N6 -> 0 | BE6: =IFERROR((VLOOKUP(B6,'SUIVI 31.12.24 ALTONEO'!$B$1:$BF$38,57,FALSE())),0) -> 0
B7: Projet Lesimple / Lesimple Ellon Nonant | C7: non | D7: Ne pas prendre en compte | E7: =VLOOKUP(D7,'% avancement'!$A$4:$B$17,2,FALSE()) -> 0 | F7: 120583.33 | G7: 7500 | H7: =F7+G7-I7 -> 123083.33 | I7: 5000 | J7: =(F7+G7-I7)*0.06 -> 7385 | K7: =(F7+G7-I7)*0.025 -> 3077.0833 | L7: 7828.15 | M7: =(F7+G7)*0.62 -> 79411.667 | N7: 6000 | U7: =IF(C7="oui","",(H7+I7)*E7) -> 0 | W7: =IF(O7="",0,(1-E7)*O7) -> 0 | X7: =IF(O7="",I7*(E7),0) -> 0 | Y7: =IF(P7="",+H7*6%*E7,0) -> 0 | Z7: =IF(P7="",0,P7*(1-E7)) -> 0 | AA7: =IF(Q7="",+H7*2.5%*E7,0) -> 0 | AB7: =IF(Q7="",0,Q7*(1-E7)) -> 0 | AC7: =IF(R7="",+L7*E7,(1-E7)*R7) -> 0 | AD7: =IF(S7="",M7*E7,S7*E7) -> 0 | AF7: =IF(E7="",0,+H7-J7-K7-L7-M7-N7) -> 19381.433 | AG7: =IFERROR((VLOOKUP(B7,'SUIVI 31.12.24 ALTONEO'!$B$1:$BF$38,33,FALSE())),0) -> 0 | AH7: =AF7*E7-AG7 -> 0 | AI7: =IF(E7="",0,H7) -> 123083.33 | AJ7: =IFERROR((VLOOKUP(B7,'SUIVI 31.12.24 ALTONEO'!$B$1:$BF$38,36,FALSE())),0) -> 0 | AK7: =AI7*E7-AJ7 -> 0 | AO7: =IF(E7=0,0,AI7-AJ7-AK7) -> 0 | AP7: =IF(E7=0,0,AF7-AG7-AH7) -> 0 | AQ7: =IF(E7="","",+AF7/AI7) -> 0.15746594 | AR7: =IF(S7="",M7*E7,S7*E7) -> 0 | AS7: =IFERROR((VLOOKUP(B7,'SUIVI 31.12.24 ALTONEO'!$B$1:$BF$38,45,FALSE())),0) -> 0 | AT7: =+AR7-AS7 -> 0 | AU7: =+L7*E7 -> 0 | AV7: =IFERROR((VLOOKUP(B7,'SUIVI 31.12.24 ALTONEO'!$B$1:$BF$38,48,FALSE())),0) -> 0 | AW7: =+AU7-AV7 -> 0 | AX7: =IF(P7="",J7*E7,P7-Z7) -> 0 | AY7: =IFERROR((VLOOKUP(B7,'SUIVI 31.12.24 ALTONEO'!$B$1:$BF$38,51,FALSE())),0) -> 0 | AZ7: =+AX7-AY7 -> 0 | BA7: =IF(Q7="",K7*E7,Q7-AB7) -> 0 | BB7: =IFERROR((VLOOKUP(B7,'SUIVI 31.12.24 ALTONEO'!$B$1:$BF$38,54,FALSE())),0) -> 0 | BC7: =+BA7-BB7 -> 0 | BD7: =+E7*N7 -> 0 | BE7: =IFERROR((VLOOKUP(B7,'SUIVI 31.12.24 ALTONEO'!$B$1:$BF$38,57,FALSE())),0) -> 0
B8: Projet Jeudi / Jeudi Ravigny | C8: non | D8: Ne pas prendre en compte | E8: =VLOOKUP(D8,'% avancement'!$A$4:$B$17,2,FALSE()) -> 0 | F8: 161583.33 | G8: 7500 | H8: =F8+G8-I8 -> 164083.33 | I8: 5000 | J8: =(F8+G8-I8)*0.06 -> 9845 | K8: =(F8+G8-I8)*0.025 -> 4102.0833 | L8: 7828.15 | M8: =(F8+G8)*0.62 -> 104831.67 | N8: 6000 | U8: =IF(C8="oui","",(H8+I8)*E8) -> 0 | W8: =IF(O8="",0,(1-E8)*O8) -> 0 | X8: =IF(O8="",I8*(E8),0) -> 0 | Y8: =IF(P8="",+H8*6%*E8,0) -> 0 | Z8: =IF(P8="",0,P8*(1-E8)) -> 0 | AA8: =IF(Q8="",+H8*2.5%*E8,0) -> 0 | AB8: =IF(Q8="",0,Q8*(1-E8)) -> 0 | AC8: =IF(R8="",+L8*E8,(1-E8)*R8) -> 0 | AD8: =IF(S8="",M8*E8,S8*E8) -> 0 | AF8: =IF(E8="",0,+H8-J8-K8-L8-M8-N8) -> 31476.433 | AG8: =IFERROR((VLOOKUP(B8,'SUIVI 31.12.24 ALTONEO'!$B$1:$BF$38,33,FALSE())),0) -> 0 | AH8: =AF8*E8-AG8 -> 0 | AI8: =IF(E8="",0,H8) -> 164083.33 | AJ8: =IFERROR((VLOOKUP(B8,'SUIVI 31.12.24 ALTONEO'!$B$1:$BF$38,36,FALSE())),0) -> 0 | AK8: =AI8*E8-AJ8 -> 0 | AO8: =IF(E8=0,0,AI8-AJ8-AK8) -> 0 | AP8: =IF(E8=0,0,AF8-AG8-AH8) -> 0 | AQ8: =IF(E8="","",+AF8/AI8) -> 0.191832 | AR8: =IF(S8="",M8*E8,S8*E8) -> 0 | AS8: =IFERROR((VLOOKUP(B8,'SUIVI 31.12.24 ALTONEO'!$B$1:$BF$38,45,FALSE())),0) -> 0 | AT8: =+AR8-AS8 -> 0 | AU8: =+L8*E8 -> 0 | AV8: =IFERROR((VLOOKUP(B8,'SUIVI 31.12.24 ALTONEO'!$B$1:$BF$38,48,FALSE())),0) -> 0 | AW8: =+AU8-AV8 -> 0 | AX8: =IF(P8="",J8*E8,P8-Z8) -> 0 | AY8: =IFERROR((VLOOKUP(B8,'SUIVI 31.12.24 ALTONEO'!$B$1:$BF$38,51,FALSE())),0) -> 0 | AZ8: =+AX8-AY8 -> 0 | BA8: =IF(Q8="",K8*E8,Q8-AB8) -> 0 | BB8: =IFERROR((VLOOKUP(B8,'SUIVI 31.12.24 ALTONEO'!$B$1:$BF$38,54,FALSE())),0) -> 0 | BC8: =+BA8-BB8 -> 0 | BD8: =+E8*N8 -> 0 | BE8: =IFERROR((VLOOKUP(B8,'SUIVI 31.12.24 ALTONEO'!$B$1:$BF$38,57,FALSE())),0) -> 0
B9: Projet Touchard / Touchard Vivoin | C9: non | D9: Ne pas prendre en compte | E9: =VLOOKUP(D9,'% avancement'!$A$4:$B$17,2,FALSE()) -> 0 | F9: 125416.67 | G9: 7500 | H9: =F9+G9-I9 -> 127916.67 | I9: 5000 | J9: =(F9+G9-I9)*0.06 -> 7675 | K9: =(F9+G9-I9)*0.025 -> 3197.9167 | L9: 7828.15 | M9: =(F9+G9)*0.62 -> 82408.333 | N9: 6000 | U9: =IF(C9="oui","",(H9+I9)*E9) -> 0 | W9: =IF(O9="",0,(1-E9)*O9) -> 0 | X9: =IF(O9="",I9*(E9),0) -> 0 | Y9: =IF(P9="",+H9*6%*E9,0) -> 0 | Z9: =IF(P9="",0,P9*(1-E9)) -> 0 | AA9: =IF(Q9="",+H9*2.5%*E9,0) -> 0 | AB9: =IF(Q9="",0,Q9*(1-E9)) -> 0 | AC9: =IF(R9="",+L9*E9,(1-E9)*R9) -> 0 | AD9: =IF(S9="",M9*E9,S9*E9) -> 0 | AF9: =IF(E9="",0,+H9-J9-K9-L9-M9-N9) -> 20807.267 | AG9: =IFERROR((VLOOKUP(B9,'SUIVI 31.12.24 ALTONEO'!$B$1:$BF$38,33,FALSE())),0) -> 0 | AH9: =AF9*E9-AG9 -> 0 | AI9: =IF(E9="",0,H9) -> 127916.67 | AJ9: =IFERROR((VLOOKUP(B9,'SUIVI 31.12.24 ALTONEO'!$B$1:$BF$38,36,FALSE())),0) -> 0 | AK9: =AI9*E9-AJ9 -> 0 | AO9: =IF(E9=0,0,AI9-AJ9-AK9) -> 0 | AP9: =IF(E9=0,0,AF9-AG9-AH9) -> 0 | AQ9: =IF(E9="","",+AF9/AI9) -> 0.16266267 | AR9: =IF(S9="",M9*E9,S9*E9) -> 0 | AS9: =IFERROR((VLOOKUP(B9,'SUIVI 31.12.24 ALTONEO'!$B$1:$BF$38,45,FALSE())),0) -> 0 | AT9: =+AR9-AS9 -> 0 | AU9: =+L9*E9 -> 0 | AV9: =IFERROR((VLOOKUP(B9,'SUIVI 31.12.24 ALTONEO'!$B$1:$BF$38,48,FALSE())),0) -> 0 | AW9: =+AU9-AV9 -> 0 | AX9: =IF(P9="",J9*E9,P9-Z9) -> 0 | AY9: =IFERROR((VLOOKUP(B9,'SUIVI 31.12.24 ALTONEO'!$B$1:$BF$38,51,FALSE())),0) -> 0 | AZ9: =+AX9-AY9 -> 0 | BA9: =IF(Q9="",K9*E9,Q9-AB9) -> 0 | BB9: =IFERROR((VLOOKUP(B9,'SUIVI 31.12.24 ALTONEO'!$B$1:$BF$38,54,FALSE())),0) -> 0 | BC9: =+BA9-BB9 -> 0 | BD9: =+E9*N9 -> 0 | BE9: =IFERROR((VLOOKUP(B9,'SUIVI 31.12.24 ALTONEO'!$B$1:$BF$38,57,FALSE())),0) -> 0
B10: Projet Cimoli / Grenier St Jean de la Motte | C10: non | D10: Ne pas prendre en compte | E10: =VLOOKUP(D10,'% avancement'!$A$4:$B$17,2,FALSE()) -> 0 | F10: 124000 | G10: 7500 | H10: =F10+G10-I10 -> 126500 | I10: 5000 | J10: =(F10+G10-I10)*0.06 -> 7590 | K10: =(F10+G10-I10)*0.025 -> 3162.5 | L10: 7828.15 | M10: =(F10+G10)*0.62 -> 81530 | N10: 6000 | U10: =IF(C10="oui","",(H10+I10)*E10) -> 0 | W10: =IF(O10="",0,(1-E10)*O10) -> 0 | X10: =IF(O10="",I10*(E10),0) -> 0 | Y10: =IF(P10="",+H10*6%*E10,0) -> 0 | Z10: =IF(P10="",0,P10*(1-E10)) -> 0 | AA10: =IF(Q10="",+H10*2.5%*E10,0) -> 0 | AB10: =IF(Q10="",0,Q10*(1-E10)) -> 0 | AC10: =IF(R10="",+L10*E10,(1-E10)*R10) -> 0 | AD10: =IF(S10="",M10*E10,S10*E10) -> 0 | AF10: =IF(E10="",0,+H10-J10-K10-L10-M10-N10) -> 20389.35 | AG10: =IFERROR((VLOOKUP(B10,'SUIVI 31.12.24 ALTONEO'!$B$1:$BF$38,33,FALSE())),0) -> 0 | AH10: =AF10*E10-AG10 -> 0 | AI10: =IF(E10="",0,H10) -> 126500 | AJ10: =IFERROR((VLOOKUP(B10,'SUIVI 31.12.24 ALTONEO'!$B$1:$BF$38,36,FALSE())),0) -> 0 | AK10: =AI10*E10-AJ10 -> 0 | AO10: =IF(E10=0,0,AI10-AJ10-AK10) -> 0 | AP10: =IF(E10=0,0,AF10-AG10-AH10) -> 0 | AQ10: =IF(E10="","",+AF10/AI10) -> 0.16118063 | AR10: =IF(S10="",M10*E10,S10*E10) -> 0 | AS10: =IFERROR((VLOOKUP(B10,'SUIVI 31.12.24 ALTONEO'!$B$1:$BF$38,45,FALSE())),0) -> 0 | AT10: =+AR10-AS10 -> 0 | AU10: =+L10*E10 -> 0 | AV10: =IFERROR((VLOOKUP(B10,'SUIVI 31.12.24 ALTONEO'!$B$1:$BF$38,48,FALSE())),0) -> 0 | AW10: =+AU10-AV10 -> 0 | AX10: =IF(P10="",J10*E10,P10-Z10) -> 0 | AY10: =IFERROR((VLOOKUP(B10,'SUIVI 31.12.24 ALTONEO'!$B$1:$BF$38,51,FALSE())),0) -> 0 | AZ10: =+AX10-AY10 -> 0 | BA10: =IF(Q10="",K10*E10,Q10-AB10) -> 0 | BB10: =IFERROR((VLOOKUP(B10,'SUIVI 31.12.24 ALTONEO'!$B$1:$BF$38,54,FALSE())),0) -> 0 | BC10: =+BA10-BB10 -> 0 | BD10: =+E10*N10 -> 0 | BE10: =IFERROR((VLOOKUP(B10,'SUIVI 31.12.24 ALTONEO'!$B$1:$BF$38,57,FALSE())),0) -> 0
B11: Projet Julien / Julien Vivoin | C11: non | D11: Ne pas prendre en compte | E11: =VLOOKUP(D11,'% avancement'!$A$4:$B$17,2,FALSE()) -> 0 | F11: 118916.67 | G11: 7500 | H11: =F11+G11-I11 -> 121416.67 | I11: 5000 | J11: =(F11+G11-I11)*0.06 -> 7285 | K11: =(F11+G11-I11)*0.025 -> 3035.4167 | L11: 7828.15 | M11: =(F11+G11)*0.62 -> 78378.333 | N11: 6000 | U11: =IF(C11="oui","",(H11+I11)*E11) -> 0 | W11: =IF(O11="",0,(1-E11)*O11) -> 0 | X11: =IF(O11="",I11*(E11),0) -> 0 | Y11: =IF(P11="",+H11*6%*E11,0) -> 0 | Z11: =IF(P11="",0,P11*(1-E11)) -> 0 | AA11: =IF(Q11="",+H11*2.5%*E11,0) -> 0 | AB11: =IF(Q11="",0,Q11*(1-E11)) -> 0 | AC11: =IF(R11="",+L11*E11,(1-E11)*R11) -> 0 | AD11: =IF(S11="",M11*E11,S11*E11) -> 0 | AF11: =IF(E11="",0,+H11-J11-K11-L11-M11-N11) -> 18889.767 | AG11: =IFERROR((VLOOKUP(B11,'SUIVI 31.12.24 ALTONEO'!$B$1:$BF$38,33,FALSE())),0) -> 0 | AH11: =AF11*E11-AG11 -> 0 | AI11: =IF(E11="",0,H11) -> 121416.67 | AJ11: =IFERROR((VLOOKUP(B11,'SUIVI 31.12.24 ALTONEO'!$B$1:$BF$38,36,FALSE())),0) -> 0 | AK11: =AI11*E11-AJ11 -> 0 | AO11: =IF(E11=0,0,AI11-AJ11-AK11) -> 0 | AP11: =IF(E11=0,0,AF11-AG11-AH11) -> 0 | AQ11: =IF(E11="","",+AF11/AI11) -> 0.15557804 | AR11: =IF(S11="",M11*E11,S11*E11) -> 0 | AS11: =IFERROR((VLOOKUP(B11,'SUIVI 31.12.24 ALTONEO'!$B$1:$BF$38,45,FALSE())),0) -> 0 | AT11: =+AR11-AS11 -> 0 | AU11: =+L11*E11 -> 0 | AV11: =IFERROR((VLOOKUP(B11,'SUIVI 31.12.24 ALTONEO'!$B$1:$BF$38,48,FALSE())),0) -> 0 | AW11: =+AU11-AV11 -> 0 | AX11: =IF(P11="",J11*E11,P11-Z11) -> 0 | AY11: =IFERROR((VLOOKUP(B11,'SUIVI 31.12.24 ALTONEO'!$B$1:$BF$38,51,FALSE())),0) -> 0 | AZ11: =+AX11-AY11 -> 0 | BA11: =IF(Q11="",K11*E11,Q11-AB11) -> 0 | BB11: =IFERROR((VLOOKUP(B11,'SUIVI 31.12.24 ALTONEO'!$B$1:$BF$38,54,FALSE())),0) -> 0 | BC11: =+BA11-BB11 -> 0 | BD11: =+E11*N11 -> 0 | BE11: =IFERROR((VLOOKUP(B11,'SUIVI 31.12.24 ALTONEO'!$B$1:$BF$38,57,FALSE())),0) -> 0
B12: Projet Clément / Clerc Lombron | C12: non | D12: Ne pas prendre en compte | E12: =VLOOKUP(D12,'% avancement'!$A$4:$B$17,2,FALSE()) -> 0 | F12: 133083.33 | G12: 7500 | H12: =F12+G12-I12 -> 135583.33 | I12: 5000 | J12: =(F12+G12-I12)*0.06 -> 8135 | K12: =(F12+G12-I12)*0.025 -> 3389.5833 | L12: 7828.15 | M12: =(F12+G12)*0.62 -> 87161.667 | N12: 6000 | U12: =IF(C12="oui","",(H12+I12)*E12) -> 0 | W12: =IF(O12="",0,(1-E12)*O12) -> 0 | X12: =IF(O12="",I12*(E12),0) -> 0 | Y12: =IF(P12="",+H12*6%*E12,0) -> 0 | Z12: =IF(P12="",0,P12*(1-E12)) -> 0 | AA12: =IF(Q12="",+H12*2.5%*E12,0) -> 0 | AB12: =IF(Q12="",0,Q12*(1-E12)) -> 0 | AC12: =IF(R12="",+L12*E12,(1-E12)*R12) -> 0 | AD12: =IF(S12="",M12*E12,S12*E12) -> 0 | AF12: =IF(E12="",0,+H12-J12-K12-L12-M12-N12) -> 23068.933 | AG12: =IFERROR((VLOOKUP(B12,'SUIVI 31.12.24 ALTONEO'!$B$1:$BF$38,33,FALSE())),0) -> 0 | AH12: =AF12*E12-AG12 -> 0 | AI12: =IF(E12="",0,H12) -> 135583.33 | AJ12: =IFERROR((VLOOKUP(B12,'SUIVI 31.12.24 ALTONEO'!$B$1:$BF$38,36,FALSE())),0) -> 0 | AK12: =AI12*E12-AJ12 -> 0 | AO12: =IF(E12=0,0,AI12-AJ12-AK12) -> 0 | AP12: =IF(E12=0,0,AF12-AG12-AH12) -> 0 | AQ12: =IF(E12="","",+AF12/AI12) -> 0.17014579 | AR12: =IF(S12="",M12*E12,S12*E12) -> 0 | AS12: =IFERROR((VLOOKUP(B12,'SUIVI 31.12.24 ALTONEO'!$B$1:$BF$38,45,FALSE())),0) -> 0 | AT12: =+AR12-AS12 -> 0 | AU12: =+L12*E12 -> 0 | AV12: =IFERROR((VLOOKUP(B12,'SUIVI 31.12.24 ALTONEO'!$B$1:$BF$38,48,FALSE())),0) -> 0 | AW12: =+AU12-AV12 -> 0 | AX12: =IF(P12="",J12*E12,P12-Z12) -> 0 | AY12: =IFERROR((VLOOKUP(B12,'SUIVI 31.12.24 ALTONEO'!$B$1:$BF$38,51,FALSE())),0) -> 0 | AZ12: =+AX12-AY12 -> 0 | BA12: =IF(Q12="",K12*E12,Q12-AB12) -> 0 | BB12: =IFERROR((VLOOKUP(B12,'SUIVI 31.12.24 ALTONEO'!$B$1:$BF$38,54,FALSE())),0) -> 0 | BC12: =+BA12-BB12 -> 0 | BD12: =+E12*N12 -> 0 | BE12: =IFERROR((VLOOKUP(B12,'SUIVI 31.12.24 ALTONEO'!$B$1:$BF$38,57,FALSE())),0) -> 0
B13: Projet Corvasier / Lorin Ecommoy | C13: non | D13: Ne pas prendre en compte | E13: =VLOOKUP(D13,'% avancement'!$A$4:$B$17,2,FALSE()) -> 0 | F13: 128916.67 | G13: 7500 | H13: =F13+G13-I13 -> 131416.67 | I13: 5000 | J13: =(F13+G13-I13)*0.06 -> 7885 | K13: =(F13+G13-I13)*0.025 -> 3285.4167 | L13: 7828.15 | M13: =(F13+G13)*0.62 -> 84578.333 | N13: 6000 | U13: =IF(C13="oui","",(H13+I13)*E13) -> 0 | W13: =IF(O13="",0,(1-E13)*O13) -> 0 | X13: =IF(O13="",I13*(E13),0) -> 0 | Y13: =IF(P13="",+H13*6%*E13,0) -> 0 | Z13: =IF(P13="",0,P13*(1-E13)) -> 0 | AA13: =IF(Q13="",+H13*2.5%*E13,0) -> 0 | AB13: =IF(Q13="",0,Q13*(1-E13)) -> 0 | AC13: =IF(R13="",+L13*E13,(1-E13)*R13) -> 0 | AD13: =IF(S13="",M13*E13,S13*E13) -> 0 | AF13: =IF(E13="",0,+H13-J13-K13-L13-M13-N13) -> 21839.767 | AG13: =IFERROR((VLOOKUP(B13,'SUIVI 31.12.24 ALTONEO'!$B$1:$BF$38,33,FALSE())),0) -> 0 | AH13: =AF13*E13-AG13 -> 0 | AI13: =IF(E13="",0,H13) -> 131416.67 | AJ13: =IFERROR((VLOOKUP(B13,'SUIVI 31.12.24 ALTONEO'!$B$1:$BF$38,36,FALSE())),0) -> 0 | AK13: =AI13*E13-AJ13 -> 0 | AO13: =IF(E13=0,0,AI13-AJ13-AK13) -> 0 | AP13: =IF(E13=0,0,AF13-AG13-AH13) -> 0 | AQ13: =IF(E13="","",+AF13/AI13) -> 0.16618719 | AR13: =IF(S13="",M13*E13,S13*E13) -> 0 | AS13: =IFERROR((VLOOKUP(B13,'SUIVI 31.12.24 ALTONEO'!$B$1:$BF$38,45,FALSE())),0) -> 0 | AT13: =+AR13-AS13 -> 0 | AU13: =+L13*E13 -> 0 | AV13: =IFERROR((VLOOKUP(B13,'SUIVI 31.12.24 ALTONEO'!$B$1:$BF$38,48,FALSE())),0) -> 0 | AW13: =+AU13-AV13 -> 0 | AX13: =IF(P13="",J13*E13,P13-Z13) -> 0 | AY13: =IFERROR((VLOOKUP(B13,'SUIVI 31.12.24 ALTONEO'!$B$1:$BF$38,51,FALSE())),0) -> 0 | AZ13: =+AX13-AY13 -> 0 | BA13: =IF(Q13="",K13*E13,Q13-AB13) -> 0 | BB13: =IFERROR((VLOOKUP(B13,'SUIVI 31.12.24 ALTONEO'!$B$1:$BF$38,54,FALSE())),0) -> 0 | BC13: =+BA13-BB13 -> 0 | BD13: =+E13*N13 -> 0 | BE13: =IFERROR((VLOOKUP(B13,'SUIVI 31.12.24 ALTONEO'!$B$1:$BF$38,57,FALSE())),0) -> 0
B14: Projet Tridon / Tranchard Laigné Saint Gervais | C14: non | D14: Ne pas prendre en compte | E14: =VLOOKUP(D14,'% avancement'!$A$4:$B$17,2,FALSE()) -> 0 | F14: 121916.67 | G14: 7500 | H14: =F14+G14-I14 -> 124416.67 | I14: 5000 | J14: =(F14+G14-I14)*0.06 -> 7465 | K14: =(F14+G14-I14)*0.025 -> 3110.4167 | L14: 7828.15 | M14: =(F14+G14)*0.62 -> 80238.333 | N14: 6000 | U14: =IF(C14="oui","",(H14+I14)*E14) -> 0 | W14: =IF(O14="",0,(1-E14)*O14) -> 0 | X14: =IF(O14="",I14*(E14),0) -> 0 | Y14: =IF(P14="",+H14*6%*E14,0) -> 0 | Z14: =IF(P14="",0,P14*(1-E14)) -> 0 | AA14: =IF(Q14="",+H14*2.5%*E14,0) -> 0 | AB14: =IF(Q14="",0,Q14*(1-E14)) -> 0 | AC14: =IF(R14="",+L14*E14,(1-E14)*R14) -> 0 | AD14: =IF(S14="",M14*E14,S14*E14) -> 0 | AF14: =IF(E14="",0,+H14-J14-K14-L14-M14-N14) -> 19774.767 | AG14: =IFERROR((VLOOKUP(B14,'SUIVI 31.12.24 ALTONEO'!$B$1:$BF$38,33,FALSE())),0) -> 0 | AH14: =AF14*E14-AG14 -> 0 | AI14: =IF(E14="",0,H14) -> 124416.67 | AJ14: =IFERROR((VLOOKUP(B14,'SUIVI 31.12.24 ALTONEO'!$B$1:$BF$38,36,FALSE())),0) -> 0 | AK14: =AI14*E14-AJ14 -> 0 | AO14: =IF(E14=0,0,AI14-AJ14-AK14) -> 0 | AP14: =IF(E14=0,0,AF14-AG14-AH14) -> 0 | AQ14: =IF(E14="","",+AF14/AI14) -> 0.15893985 | AR14: =IF(S14="",M14*E14,S14*E14) -> 0 | AS14: =IFERROR((VLOOKUP(B14,'SUIVI 31.12.24 ALTONEO'!$B$1:$BF$38,45,FALSE())),0) -> 0 | AT14: =+AR14-AS14 -> 0 | AU14: =+L14*E14 -> 0 | AV14: =IFERROR((VLOOKUP(B14,'SUIVI 31.12.24 ALTONEO'!$B$1:$BF$38,48,FALSE())),0) -> 0 | AW14: =+AU14-AV14 -> 0 | AX14: =IF(P14="",J14*E14,P14-Z14) -> 0 | AY14: =IFERROR((VLOOKUP(B14,'SUIVI 31.12.24 ALTONEO'!$B$1:$BF$38,51,FALSE())),0) -> 0 | AZ14: =+AX14-AY14 -> 0 | BA14: =IF(Q14="",K14*E14,Q14-AB14) -> 0 | BB14: =IFERROR((VLOOKUP(B14,'SUIVI 31.12.24 ALTONEO'!$B$1:$BF$38,54,FALSE())),0) -> 0 | BC14: =+BA14-BB14 -> 0 | BD14: =+E14*N14 -> 0 | BE14: =IFERROR((VLOOKUP(B14,'SUIVI 31.12.24 ALTONEO'!$B$1:$BF$38,57,FALSE())),0) -> 0
... B29: Projet Delaunay / Blet Vaas | C29: non | D29: 1.1 Administratif validé prêt à ouvrir | E29: =VLOOKUP(D29,'% avancement'!$A$4:$B$17,2,FALSE()) -> 0.25 | F29: 115583.33 | G29: 7500 | H29: =F29+G29-I29 -> 118083.33 | I29: 5000 | J29: =(F29+G29-I29)*0.06 -> 7085 | K29: =(F29+G29-I29)*0.025 -> 2952.0833 | L29: 7828.15 | M29: =(F29+G29)*0.62 -> 76311.667 | N29: 6000 | U29: =IF(C29="oui","",(H29+I29)*E29) -> 30770.833 | W29: =IF(O29="",0,(1-E29)*O29) -> 0 | X29: =IF(O29="",I29*(E29),0) -> 1250 | Y29: =IF(P29="",+H29*6%*E29,0) -> 1771.25 | Z29: =IF(P29="",0,P29*(1-E29)) -> 0 | AA29: =IF(Q29="",+H29*2.5%*E29,0) -> 738.02083 | AB29: =IF(Q29="",0,Q29*(1-E29)) -> 0 | AC29: =IF(R29="",+L29*E29,(1-E29)*R29) -> 1957.0375 | AD29: =IF(S29="",M29*E29,S29*E29) -> 19077.917 | AF29: =IF(E29="",0,+H29-J29-K29-L29-M29-N29) -> 17906.433 | AG29: =IFERROR((VLOOKUP(B29,'SUIVI 31.12.24 ALTONEO'!$B$1:$BF$38,33,FALSE())),0) -> 0 | AH29: =AF29*E29-AG29 -> 4476.6083 | AI29: =IF(E29="",0,H29) -> 118083.33 | AJ29: =IFERROR((VLOOKUP(B29,'SUIVI 31.12.24 ALTONEO'!$B$1:$BF$38,36,FALSE())),0) -> 0 | AK29: =AI29*E29-AJ29 -> 29520.833 | AO29: =IF(E29=0,0,AI29-AJ29-AK29) -> 88562.5 | AP29: =IF(E29=0,0,AF29-AG29-AH29) -> 13429.825 | AQ29: =IF(E29="","",+AF29/AI29) -> 0.15164234 | AR29: =IF(S29="",M29*E29,S29*E29) -> 19077.917 | AS29: =IFERROR((VLOOKUP(B29,'SUIVI 31.12.24 ALTONEO'!$B$1:$BF$38,45,FALSE())),0) -> 0 | AT29: =+AR29-AS29 -> 19077.917 | AU29: =+L29*E29 -> 1957.0375 | AV29: =IFERROR((VLOOKUP(B29,'SUIVI 31.12.24 ALTONEO'!$B$1:$BF$38,48,FALSE())),0) -> 0 | AW29: =+AU29-AV29 -> 1957.0375 | AX29: =IF(P29="",J29*E29,P29-Z29) -> 1771.25 | AY29: =IFERROR((VLOOKUP(B29,'SUIVI 31.12.24 ALTONEO'!$B$1:$BF$38,51,FALSE())),0) -> 0 | AZ29: =+AX29-AY29 -> 1771.25 | BA29: =IF(Q29="",K29*E29,Q29-AB29) -> 738.02083 | BB29: =IFERROR((VLOOKUP(B29,'SUIVI 31.12.24 ALTONEO'!$B$1:$BF$38,54,FALSE())),0) -> 0 | BC29: =+BA29-BB29 -> 738.02083 | BD29: =+E29*N29 -> 1500 | BE29: =IFERROR((VLOOKUP(B29,'SUIVI 31.12.24 ALTONEO'!$B$1:$BF$38,57,FALSE())),0) -> 0
B30: Projet Partaud / Partaud Mulsanne | C30: non | D30: 4. Assurances | E30: =VLOOKUP(D30,'% avancement'!$A$4:$B$17,2,FALSE()) -> 0.4 | F30: =129800/1.2 -> 108166.67 | G30: =10918/1.2 -> 9098.3333 | H30: =F30+G30-I30 -> 112265 | I30: 5000 | J30: 7297.23 | K30: 2806.63 | L30: 7828.15 | M30: 71808.43 | N30: 6000 | O30: 5000 | P30: 7297.23 | Q30: 2806.63 | R30: 7828.15 | T30: 6000 | U30: =IF(C30="oui","",(H30+I30)*E30) -> 46906 | W30: =IF(O30="",0,(1-E30)*O30) -> 3000 | X30: =IF(O30="",I30*(E30),0) -> 0 | Y30: =IF(P30="",+H30*6%*E30,0) -> 0 | Z30: =IF(P30="",0,P30*(1-E30)) -> 4378.338 | AA30: =IF(Q30="",+H30*2.5%*E30,0) -> 0 | AB30: =IF(Q30="",0,Q30*(1-E30)) -> 1683.978 | AC30: =IF(R30="",+L30*E30,(1-E30)*R30) -> 4696.89 | AD30: =IF(S30="",M30*E30,S30*E30) -> 28723.372 | AF30: =IF(E30="",0,+H30-J30-K30-L30-M30-N30) -> 16524.56 | AG30: =IFERROR((VLOOKUP(B30,'SUIVI 31.12.24 ALTONEO'!$B$1:$BF$38,33,FALSE())),0) -> 0 | AH30: =AF30*E30-AG30 -> 6609.824 | AI30: =IF(E30="",0,H30) -> 112265 | AJ30: =IFERROR((VLOOKUP(B30,'SUIVI 31.12.24 ALTONEO'!$B$1:$BF$38,36,FALSE())),0) -> 0 | AK30: =AI30*E30-AJ30 -> 44906 | AO30: =IF(E30=0,0,AI30-AJ30-AK30) -> 67359 | AP30: =IF(E30=0,0,AF30-AG30-AH30) -> 9914.736 | AQ30: =IF(E30="","",+AF30/AI30) -> 0.14719245 | AR30: =IF(S30="",M30*E30,S30*E30) -> 28723.372 | AS30: =IFERROR((VLOOKUP(B30,'SUIVI 31.12.24 ALTONEO'!$B$1:$BF$38,45,FALSE())),0) -> 0 | AT30: =+AR30-AS30 -> 28723.372 | AU30: =+L30*E30 -> 3131.26 | AV30: =IFERROR((VLOOKUP(B30,'SUIVI 31.12.24 ALTONEO'!$B$1:$BF$38,48,FALSE())),0) -> 0 | AW30: =+AU30-AV30 -> 3131.26 | AX30: =IF(P30="",J30*E30,P30-Z30) -> 2918.892 | AY30: =IFERROR((VLOOKUP(B30,'SUIVI 31.12.24 ALTONEO'!$B$1:$BF$38,51,FALSE())),0) -> 0 | AZ30: =+AX30-AY30 -> 2918.892 | BA30: =IF(Q30="",K30*E30,Q30-AB30) -> 1122.652 | BB30: =IFERROR((VLOOKUP(B30,'SUIVI 31.12.24 ALTONEO'!$B$1:$BF$38,54,FALSE())),0) -> 0 | BC30: =+BA30-BB30 -> 1122.652 | BD30: =+E30*N30 -> 2400 | BE30: =IFERROR((VLOOKUP(B30,'SUIVI 31.12.24 ALTONEO'!$B$1:$BF$38,57,FALSE())),0) -> 0
B31: Projet Protin / Subranne St Jean de la Motte | C31: non | D31: 5. Achèvement des murs | E31: =VLOOKUP(D31,'% avancement'!$A$5:$B$17,2,FALSE()) -> 0.6 | F31: =178200/1.2 -> 148500 | G31: =10305/1.2 -> 8587.5 | H31: =F31+G31-I31 -> 152087.5 | I31: 5000 | J31: =11862.83/1.2 -> 9885.6917 | K31: =4562.63/1.2 -> 3802.1917 | L31: 7828.15 | M31: 102829.4 | N31: 6000 | O31: 5000 | P31: 9885.6917 | Q31: 3802.1917 | R31: 7828.15 | T31: 6000 | U31: =IF(C31="oui","",(H31+I31)*E31) -> 94252.5 | W31: =IF(O31="",0,(1-E31)*O31) -> 2000 | X31: =IF(O31="",I31*(E31),0) -> 0 | Y31: =IF(P31="",+H31*6%*E31,0) -> 0 | Z31: =IF(P31="",0,P31*(1-E31)) -> 3954.2767 | AA31: =IF(Q31="",+H31*2.5%*E31,0) -> 0 | AB31: =IF(Q31="",0,Q31*(1-E31)) -> 1520.8767 | AC31: =IF(R31="",+L31*E31,(1-E31)*R31) -> 3131.26 | AD31: =IF(S31="",M31*E31,S31*E31) -> 61697.64 | AF31: =IF(E31="",0,+H31-J31-K31-L31-M31-N31) -> 21742.067 | AG31: =IFERROR((VLOOKUP(B31,'SUIVI 31.12.24 ALTONEO'!$B$1:$BF$38,33,FALSE())),0) -> 0 | AH31: =AF31*E31-AG31 -> 13045.24 | AI31: =IF(E31="",0,H31) -> 152087.5 | AJ31: =IFERROR((VLOOKUP(B31,'SUIVI 31.12.24 ALTONEO'!$B$1:$BF$38,36,FALSE())),0) -> 0 | AK31: =AI31*E31-AJ31 -> 91252.5 | AO31: =IF(E31=0,0,AI31-AJ31-AK31) -> 60835 | AP31: =IF(E31=0,0,AF31-AG31-AH31) -> 8696.8267 | AQ31: =IF(E31="","",+AF31/AI31) -> 0.14295762 | AR31: =IF(S31="",M31*E31,S31*E31) -> 61697.64 | AS31: =IFERROR((VLOOKUP(B31,'SUIVI 31.12.24 ALTONEO'!$B$1:$BF$38,45,FALSE())),0) -> 0 | AT31: =+AR31-AS31 -> 61697.64 | AU31: =+L31*E31 -> 4696.89 | AV31: =IFERROR((VLOOKUP(B31,'SUIVI 31.12.24 ALTONEO'!$B$1:$BF$38,48,FALSE())),0) -> 0 | AW31: =+AU31-AV31 -> 4696.89 | AX31: =IF(P31="",J31*E31,P31-Z31) -> 5931.415 | AY31: =IFERROR((VLOOKUP(B31,'SUIVI 31.12.24 ALTONEO'!$B$1:$BF$38,51,FALSE())),0) -> 0 | AZ31: =+AX31-AY31 -> 5931.415 | BA31: =IF(Q31="",K31*E31,Q31-AB31) -> 2281.315 | BB31: =IFERROR((VLOOKUP(B31,'SUIVI 31.12.24 ALTONEO'!$B$1:$BF$38,54,FALSE())),0) -> 0 | BC31: =+BA31-BB31 -> 2281.315 | BD31: =+E31*N31 -> 3600 | BE31: =IFERROR((VLOOKUP(B31,'SUIVI 31.12.24 ALTONEO'!$B$1:$BF$38,57,FALSE())),0) -> 0
B32: Projet Chafiol / Chafiol Ecommoy | C32: non | D32: 6. Mise hors d'eau | E32: =VLOOKUP(D32,'% avancement'!$A$5:$B$17,2,FALSE()) -> 0.8 | F32: 121500 | G32: 8878.3333 | H32: =F32+G32-I32 -> 125378.33 | I32: 5000 | J32: 8149.59 | K32: 3134.46 | L32: 7828.15 | M32: 72954.42 | N32: 6000 | O32: 5000 | T32: 6000 | U32: =IF(C32="oui","",(H32+I32)*E32) -> 104302.67 | W32: =IF(O32="",0,(1-E32)*O32) -> 1000 | X32: =IF(O32="",I32*(E32),0) -> 0 | Y32: =IF(P32="",+H32*6%*E32,0) -> 6018.16 | Z32: =IF(P32="",0,P32*(1-E32)) -> 0 | AA32: =IF(Q32="",+H32*2.5%*E32,0) -> 2507.5667 | AB32: =IF(Q32="",0,Q32*(1-E32)) -> 0 | AC32: =IF(R32="",+L32*E32,(1-E32)*R32) -> 6262.52 | AD32: =IF(S32="",M32*E32,S32*E32) -> 58363.536 | AF32: =IF(E32="",0,+H32-J32-K32-L32-M32-N32) -> 27311.713 | AG32: =IFERROR((VLOOKUP(B32,'SUIVI 31.12.24 ALTONEO'!$B$1:$BF$38,33,FALSE())),0) -> 0 | AH32: =AF32*E32-AG32 -> 21849.371 | AI32: =IF(E32="",0,H32) -> 125378.33 | AJ32: =IFERROR((VLOOKUP(B32,'SUIVI 31.12.24 ALTONEO'!$B$1:$BF$38,36,FALSE())),0) -> 0 | AK32: =AI32*E32-AJ32 -> 100302.67 | AO32: =IF(E32=0,0,AI32-AJ32-AK32) -> 25075.667 | AP32: =IF(E32=0,0,AF32-AG32-AH32) -> 5462.3427 | AQ32: =IF(E32="","",+AF32/AI32) -> 0.21783439 | AR32: =IF(S32="",M32*E32,S32*E32) -> 58363.536 | AS32: =IFERROR((VLOOKUP(B32,'SUIVI 31.12.24 ALTONEO'!$B$1:$BF$38,45,FALSE())),0) -> 0 | AT32: =+AR32-AS32 -> 58363.536 | AU32: =+L32*E32 -> 6262.52 | AV32: =IFERROR((VLOOKUP(B32,'SUIVI 31.12.24 ALTONEO'!$B$1:$BF$38,48,FALSE())),0) -> 0 | AW32: =+AU32-AV32 -> 6262.52 | AX32: =IF(P32="",J32*E32,P32-Z32) -> 6519.672 | AY32: =IFERROR((VLOOKUP(B32,'SUIVI 31.12.24 ALTONEO'!$B$1:$BF$38,51,FALSE())),0) -> 0 | AZ32: =+AX32-AY32 -> 6519.672 | BA32: =IF(Q32="",K32*E32,Q32-AB32) -> 2507.568 | BB32: =IFERROR((VLOOKUP(B32,'SUIVI 31.12.24 ALTONEO'!$B$1:$BF$38,54,FALSE())),0) -> 0 | BC32: =+BA32-BB32 -> 2507.568 | BD32: =+E32*N32 -> 4800 | BE32: =IFERROR((VLOOKUP(B32,'SUIVI 31.12.24 ALTONEO'!$B$1:$BF$38,57,FALSE())),0) -> 0
B33: Projet Bigaret / Cheniour St Jean de la Motte | C33: non | D33: 5. Achèvement des murs | E33: =VLOOKUP(D33,'% avancement'!$A$5:$B$17,2,FALSE()) -> 0.6 | F33: =155200/1.2 -> 129333.33 | G33: =10268/1.2 -> 8556.6667 | H33: =F33+G33-I33 -> 132890 | I33: 5000 | J33: =10365.42/1.2 -> 8637.85 | K33: =3986.7/1.2 -> 3322.25 | L33: 7828.15 | M33: 84311.97 | N33: 6000 | O33: 5000 | P33: =10365.42/1.2 -> 8637.85 | Q33: =3986.7/1.2 -> 3322.25 | R33: 7828.15 | T33: 6000 | U33: =IF(C33="oui","",(H33+I33)*E33) -> 82734 | W33: =IF(O33="",0,(1-E33)*O33) -> 2000 | X33: =IF(O33="",I33*(E33),0) -> 0 | Y33: =IF(P33="",+H33*6%*E33,0) -> 0 | Z33: =IF(P33="",0,P33*(1-E33)) -> 3455.14 | AA33: =IF(Q33="",+H33*2.5%*E33,0) -> 0 | AB33: =IF(Q33="",0,Q33*(1-E33)) -> 1328.9 | AC33: =IF(R33="",+L33*E33,(1-E33)*R33) -> 3131.26 | AD33: =IF(S33="",M33*E33,S33*E33) -> 50587.182 | AF33: =IF(E33="",0,+H33-J33-K33-L33-M33-N33) -> 22789.78 | AG33: =IFERROR((VLOOKUP(B33,'SUIVI 31.12.24 ALTONEO'!$B$1:$BF$38,33,FALSE())),0) -> 0 | AH33: =AF33*E33-AG33 -> 13673.868 | AI33: =IF(E33="",0,H33) -> 132890 | AJ33: =IFERROR((VLOOKUP(B33,'SUIVI 31.12.24 ALTONEO'!$B$1:$BF$38,36,FALSE())),0) -> 0 | AK33: =AI33*E33-AJ33 -> 79734 | AO33: =IF(E33=0,0,AI33-AJ33-AK33) -> 53156 | AP33: =IF(E33=0,0,AF33-AG33-AH33) -> 9115.912 | AQ33: =IF(E33="","",+AF33/AI33) -> 0.17149357 | AR33: =IF(S33="",M33*E33,S33*E33) -> 50587.182 | AS33: =IFERROR((VLOOKUP(B33,'SUIVI 31.12.24 ALTONEO'!$B$1:$BF$38,45,FALSE())),0) -> 0 | AT33: =+AR33-AS33 -> 50587.182 | AU33: =+L33*E33 -> 4696.89 | AV33: =IFERROR((VLOOKUP(B33,'SUIVI 31.12.24 ALTONEO'!$B$1:$BF$38,48,FALSE())),0) -> 0 | AW33: =+AU33-AV33 -> 4696.89 | AX33: =IF(P33="",J33*E33,P33-Z33) -> 5182.71 | AY33: =IFERROR((VLOOKUP(B33,'SUIVI 31.12.24 ALTONEO'!$B$1:$BF$38,51,FALSE())),0) -> 0 | AZ33: =+AX33-AY33 -> 5182.71 | BA33: =IF(Q33="",K33*E33,Q33-AB33) -> 1993.35 | BB33: =IFERROR((VLOOKUP(B33,'SUIVI 31.12.24 ALTONEO'!$B$1:$BF$38,54,FALSE())),0) -> 0 | BC33: =+BA33-BB33 -> 1993.35 | BD33: =+E33*N33 -> 3600 | BE33: =IFERROR((VLOOKUP(B33,'SUIVI 31.12.24 ALTONEO'!$B$1:$BF$38,57,FALSE())),0) -> 0
B34: Projet Paradis / Allonnes | C34: non | D34: 1.1 Administratif validé prêt à ouvrir | E34: =VLOOKUP(D34,'% avancement'!$A$5:$B$17,2,FALSE()) -> 0.25 | F34: =133500/1.2 -> 111250 | G34: =8900/1.2 -> 7416.6667 | H34: =F34+G34-I34 -> 118666.67 | I34: 0 | J34: =(F34+G34-I34)*0.06 -> 7120 | K34: =(F34+G34-I34)*0.025 -> 2966.6667 | L34: 7828.15 | M34: =(F34+G34)*0.62 -> 73573.333 | N34: 3800 | O34: 0 | T34: 3800 | U34: =IF(C34="oui","",(H34+I34)*E34) -> 29666.667 | W34: =IF(O34="",0,(1-E34)*O34) -> 0 | X34: =IF(O34="",I34*(E34),0) -> 0 | Y34: =IF(P34="",+H34*6%*E34,0) -> 1780 | Z34: =IF(P34="",0,P34*(1-E34)) -> 0 | AA34: =IF(Q34="",+H34*2.5%*E34,0) -> 741.66667 | AB34: =IF(Q34="",0,Q34*(1-E34)) -> 0 | AC34: =IF(R34="",+L34*E34,(1-E34)*R34) -> 1957.0375 | AD34: =IF(S34="",M34*E34,S34*E34) -> 18393.333 | AF34: =IF(E34="",0,+H34-J34-K34-L34-M34-N34) -> 23378.517 | AG34: =IFERROR((VLOOKUP(B34,'SUIVI 31.12.24 ALTONEO'!$B$1:$BF$38,33,FALSE())),0) -> 0 | AH34: =AF34*E34-AG34 -> 5844.6292 | AI34: =IF(E34="",0,H34) -> 118666.67 | AJ34: =IFERROR((VLOOKUP(B34,'SUIVI 31.12.24 ALTONEO'!$B$1:$BF$38,36,FALSE())),0) -> 0 | AK34: =AI34*E34-AJ34 -> 29666.667 | AO34: =IF(E34=0,0,AI34-AJ34-AK34) -> 89000 | AP34: =IF(E34=0,0,AF34-AG34-AH34) -> 17533.887 | AQ34: =IF(E34="","",+AF34/AI34) -> 0.19700997 | AR34: =IF(S34="",M34*E34,S34*E34) -> 18393.333 | AS34: =IFERROR((VLOOKUP(B34,'SUIVI 31.12.24 ALTONEO'!$B$1:$BF$38,45,FALSE())),0) -> 0 | AT34: =+AR34-AS34 -> 18393.333 | AU34: =+L34*E34 -> 1957.0375 | AV34: =IFERROR((VLOOKUP(B34,'SUIVI 31.12.24 ALTONEO'!$B$1:$BF$38,48,FALSE())),0) -> 0 | AW34: =+AU34-AV34 -> 1957.0375 | AX34: =IF(P34="",J34*E34,P34-Z34) -> 1780 | AY34: =IFERROR((VLOOKUP(B34,'SUIVI 31.12.24 ALTONEO'!$B$1:$BF$38,51,FALSE())),0) -> 0 | AZ34: =+AX34-AY34 -> 1780 | BA34: =IF(Q34="",K34*E34,Q34-AB34) -> 741.66667 | BB34: =IFERROR((VLOOKUP(B34,'SUIVI 31.12.24 ALTONEO'!$B$1:$BF$38,54,FALSE())),0) -> 0 | BC34: =+BA34-BB34 -> 741.66667 | BD34: =+E34*N34 -> 950 | BE34: =IFERROR((VLOOKUP(B34,'SUIVI 31.12.24 ALTONEO'!$B$1:$BF$38,57,FALSE())),0) -> 0
B35: Projet Cardoso / Ryckewaert Epuisay | C35: non | D35: 5. Achèvement des murs | E35: =VLOOKUP(D35,'% avancement'!$A$5:$B$17,2,FALSE()) -> 0.6 | F35: =153300/1.2 -> 127750 | G35: =12561/1.2 -> 10467.5 | H35: =F35+G35-I35 -> 133217.5 | I35: 5000 | J35: 8659.14 | K35: 3330.44 | L35: 7828.15 | M35: 82736.3 | N35: 6000 | O35: 5000 | T35: 6000 | U35: =IF(C35="oui","",(H35+I35)*E35) -> 82930.5 | W35: =IF(O35="",0,(1-E35)*O35) -> 2000 | X35: =IF(O35="",I35*(E35),0) -> 0 | Y35: =IF(P35="",+H35*6%*E35,0) -> 4795.83 | Z35: =IF(P35="",0,P35*(1-E35)) -> 0 | AA35: =IF(Q35="",+H35*2.5%*E35,0) -> 1998.2625 | AB35: =IF(Q35="",0,Q35*(1-E35)) -> 0 | AC35: =IF(R35="",+L35*E35,(1-E35)*R35) -> 4696.89 | AD35: =IF(S35="",M35*E35,S35*E35) -> 49641.78 | AF35: =IF(E35="",0,+H35-J35-K35-L35-M35-N35) -> 24663.47 | AG35: =IFERROR((VLOOKUP(B35,'SUIVI 31.12.24 ALTONEO'!$B$1:$BF$38,33,FALSE())),0) -> 0 | AH35: =AF35*E35-AG35 -> 14798.082 | AI35: =IF(E35="",0,H35) -> 133217.5 | AJ35: =IFERROR((VLOOKUP(B35,'SUIVI 31.12.24 ALTONEO'!$B$1:$BF$38,36,FALSE())),0) -> 0 | AK35: =AI35*E35-AJ35 -> 79930.5 | AO35: =IF(E35=0,0,AI35-AJ35-AK35) -> 53287 | AP35: =IF(E35=0,0,AF35-AG35-AH35) -> 9865.388 | AQ35: =IF(E35="","",+AF35/AI35) -> 0.18513686 | AR35: =IF(S35="",M35*E35,S35*E35) -> 49641.78 | AS35: =IFERROR((VLOOKUP(B35,'SUIVI 31.12.24 ALTONEO'!$B$1:$BF$38,45,FALSE())),0) -> 0 | AT35: =+AR35-AS35 -> 49641.78 | AU35: =+L35*E35 -> 4696.89 | AV35: =IFERROR((VLOOKUP(B35,'SUIVI 31.12.24 ALTONEO'!$B$1:$BF$38,48,FALSE())),0) -> 0 | AW35: =+AU35-AV35 -> 4696.89 | AX35: =IF(P35="",J35*E35,P35-Z35) -> 5195.484 | AY35: =IFERROR((VLOOKUP(B35,'SUIVI 31.12.24 ALTONEO'!$B$1:$BF$38,51,FALSE())),0) -> 0 | AZ35: =+AX35-AY35 -> 5195.484 | BA35: =IF(Q35="",K35*E35,Q35-AB35) -> 1998.264 | BB35: =IFERROR((VLOOKUP(B35,'SUIVI 31.12.24 ALTONEO'!$B$1:$BF$38,54,FALSE())),0) -> 0 | BC35: =+BA35-BB35 -> 1998.264 | BD35: =+E35*N35 -> 3600 | BE35: =IFERROR((VLOOKUP(B35,'SUIVI 31.12.24 ALTONEO'!$B$1:$BF$38,57,FALSE())),0) -> 0
B36: Projet Journaux / Thinard Meurcé | C36: non | D36: 5. Achèvement des murs | E36: =VLOOKUP(D36,'% avancement'!$A$5:$B$17,2,FALSE()) -> 0.6 | F36: 116416.67 | G36: 20345 | H36: =F36+G36-I36 -> 131761.67 | I36: 5000 | J36: 8564.5083 | K36: 3294.0417 | L36: 7828.15 | M36: 82093.95 | N36: 6000 | O36: 5000 | P36: 8564.5083 | Q36: 3294.0417 | R36: 7828.15 | T36: 6000 | U36: =IF(C36="oui","",(H36+I36)*E36) -> 82057 | W36: =IF(O36="",0,(1-E36)*O36) -> 2000 | X36: =IF(O36="",I36*(E36),0) -> 0 | Y36: =IF(P36="",+H36*6%*E36,0) -> 0 | Z36: =IF(P36="",0,P36*(1-E36)) -> 3425.8033 | AA36: =IF(Q36="",+H36*2.5%*E36,0) -> 0 | AB36: =IF(Q36="",0,Q36*(1-E36)) -> 1317.6167 | AC36: =IF(R36="",+L36*E36,(1-E36)*R36) -> 3131.26 | AD36: =IF(S36="",M36*E36,S36*E36) -> 49256.37 | AF36: =IF(E36="",0,+H36-J36-K36-L36-M36-N36) -> 23981.017 | AG36: =IFERROR((VLOOKUP(B36,'SUIVI 31.12.24 ALTONEO'!$B$1:$BF$38,33,FALSE())),0) -> 0 | AH36: =AF36*E36-AG36 -> 14388.61 | AI36: =IF(E36="",0,H36) -> 131761.67 | AJ36: =IFERROR((VLOOKUP(B36,'SUIVI 31.12.24 ALTONEO'!$B$1:$BF$38,36,FALSE())),0) -> 0 | AK36: =AI36*E36-AJ36 -> 79057 | AO36: =IF(E36=0,0,AI36-AJ36-AK36) -> 52704.667 | AP36: =IF(E36=0,0,AF36-AG36-AH36) -> 9592.4067 | AQ36: =IF(E36="","",+AF36/AI36) -> 0.18200299 | AR36: =IF(S36="",M36*E36,S36*E36) -> 49256.37 | AS36: =IFERROR((VLOOKUP(B36,'SUIVI 31.12.24 ALTONEO'!$B$1:$BF$38,45,FALSE())),0) -> 0 | AT36: =+AR36-AS36 -> 49256.37 | AU36: =+L36*E36 -> 4696.89 | AV36: =IFERROR((VLOOKUP(B36,'SUIVI 31.12.24 ALTONEO'!$B$1:$BF$38,48,FALSE())),0) -> 0 | AW36: =+AU36-AV36 -> 4696.89 | AX36: =IF(P36="",J36*E36,P36-Z36) -> 5138.705 | AY36: =IFERROR((VLOOKUP(B36,'SUIVI 31.12.24 ALTONEO'!$B$1:$BF$38,51,FALSE())),0) -> 0 | AZ36: =+AX36-AY36 -> 5138.705 | BA36: =IF(Q36="",K36*E36,Q36-AB36) -> 1976.425 | BB36: =IFERROR((VLOOKUP(B36,'SUIVI 31.12.24 ALTONEO'!$B$1:$BF$38,54,FALSE())),0) -> 0 | BC36: =+BA36-BB36 -> 1976.425 | BD36: =+E36*N36 -> 3600 | BE36: =IFERROR((VLOOKUP(B36,'SUIVI 31.12.24 ALTONEO'!$B$1:$BF$38,57,FALSE())),0) -> 0
B37: Projet Moreau / Moreau Montfort Le Gesnois | C37: non | D37: 4. Assurances | E37: =VLOOKUP(D37,'% avancement'!$A$5:$B$17,2,FALSE()) -> 0.4 | F37: 142333 | G37: 9400 | H37: =F37+G37-I37 -> 146733 | I37: 5000 | J37: 9537.6667 | K37: 3668.3333 | L37: 7828.15 | M37: 95038.15 | N37: 6000 | O37: 5000 | P37: 9537.6667 | Q37: 3668.3333 | R37: 7828.15 | T37: 6000 | U37: =IF(C37="oui","",(H37+I37)*E37) -> 60693.2 | W37: =IF(O37="",0,(1-E37)*O37) -> 3000 | X37: =IF(O37="",I37*(E37),0) -> 0 | Y37: =IF(P37="",+H37*6%*E37,0) -> 0 | Z37: =IF(P37="",0,P37*(1-E37)) -> 5722.6 | AA37: =IF(Q37="",+H37*2.5%*E37,0) -> 0 | AB37: =IF(Q37="",0,Q37*(1-E37)) -> 2201 | AC37: =IF(R37="",+L37*E37,(1-E37)*R37) -> 4696.89 | AD37: =IF(S37="",M37*E37,S37*E37) -> 38015.26 | AF37: =IF(E37="",0,+H37-J37-K37-L37-M37-N37) -> 24660.7 | AG37: =IFERROR((VLOOKUP(B37,'SUIVI 31.12.24 ALTONEO'!$B$1:$BF$38,33,FALSE())),0) -> 0 | AH37: =AF37*E37-AG37 -> 9864.28 | AI37: =IF(E37="",0,H37) -> 146733 | AJ37: =IFERROR((VLOOKUP(B37,'SUIVI 31.12.24 ALTONEO'!$B$1:$BF$38,36,FALSE())),0) -> 0 | AK37: =AI37*E37-AJ37 -> 58693.2 | AO37: =IF(E37=0,0,AI37-AJ37-AK37) -> 88039.8 | AP37: =IF(E37=0,0,AF37-AG37-AH37) -> 14796.42 | AQ37: =IF(E37="","",+AF37/AI37) -> 0.16806513 | AR37: =IF(S37="",M37*E37,S37*E37) -> 38015.26 | AS37: =IFERROR((VLOOKUP(B37,'SUIVI 31.12.24 ALTONEO'!$B$1:$BF$38,45,FALSE())),0) -> 0 | AT37: =+AR37-AS37 -> 38015.26 | AU37: =+L37*E37 -> 3131.26 | AV37: =IFERROR((VLOOKUP(B37,'SUIVI 31.12.24 ALTONEO'!$B$1:$BF$38,48,FALSE())),0) -> 0 | AW37: =+AU37-AV37 -> 3131.26 | AX37: =IF(P37="",J37*E37,P37-Z37) -> 3815.0667 | AY37: =IFERROR((VLOOKUP(B37,'SUIVI 31.12.24 ALTONEO'!$B$1:$BF$38,51,FALSE())),0) -> 0 | AZ37: =+AX37-AY37 -> 3815.0667 | BA37: =IF(Q37="",K37*E37,Q37-AB37) -> 1467.3333 | BB37: =IFERROR((VLOOKUP(B37,'SUIVI 31.12.24 ALTONEO'!$B$1:$BF$38,54,FALSE())),0) -> 0 | BC37: =+BA37-BB37 -> 1467.3333 | BD37: =+E37*N37 -> 2400 | BE37: =IFERROR((VLOOKUP(B37,'SUIVI 31.12.24 ALTONEO'!$B$1:$BF$38,57,FALSE())),0) -> 0
B38: Projet Toin / Brault Saint Remy De Sillé | C38: non | D38: 1.1 Administratif validé prêt à ouvrir | E38: =VLOOKUP(D38,'% avancement'!$A$5:$B$17,2,FALSE()) -> 0.25 | F38: =131200/1.2 -> 109333.33 | G38: =14494/1.2 -> 12078.333 | H38: =F38+G38-I38 -> 116411.67 | I38: 5000 | J38: =9080.11/1.2 -> 7566.7583 | K38: =3495.35/1.2 -> 2912.7917 | L38: 7828.15 | M38: 69859.57 | N38: 6000 | O38: 5000 | T38: 6000 | U38: =IF(C38="oui","",(H38+I38)*E38) -> 30352.917 | W38: =IF(O38="",0,(1-E38)*O38) -> 3750 | X38: =IF(O38="",I38*(E38),0) -> 0 | Y38: =IF(P38="",+H38*6%*E38,0) -> 1746.175 | Z38: =IF(P38="",0,P38*(1-E38)) -> 0 | AA38: =IF(Q38="",+H38*2.5%*E38,0) -> 727.57292 | AB38: =IF(Q38="",0,Q38*(1-E38)) -> 0 | AC38: =IF(R38="",+L38*E38,(1-E38)*R38) -> 1957.0375 | AD38: =IF(S38="",M38*E38,S38*E38) -> 17464.893 | AF38: =IF(E38="",0,+H38-J38-K38-L38-M38-N38) -> 22244.397 | AG38: =IFERROR((VLOOKUP(B38,'SUIVI 31.12.24 ALTONEO'!$B$1:$BF$38,33,FALSE())),0) -> 0 | AH38: =AF38*E38-AG38 -> 5561.0992 | AI38: =IF(E38="",0,H38) -> 116411.67 | AJ38: =IFERROR((VLOOKUP(B38,'SUIVI 31.12.24 ALTONEO'!$B$1:$BF$38,36,FALSE())),0) -> 0 | AK38: =AI38*E38-AJ38 -> 29102.917 | AO38: =IF(E38=0,0,AI38-AJ38-AK38) -> 87308.75 | AP38: =IF(E38=0,0,AF38-AG38-AH38) -> 16683.298 | AQ38: =IF(E38="","",+AF38/AI38) -> 0.19108391 | AR38: =IF(S38="",M38*E38,S38*E38) -> 17464.893 | AS38: =IFERROR((VLOOKUP(B38,'SUIVI 31.12.24 ALTONEO'!$B$1:$BF$38,45,FALSE())),0) -> 0 | AT38: =+AR38-AS38 -> 17464.893 | AU38: =+L38*E38 -> 1957.0375 | AV38: =IFERROR((VLOOKUP(B38,'SUIVI 31.12.24 ALTONEO'!$B$1:$BF$38,48,FALSE())),0) -> 0 | AW38: =+AU38-AV38 -> 1957.0375 | AX38: =IF(P38="",J38*E38,P38-Z38) -> 1891.6896 | AY38: =IFERROR((VLOOKUP(B38,'SUIVI 31.12.24 ALTONEO'!$B$1:$BF$38,51,FALSE())),0) -> 0 | AZ38: =+AX38-AY38 -> 1891.6896 | BA38: =IF(Q38="",K38*E38,Q38-AB38) -> 728.19792 | BB38: =IFERROR((VLOOKUP(B38,'SUIVI 31.12.24 ALTONEO'!$B$1:$BF$38,54,FALSE())),0) -> 0 | BC38: =+BA38-BB38 -> 728.19792 | BD38: =+E38*N38 -> 1500 | BE38: =IFERROR((VLOOKUP(B38,'SUIVI 31.12.24 ALTONEO'!$B$1:$BF$38,57,FALSE())),0) -> 0
B39: =+ROWS(B3:B38) -> 36 | AO39: =IF(E39=0,0,AI39-AJ39-AK39) -> 0 | AP39: =IF(E39=0,0,AF39-AG39-AH39) -> 0
A40: Chantiers N Livrés N | B40: Projet Tilliet / Pecqueur Vaas | C40: non | D40: 6. Mise hors d'eau | E40: =VLOOKUP(D40,'% avancement'!$A$5:$B$17,2,FALSE()) -> 0.8 | F40: 133916.67 | G40: 11215 | H40: =F40+G40-I40 -> 140131.67 | I40: 5000 | J40: 8331.4 | K40: 3471.42 | L40: 7828.15 | M40: 87352.8 | N40: 6000 | O40: 5000 | P40: 8331.4 | Q40: 3471.42 | R40: 7828.15 | T40: 6000 | U40: =IF(C40="oui","",(H40+I40)*E40) -> 116105.33 | W40: =IF(O40="",0,(1-E40)*O40) -> 1000 | X40: =IF(O40="",I40*(E40),0) -> 0 | Y40: =IF(P40="",+H40*6%*E40,0) -> 0 | Z40: =IF(P40="",0,P40*(1-E40)) -> 1666.28 | AA40: =IF(Q40="",+H40*2.5%*E40,0) -> 0 | AB40: =IF(Q40="",0,Q40*(1-E40)) -> 694.284 | AC40: =IF(R40="",+L40*E40,(1-E40)*R40) -> 1565.63 | AD40: =IF(S40="",M40*E40,S40*E40) -> 69882.24 | AF40: =IF(E40="",0,+H40-J40-K40-L40-M40-N40) -> 27147.897 | AG40: =IFERROR((VLOOKUP(B40,'SUIVI 31.12.24 ALTONEO'!$B$1:$BF$38,33,FALSE())),0) -> 0 | AH40: =AF40*E40-AG40 -> 21718.317 | AI40: =IF(E40="",0,H40) -> 140131.67 | AJ40: =IFERROR((VLOOKUP(B40,'SUIVI 31.12.24 ALTONEO'!$B$1:$BF$38,36,FALSE())),0) -> 0 | AK40: =AI40*E40-AJ40 -> 112105.33 | AO40: =IF(E40=0,0,AI40-AJ40-AK40) -> 28026.333 | AP40: =IF(E40=0,0,AF40-AG40-AH40) -> 5429.5793 | AQ40: =IF(E40="","",+AF40/AI40) -> 0.19373135 | AR40: =IF(S40="",M40*E40,S40*E40) -> 69882.24 | AS40: =IFERROR((VLOOKUP(B40,'SUIVI 31.12.24 ALTONEO'!$B$1:$BF$38,45,FALSE())),0) -> 0 | AT40: =+AR40-AS40 -> 69882.24 | AU40: =+L40*E40 -> 6262.52 | AV40: =IFERROR((VLOOKUP(B40,'SUIVI 31.12.24 ALTONEO'!$B$1:$BF$38,48,FALSE())),0) -> 0 | AW40: =+AU40-AV40 -> 6262.52 | AX40: =IF(P40="",J40*E40,P40-Z40) -> 6665.12 | AY40: =IFERROR((VLOOKUP(B40,'SUIVI 31.12.24 ALTONEO'!$B$1:$BF$38,51,FALSE())),0) -> 0 | AZ40: =+AX40-AY40 -> 6665.12 | BA40: =IF(Q40="",K40*E40,Q40-AB40) -> 2777.136 | BB40: =IFERROR((VLOOKUP(B40,'SUIVI 31.12.24 ALTONEO'!$B$1:$BF$38,54,FALSE())),0) -> 0 | BC40: =+BA40-BB40 -> 2777.136 | BD40: =+E40*N40 -> 4800 | BE40: =IFERROR((VLOOKUP(B40,'SUIVI 31.12.24 ALTONEO'!$B$1:$BF$38,57,FALSE())),0) -> 0
B41: Projet Ikia / La Ferté Bernard | C41: non | D41: 1.1 Administratif validé prêt à ouvrir | E41: =VLOOKUP(D41,'% avancement'!$A$5:$B$17,2,FALSE()) -> 0.25 | F41: =118000/1.2 -> 98333.333 | G41: =7545/1.2 -> 6287.5 | H41: =F41+G41-I41 -> 99620.833 | I41: 5000 | J41: =(F41+G41-I41)*0.065 -> 6475.3542 | K41: =(F41+G41-I41)*0.025 -> 2490.5208 | L41: 7828.15 | M41: 57880 | N41: 6000 | O41: 5000 | T41: 6000 | U41: =IF(C41="oui","",(H41+I41)*E41) -> 26155.208 | W41: =IF(O41="",0,(1-E41)*O41) -> 3750 | X41: =IF(O41="",I41*(E41),0) -> 0 | Y41: =IF(P41="",+H41*6%*E41,0) -> 1494.3125 | Z41: =IF(P41="",0,P41*(1-E41)) -> 0 | AA41: =IF(Q41="",+H41*2.5%*E41,0) -> 622.63021 | AB41: =IF(Q41="",0,Q41*(1-E41)) -> 0 | AC41: =IF(R41="",+L41*E41,(1-E41)*R41) -> 1957.0375 | AD41: =IF(S41="",M41*E41,S41*E41) -> 14470 | AF41: =IF(E41="",0,+H41-J41-K41-L41-M41-N41) -> 18946.808 | AG41: =IFERROR((VLOOKUP(B41,'SUIVI 31.12.24 ALTONEO'!$B$1:$BF$38,33,FALSE())),0) -> 0 | AH41: =AF41*E41-AG41 -> 4736.7021 | AI41: =IF(E41="",0,H41) -> 99620.833 | AJ41: =IFERROR((VLOOKUP(B41,'SUIVI 31.12.24 ALTONEO'!$B$1:$BF$38,36,FALSE())),0) -> 0 | AK41: =AI41*E41-AJ41 -> 24905.208 | AO41: =IF(E41=0,0,AI41-AJ41-AK41) -> 74715.625 | AP41: =IF(E41=0,0,AF41-AG41-AH41) -> 14210.106 | AQ41: =IF(E41="","",+AF41/AI41) -> 0.19018922 | AR41: =IF(S41="",M41*E41,S41*E41) -> 14470 | AS41: =IFERROR((VLOOKUP(B41,'SUIVI 31.12.24 ALTONEO'!$B$1:$BF$38,45,FALSE())),0) -> 0 | AT41: =+AR41-AS41 -> 14470 | AU41: =+L41*E41 -> 1957.0375 | AV41: =IFERROR((VLOOKUP(B41,'SUIVI 31.12.24 ALTONEO'!$B$1:$BF$38,48,FALSE())),0) -> 0 | AW41: =+AU41-AV41 -> 1957.0375 | AX41: =IF(P41="",J41*E41,P41-Z41) -> 1618.8385 | AY41: =IFERROR((VLOOKUP(B41,'SUIVI 31.12.24 ALTONEO'!$B$1:$BF$38,51,FALSE())),0) -> 0 | AZ41: =+AX41-AY41 -> 1618.8385 | BA41: =IF(Q41="",K41*E41,Q41-AB41) -> 622.63021 | BB41: =IFERROR((VLOOKUP(B41,'SUIVI 31.12.24 ALTONEO'!$B$1:$BF$38,54,FALSE())),0) -> 0 | BC41: =+BA41-BB41 -> 622.63021 | BD41: =+E41*N41 -> 1500 | BE41: =IFERROR((VLOOKUP(B41,'SUIVI 31.12.24 ALTONEO'!$B$1:$BF$38,57,FALSE())),0) -> 0
B42: Projet Bernard / Bernard Meurcé | C42: non | D42: 6. Mise hors d'eau | E42: =VLOOKUP(D42,'% avancement'!$A$5:$B$17,2,FALSE()) -> 0.8 | F42: 134000 | G42: 7462.5 | H42: =F42+G42-I42 -> 136462.5 | I42: 5000 | J42: 8187.75 | K42: 1705.78 | L42: 7828.15 | M42: 89134.3 | N42: 6000 | O42: 5000 | P42: 8187.75 | Q42: 1705.78 | R42: 7828.15 | T42: 6000 | U42: =IF(C42="oui","",(H42+I42)*E42) -> 113170 | W42: =IF(O42="",0,(1-E42)*O42) -> 1000 | X42: =IF(O42="",I42*(E42),0) -> 0 | Y42: =IF(P42="",+H42*6%*E42,0) -> 0 | Z42: =IF(P42="",0,P42*(1-E42)) -> 1637.55 | AA42: =IF(Q42="",+H42*2.5%*E42,0) -> 0 | AB42: =IF(Q42="",0,Q42*(1-E42)) -> 341.156 | AC42: =IF(R42="",+L42*E42,(1-E42)*R42) -> 1565.63 | AD42: =IF(S42="",M42*E42,S42*E42) -> 71307.44 | AF42: =IF(E42="",0,+H42-J42-K42-L42-M42-N42) -> 23606.52 | AG42: =IFERROR((VLOOKUP(B42,'SUIVI 31.12.24 ALTONEO'!$B$1:$BF$38,33,FALSE())),0) -> 0 | AH42: =AF42*E42-AG42 -> 18885.216 | AI42: =IF(E42="",0,H42) -> 136462.5 | AJ42: =IFERROR((VLOOKUP(B42,'SUIVI 31.12.24 ALTONEO'!$B$1:$BF$38,36,FALSE())),0) -> 0 | AK42: =AI42*E42-AJ42 -> 109170 | AO42: =IF(E42=0,0,AI42-AJ42-AK42) -> 27292.5 | AP42: =IF(E42=0,0,AF42-AG42-AH42) -> 4721.304 | AQ42: =IF(E42="","",+AF42/AI42) -> 0.17298906 | AR42: =IF(S42="",M42*E42,S42*E42) -> 71307.44 | AS42: =IFERROR((VLOOKUP(B42,'SUIVI 31.12.24 ALTONEO'!$B$1:$BF$38,45,FALSE())),0) -> 0 | AT42: =+AR42-AS42 -> 71307.44 | AU42: =+L42*E42 -> 6262.52 | AV42: =IFERROR((VLOOKUP(B42,'SUIVI 31.12.24 ALTONEO'!$B$1:$BF$38,48,FALSE())),0) -> 0 | AW42: =+AU42-AV42 -> 6262.52 | AX42: =IF(P42="",J42*E42,P42-Z42) -> 6550.2 | AY42: =IFERROR((VLOOKUP(B42,'SUIVI 31.12.24 ALTONEO'!$B$1:$BF$38,51,FALSE())),0) -> 0 | AZ42: =+AX42-AY42 -> 6550.2 | BA42: =IF(Q42="",K42*E42,Q42-AB42) -> 1364.624 | BB42: =IFERROR((VLOOKUP(B42,'SUIVI 31.12.24 ALTONEO'!$B$1:$BF$38,54,FALSE())),0) -> 0 | BC42: =+BA42-BB42 -> 1364.624 | BD42: =+E42*N42 -> 4800 | BE42: =IFERROR((VLOOKUP(B42,'SUIVI 31.12.24 ALTONEO'!$B$1:$BF$38,57,FALSE())),0) -> 0
B43: Projet Pluquin / Girard Valframbert | C43: non | D43: 6. Mise hors d'eau | E43: =VLOOKUP(D43,'% avancement'!$A$5:$B$17,2,FALSE()) -> 0.8 | F43: 134333.33 | G43: 7478.3333 | H43: =F43+G43-I43 -> 136811.67 | I43: 5000 | J43: 8208.7 | K43: 3420.29 | L43: 7828.15 | M43: 78867.86 | N43: 6000 | O43: 5000 | P43: 8208.7 | Q43: 3420.29 | R43: 7828.15 | T43: 6000 | U43: =IF(C43="oui","",(H43+I43)*E43) -> 113449.33 | W43: =IF(O43="",0,(1-E43)*O43) -> 1000 | X43: =IF(O43="",I43*(E43),0) -> 0 | Y43: =IF(P43="",+H43*6%*E43,0) -> 0 | Z43: =IF(P43="",0,P43*(1-E43)) -> 1641.74 | AA43: =IF(Q43="",+H43*2.5%*E43,0) -> 0 | AB43: =IF(Q43="",0,Q43*(1-E43)) -> 684.058 | AC43: =IF(R43="",+L43*E43,(1-E43)*R43) -> 1565.63 | AD43: =IF(S43="",M43*E43,S43*E43) -> 63094.288 | AF43: =IF(E43="",0,+H43-J43-K43-L43-M43-N43) -> 32486.667 | AG43: =IFERROR((VLOOKUP(B43,'SUIVI 31.12.24 ALTONEO'!$B$1:$BF$38,33,FALSE())),0) -> 0 | AH43: =AF43*E43-AG43 -> 25989.333 | AI43: =IF(E43="",0,H43) -> 136811.67 | AJ43: =IFERROR((VLOOKUP(B43,'SUIVI 31.12.24 ALTONEO'!$B$1:$BF$38,36,FALSE())),0) -> 0 | AK43: =AI43*E43-AJ43 -> 109449.33 | AO43: =IF(E43=0,0,AI43-AJ43-AK43) -> 27362.333 | AP43: =IF(E43=0,0,AF43-AG43-AH43) -> 6497.3333 | AQ43: =IF(E43="","",+AF43/AI43) -> 0.23745538 | AR43: =IF(S43="",M43*E43,S43*E43) -> 63094.288 | AS43: =IFERROR((VLOOKUP(B43,'SUIVI 31.12.24 ALTONEO'!$B$1:$BF$38,45,FALSE())),0) -> 0 | AT43: =+AR43-AS43 -> 63094.288 | AU43: =+L43*E43 -> 6262.52 | AV43: =IFERROR((VLOOKUP(B43,'SUIVI 31.12.24 ALTONEO'!$B$1:$BF$38,48,FALSE())),0) -> 0 | AW43: =+AU43-AV43 -> 6262.52 | AX43: =IF(P43="",J43*E43,P43-Z43) -> 6566.96 | AY43: =IFERROR((VLOOKUP(B43,'SUIVI 31.12.24 ALTONEO'!$B$1:$BF$38,51,FALSE())),0) -> 0 | AZ43: =+AX43-AY43 -> 6566.96 | BA43: =IF(Q43="",K43*E43,Q43-AB43) -> 2736.232 | BB43: =IFERROR((VLOOKUP(B43,'SUIVI 31.12.24 ALTONEO'!$B$1:$BF$38,54,FALSE())),0) -> 0 | BC43: =+BA43-BB43 -> 2736.232 | BD43: =+E43*N43 -> 4800 | BE43: =IFERROR((VLOOKUP(B43,'SUIVI 31.12.24 ALTONEO'!$B$1:$BF$38,57,FALSE())),0) -> 0
B44: Projet Cordola / Ouvrard Longnes | C44: oui | D44: 9. Réception | E44: =VLOOKUP(D44,'% avancement'!$A$5:$B$17,2,FALSE()) -> 1 | F44: 113166.67 | G44: 6352.5 | H44: =F44+G44-I44 -> 114519.17 | I44: 5000 | J44: 6871.15 | K44: 1431.49 | L44: 7828.15 | M44: 69147.94 | N44: 6000 | O44: 5000 | P44: 6871.15 | Q44: 1431.49 | R44: 7828.15 | S44: 69147.94 | T44: 6000 | U44: =IF(C44="oui","",(H44+I44)*E44) | W44: =IF(O44="",0,(1-E44)*O44) -> 0 | X44: =IF(O44="",I44*(E44),0) -> 0 | Y44: =IF(P44="",+H44*6%*E44,0) -> 0 | Z44: =IF(P44="",0,P44*(1-E44)) -> 0 | AA44: =IF(Q44="",+H44*2.5%*E44,0) -> 0 | AB44: =IF(Q44="",0,Q44*(1-E44)) -> 0 | AC44: =IF(R44="",+L44*E44,(1-E44)*R44) -> 0 | AD44: =IF(S44="",M44*E44,S44*E44) -> 69147.94 | AF44: =IF(E44="",0,+H44-J44-K44-L44-M44-N44) -> 23240.437 | AG44: =IFERROR((VLOOKUP(B44,'SUIVI 31.12.24 ALTONEO'!$B$1:$BF$38,33,FALSE())),0) -> 0 | AH44: =AF44*E44-AG44 -> 23240.437 | AI44: =IF(E44="",0,H44) -> 114519.17 | AJ44: =IFERROR((VLOOKUP(B44,'SUIVI 31.12.24 ALTONEO'!$B$1:$BF$38,36,FALSE())),0) -> 0 | AK44: =AI44*E44-AJ44 -> 114519.17 | AO44: =IF(E44=0,0,AI44-AJ44-AK44) -> 0 | AP44: =IF(E44=0,0,AF44-AG44-AH44) -> 0 | AQ44: =IF(E44="","",+AF44/AI44) -> 0.20293928 | AR44: =IF(S44="",M44*E44,S44*E44) -> 69147.94 | AS44: =IFERROR((VLOOKUP(B44,'SUIVI 31.12.24 ALTONEO'!$B$1:$BF$38,45,FALSE())),0) -> 0 | AT44: =+AR44-AS44 -> 69147.94 | AU44: =+L44*E44 -> 7828.15 | AV44: =IFERROR((VLOOKUP(B44,'SUIVI 31.12.24 ALTONEO'!$B$1:$BF$38,48,FALSE())),0) -> 0 | AW44: =+AU44-AV44 -> 7828.15 | AX44: =IF(P44="",J44*E44,P44-Z44) -> 6871.15 | AY44: =IFERROR((VLOOKUP(B44,'SUIVI 31.12.24 ALTONEO'!$B$1:$BF$38,51,FALSE())),0) -> 0 | AZ44: =+AX44-AY44 -> 6871.15 | BA44: =IF(Q44="",K44*E44,Q44-AB44) -> 1431.49 | BB44: =IFERROR((VLOOKUP(B44,'SUIVI 31.12.24 ALTONEO'!$B$1:$BF$38,54,FALSE())),0) -> 0 | BC44: =+BA44-BB44 -> 1431.49 | BD44: =+E44*N44 -> 6000 | BE44: =IFERROR((VLOOKUP(B44,'SUIVI 31.12.24 ALTONEO'!$B$1:$BF$38,57,FALSE())),0) -> 0
B45: Chantier Adame / Saïd Neuville sur Sarthe | C45: oui | D45: 9. Réception | E45: =VLOOKUP(D45,'% avancement'!$A$5:$B$17,2,FALSE()) -> 1 | F45: 129333.33 | G45: 8087.5 | H45: =F45+G45-I45 -> 132420.83 | I45: 5000 | J45: =(F45+G45-I45)*0.06 -> 7945.25 | K45: 1655.26 | L45: 7828.15 | M45: 81535.09 | N45: 6000 | O45: 5000 | P45: 7945.25 | Q45: 1655.26 | R45: 7828.15 | S45: 81535.09 | T45: 6000 | U45: =IF(C45="oui","",(H45+I45)*E45) | W45: =IF(O45="",0,(1-E45)*O45) -> 0 | X45: =IF(O45="",I45*(E45),0) -> 0 | Y45: =IF(P45="",+H45*6%*E45,0) -> 0 | Z45: =IF(P45="",0,P45*(1-E45)) -> 0 | AA45: =IF(Q45="",+H45*2.5%*E45,0) -> 0 | AB45: =IF(Q45="",0,Q45*(1-E45)) -> 0 | AC45: =IF(R45="",+L45*E45,(1-E45)*R45) -> 0 | AD45: =IF(S45="",M45*E45,S45*E45) -> 81535.09 | AF45: =IF(E45="",0,+H45-J45-K45-L45-M45-N45) -> 27457.083 | AG45: =IFERROR((VLOOKUP(B45,'SUIVI 31.12.24 ALTONEO'!$B$1:$BF$38,33,FALSE())),0) -> 0 | AH45: =AF45*E45-AG45 -> 27457.083 | AI45: =IF(E45="",0,H45) -> 132420.83 | AJ45: =IFERROR((VLOOKUP(B45,'SUIVI 31.12.24 ALTONEO'!$B$1:$BF$38,36,FALSE())),0) -> 0 | AK45: =AI45*E45-AJ45 -> 132420.83 | AO45: =IF(E45=0,0,AI45-AJ45-AK45) -> 0 | AP45: =IF(E45=0,0,AF45-AG45-AH45) -> 0 | AQ45: =IF(E45="","",+AF45/AI45) -> 0.20734716 | AR45: =IF(S45="",M45*E45,S45*E45) -> 81535.09 | AS45: =IFERROR((VLOOKUP(B45,'SUIVI 31.12.24 ALTONEO'!$B$1:$BF$38,45,FALSE())),0) -> 0 | AT45: =+AR45-AS45 -> 81535.09 | AU45: =+L45*E45 -> 7828.15 | AV45: =IFERROR((VLOOKUP(B45,'SUIVI 31.12.24 ALTONEO'!$B$1:$BF$38,48,FALSE())),0) -> 0 | AW45: =+AU45-AV45 -> 7828.15 | AX45: =IF(P45="",J45*E45,P45-Z45) -> 7945.25 | AY45: =IFERROR((VLOOKUP(B45,'SUIVI 31.12.24 ALTONEO'!$B$1:$BF$38,51,FALSE())),0) -> 0 | AZ45: =+AX45-AY45 -> 7945.25 | BA45: =IF(Q45="",K45*E45,Q45-AB45) -> 1655.26 | BB45: =IFERROR((VLOOKUP(B45,'SUIVI 31.12.24 ALTONEO'!$B$1:$BF$38,54,FALSE())),0) -> 0 | BC45: =+BA45-BB45 -> 1655.26 | BD45: =+E45*N45 -> 6000 | BE45: =IFERROR((VLOOKUP(B45,'SUIVI 31.12.24 ALTONEO'!$B$1:$BF$38,57,FALSE())),0) -> 0
B46: =+ROWS(B40:B45) -> 6 | AP46: =IF(E46=0,0,AF46-AG46-AH46) -> 0
A47: Chantiers N-1 Livrés N | B47: Chantier Renard Volnay | C47: oui | D47: 9. Réception | E47: =VLOOKUP(D47,'% avancement'!$A$5:$B$17,2,FALSE()) -> 1 | F47: 118666.67 | G47: 4031.67 | H47: =F47+G47-I47 -> 122698.34 | I47: 0 | J47: 8834.28 | K47: 1840.48 | L47: 7828.15 | M47: 78169.29 | N47: 6000 | O47: 0 | P47: 8834.28 | Q47: 1840.48 | R47: 7828.15 | S47: 78169.29 | T47: 6000 | U47: =IF(C47="oui","",(H47+I47)*E47) | W47: =IF(O47="",0,(1-E47)*O47) -> 0 | X47: =IF(O47="",I47*(E47),0) -> 0 | Y47: =IF(P47="",+H47*6%*E47,0) -> 0 | Z47: =IF(P47="",0,P47*(1-E47)) -> 0 | AA47: =IF(Q47="",+H47*2.5%*E47,0) -> 0 | AB47: =IF(Q47="",0,Q47*(1-E47)) -> 0 | AC47: =IF(R47="",+L47*E47,(1-E47)*R47) -> 0 | AD47: =IF(S47="",M47*E47,S47*E47) -> 78169.29 | AF47: =IF(E47="",0,+H47-J47-K47-L47-M47-N47) -> 20026.137 | AG47: =IFERROR((VLOOKUP(B47,'SUIVI 31.12.24 ALTONEO'!$B$1:$BF$38,33,FALSE())),0) -> 5776.3033 | AH47: =AF47*E47-AG47 -> 14249.833 | AI47: =IF(E47="",0,H47) -> 122698.34 | AJ47: =IFERROR((VLOOKUP(B47,'SUIVI 31.12.24 ALTONEO'!$B$1:$BF$38,36,FALSE())),0) -> 24733.333 | AK47: =AI47*E47-AJ47 -> 97965.003 | AO47: =AI47-AJ47-AK47 -> 0 | AP47: =IF(E47=0,0,AF47-AG47-AH47) -> 0 | AQ47: =IF(E47="","",+AF47/AI47) -> 0.16321441 | AR47: =IF(S47="",M47*E47,S47*E47) -> 78169.29 | AS47: =IFERROR((VLOOKUP(B47,'SUIVI 31.12.24 ALTONEO'!$B$1:$BF$38,45,FALSE())),0) -> 15334.667 | AT47: =+AR47-AS47 -> 62834.623 | AU47: =+L47*E47 -> 7828.15 | AV47: =IFERROR((VLOOKUP(B47,'SUIVI 31.12.24 ALTONEO'!$B$1:$BF$38,48,FALSE())),0) -> 1520.03 | AW47: =+AU47-AV47 -> 6308.12 | AX47: =IF(P47="",J47*E47,P47-Z47) -> 8834.28 | AY47: =IFERROR((VLOOKUP(B47,'SUIVI 31.12.24 ALTONEO'!$B$1:$BF$38,51,FALSE())),0) -> 1484 | AZ47: =+AX47-AY47 -> 7350.28 | BA47: =IF(Q47="",K47*E47,Q47-AB47) -> 1840.48 | BB47: =IFERROR((VLOOKUP(B47,'SUIVI 31.12.24 ALTONEO'!$B$1:$BF$38,54,FALSE())),0) -> 618.33333 | BC47: =+BA47-BB47 -> 1222.1467 | BD47: =+E47*N47 -> 6000 | BE47: =IFERROR((VLOOKUP(B47,'SUIVI 31.12.24 ALTONEO'!$B$1:$BF$38,57,FALSE())),0) -> 0
B48: Chantier Furia / Vivoin | C48: oui | D48: 9. Réception | E48: =VLOOKUP(D48,'% avancement'!$A$5:$B$17,2,FALSE()) -> 1 | F48: 117916.67 | G48: 8827.35 | H48: =F48+G48-I48 -> 121744.02 | I48: 5000 | J48: 8545.98 | K48: 1780.42 | L48: 7828.15 | M48: 72289.93 | N48: 6000 | O48: 5000 | P48: 8545.98 | Q48: 1780.42 | R48: 7828.15 | S48: 72289.93 | T48: 6000 | U48: =IF(C48="oui","",(H48+I48)*E48) | W48: =IF(O48="",0,(1-E48)*O48) -> 0 | X48: =IF(O48="",I48*(E48),0) -> 0 | Y48: =IF(P48="",+H48*6%*E48,0) -> 0 | Z48: =IF(P48="",0,P48*(1-E48)) -> 0 | AA48: =IF(Q48="",+H48*2.5%*E48,0) -> 0 | AB48: =IF(Q48="",0,Q48*(1-E48)) -> 0 | AC48: =IF(R48="",+L48*E48,(1-E48)*R48) -> 0 | AD48: =IF(S48="",M48*E48,S48*E48) -> 72289.93 | AF48: =IF(E48="",0,+H48-J48-K48-L48-M48-N48) -> 25299.537 | AG48: =IFERROR((VLOOKUP(B48,'SUIVI 31.12.24 ALTONEO'!$B$1:$BF$38,33,FALSE())),0) -> 9634.1067 | AH48: =AF48*E48-AG48 -> 15665.43 | AI48: =IF(E48="",0,H48) -> 121744.02 | AJ48: =IFERROR((VLOOKUP(B48,'SUIVI 31.12.24 ALTONEO'!$B$1:$BF$38,36,FALSE())),0) -> 47166.667 | AK48: =AI48*E48-AJ48 -> 74577.35 | AO48: =AI48-AJ48-AK48 -> 0 | AP48: =IF(E48=0,0,AF48-AG48-AH48) -> 0 | AQ48: =IF(E48="","",+AF48/AI48) -> 0.20780928 | AR48: =IF(S48="",M48*E48,S48*E48) -> 72289.93 | AS48: =IFERROR((VLOOKUP(B48,'SUIVI 31.12.24 ALTONEO'!$B$1:$BF$38,45,FALSE())),0) -> 30483.333 | AT48: =+AR48-AS48 -> 41806.597 | AU48: =+L48*E48 -> 7828.15 | AV48: =IFERROR((VLOOKUP(B48,'SUIVI 31.12.24 ALTONEO'!$B$1:$BF$38,48,FALSE())),0) -> 3040.06 | AW48: =+AU48-AV48 -> 4788.09 | AX48: =IF(P48="",J48*E48,P48-Z48) -> 8545.98 | AY48: =IFERROR((VLOOKUP(B48,'SUIVI 31.12.24 ALTONEO'!$B$1:$BF$38,51,FALSE())),0) -> 2848.66 | AZ48: =+AX48-AY48 -> 5697.32 | BA48: =IF(Q48="",K48*E48,Q48-AB48) -> 1780.42 | BB48: =IFERROR((VLOOKUP(B48,'SUIVI 31.12.24 ALTONEO'!$B$1:$BF$38,54,FALSE())),0) -> 593.472 | BC48: =+BA48-BB48 -> 1186.948 | BD48: =+E48*N48 -> 6000 | BE48: =IFERROR((VLOOKUP(B48,'SUIVI 31.12.24 ALTONEO'!$B$1:$BF$38,57,FALSE())),0) -> 0
B49: Chantier Lepetit / Ménagé Fercé sur Sarthe | C49: oui | D49: 9. Réception | E49: =VLOOKUP(D49,'% avancement'!$A$5:$B$17,2,FALSE()) -> 1 | F49: 135750 | G49: 9886.13 | H49: =F49+G49-I49 -> 139386.13 | I49: 6250 | J49: 9871.56 | K49: 2056.57 | L49: 7828.15 | M49: 88371.58 | N49: 6000 | O49: 6250 | P49: 9871.56 | Q49: 2056.57 | R49: 7828.15 | S49: 88371.58 | T49: 6000 | U49: =IF(C49="oui","",(H49+I49)*E49) | W49: =IF(O49="",0,(1-E49)*O49) -> 0 | X49: =IF(O49="",I49*(E49),0) -> 0 | Y49: =IF(P49="",+H49*6%*E49,0) -> 0 | Z49: =IF(P49="",0,P49*(1-E49)) -> 0 | AA49: =IF(Q49="",+H49*2.5%*E49,0) -> 0 | AB49: =IF(Q49="",0,Q49*(1-E49)) -> 0 | AC49: =IF(R49="",+L49*E49,(1-E49)*R49) -> 0 | AD49: =IF(S49="",M49*E49,S49*E49) -> 88371.58 | AF49: =IF(E49="",0,+H49-J49-K49-L49-M49-N49) -> 25258.27 | AG49: =IFERROR((VLOOKUP(B49,'SUIVI 31.12.24 ALTONEO'!$B$1:$BF$38,33,FALSE())),0) -> 11738.44 | AH49: =AF49*E49-AG49 -> 13519.83 | AI49: =IF(E49="",0,H49) -> 139386.13 | AJ49: =IFERROR((VLOOKUP(B49,'SUIVI 31.12.24 ALTONEO'!$B$1:$BF$38,36,FALSE())),0) -> 54300 | AK49: =AI49*E49-AJ49 -> 85086.13 | AO49: =AI49-AJ49-AK49 -> 0 | AP49: =IF(E49=0,0,AF49-AG49-AH49) -> 0 | AQ49: =IF(E49="","",+AF49/AI49) -> 0.18121078 | AR49: =IF(S49="",M49*E49,S49*E49) -> 88371.58 | AS49: =IFERROR((VLOOKUP(B49,'SUIVI 31.12.24 ALTONEO'!$B$1:$BF$38,45,FALSE())),0) -> 34906 | AT49: =+AR49-AS49 -> 53465.58 | AU49: =+L49*E49 -> 7828.15 | AV49: =IFERROR((VLOOKUP(B49,'SUIVI 31.12.24 ALTONEO'!$B$1:$BF$38,48,FALSE())),0) -> 3040.06 | AW49: =+AU49-AV49 -> 4788.09 | AX49: =IF(P49="",J49*E49,P49-Z49) -> 9871.56 | AY49: =IFERROR((VLOOKUP(B49,'SUIVI 31.12.24 ALTONEO'!$B$1:$BF$38,51,FALSE())),0) -> 3258 | AZ49: =+AX49-AY49 -> 6613.56 | BA49: =IF(Q49="",K49*E49,Q49-AB49) -> 2056.57 | BB49: =IFERROR((VLOOKUP(B49,'SUIVI 31.12.24 ALTONEO'!$B$1:$BF$38,54,FALSE())),0) -> 1357.5 | BC49: =+BA49-BB49 -> 699.07 | BD49: =+E49*N49 -> 6000 | BE49: =IFERROR((VLOOKUP(B49,'SUIVI 31.12.24 ALTONEO'!$B$1:$BF$38,57,FALSE())),0) -> 0
B50: Chantier Attané / Attané Ecommoy | C50: oui | D50: 9. Réception | E50: =VLOOKUP(D50,'% avancement'!$A$5:$B$17,2,FALSE()) -> 1 | F50: 119002 | G50: 5723 | H50: =F50+G50-I50 -> 119725 | I50: 5000 | J50: 6818.33 | K50: 1420.83 | L50: 7600.15 | M50: 69085.95 | N50: 6000 | O50: 5000 | P50: 6818.33 | Q50: 1420.83 | R50: 7600.15 | S50: 69085.95 | T50: 6000 | U50: =IF(C50="oui","",(H50+I50)*E50) | W50: =IF(O50="",0,(1-E50)*O50) -> 0 | X50: =IF(O50="",I50*(E50),0) -> 0 | Y50: =IF(P50="",+H50*6%*E50,0) -> 0 | Z50: =IF(P50="",0,P50*(1-E50)) -> 0 | AA50: =IF(Q50="",+H50*2.5%*E50,0) -> 0 | AB50: =IF(Q50="",0,Q50*(1-E50)) -> 0 | AC50: =IF(R50="",+L50*E50,(1-E50)*R50) -> 0 | AD50: =IF(S50="",M50*E50,S50*E50) -> 69085.95 | AF50: =IF(E50="",0,+H50-J50-K50-L50-M50-N50) -> 28799.74 | AG50: =IFERROR((VLOOKUP(B50,'SUIVI 31.12.24 ALTONEO'!$B$1:$BF$38,33,FALSE())),0) -> 8222.476 | AH50: =AF50*E50-AG50 -> 20577.264 | AI50: =IF(E50="",0,H50) -> 119725 | AJ50: =IFERROR((VLOOKUP(B50,'SUIVI 31.12.24 ALTONEO'!$B$1:$BF$38,36,FALSE())),0) -> 47890 | AK50: =AI50*E50-AJ50 -> 71835 | AO50: =AI50-AJ50-AK50 -> 0 | AP50: =IF(E50=0,0,AF50-AG50-AH50) -> 0 | AQ50: =IF(E50="","",+AF50/AI50) -> 0.24054909 | AR50: =IF(S50="",M50*E50,S50*E50) -> 69085.95 | AS50: =IFERROR((VLOOKUP(B50,'SUIVI 31.12.24 ALTONEO'!$B$1:$BF$38,45,FALSE())),0) -> 30931.8 | AT50: =+AR50-AS50 -> 38154.15 | AU50: =+L50*E50 -> 7600.15 | AV50: =IFERROR((VLOOKUP(B50,'SUIVI 31.12.24 ALTONEO'!$B$1:$BF$38,48,FALSE())),0) -> 3040.06 | AW50: =+AU50-AV50 -> 4560.09 | AX50: =IF(P50="",J50*E50,P50-Z50) -> 6818.33 | AY50: =IFERROR((VLOOKUP(B50,'SUIVI 31.12.24 ALTONEO'!$B$1:$BF$38,51,FALSE())),0) -> 2727.332 | AZ50: =+AX50-AY50 -> 4090.998 | BA50: =IF(Q50="",K50*E50,Q50-AB50) -> 1420.83 | BB50: =IFERROR((VLOOKUP(B50,'SUIVI 31.12.24 ALTONEO'!$B$1:$BF$38,54,FALSE())),0) -> 568.332 | BC50: =+BA50-BB50 -> 852.498 | BD50: =+E50*N50 -> 6000 | BE50: =IFERROR((VLOOKUP(B50,'SUIVI 31.12.24 ALTONEO'!$B$1:$BF$38,57,FALSE())),0) -> 2400 | BF50: =+BD50-BE50 -> 3600
B51: Chantier Kong / Luy Vivoin | C51: oui | D51: 9. Réception | E51: =VLOOKUP(D51,'% avancement'!$A$5:$B$17,2,FALSE()) -> 1 | F51: 120621.96 | G51: 6664.41 | H51: =120622-I51 -> 115622 | I51: 5000 | J51: =8187/1.2 -> 6822.5 | K51: =1706/1.2 -> 1421.6667 | L51: 7600.15 | M51: 70635.11 | N51: 6000 | O51: 5000 | P51: 6822.5 | Q51: 1421.6667 | R51: 7600 | S51: 70635.11 | T51: 6000 | U51: =IF(C51="oui","",(H51+I51)*E51) | W51: =IF(O51="",0,(1-E51)*O51) -> 0 | X51: =IF(O51="",I51*(E51),0) -> 0 | Y51: =IF(P51="",+H51*6%*E51,0) -> 0 | Z51: =IF(P51="",0,P51*(1-E51)) -> 0 | AA51: =IF(Q51="",+H51*2.5%*E51,0) -> 0 | AB51: =IF(Q51="",0,Q51*(1-E51)) -> 0 | AC51: =IF(R51="",+L51*E51,(1-E51)*R51) -> 0 | AD51: =IF(S51="",M51*E51,S51*E51) -> 70635.11 | AF51: =IF(E51="",0,+H51-J51-K51-L51-M51-N51) -> 23142.573 | AG51: =IFERROR((VLOOKUP(B51,'SUIVI 31.12.24 ALTONEO'!$B$1:$BF$38,33,FALSE())),0) -> 18514.059 | AH51: =AF51*E51-AG51 -> 4628.5147 | AI51: =IF(E51="",0,H51) -> 115622 | AJ51: =IFERROR((VLOOKUP(B51,'SUIVI 31.12.24 ALTONEO'!$B$1:$BF$38,36,FALSE())),0) -> 92497.6 | AK51: =AI51*E51-AJ51 -> 23124.4 | AO51: =AI51-AJ51-AK51 -> 0 | AP51: =IF(E51=0,0,AF51-AG51-AH51) -> 0 | AQ51: =IF(E51="","",+AF51/AI51) -> 0.20015718 | AR51: =IF(S51="",M51*E51,S51*E51) -> 70635.11 | AS51: =IFERROR((VLOOKUP(B51,'SUIVI 31.12.24 ALTONEO'!$B$1:$BF$38,45,FALSE())),0) -> 56508.088 | AT51: =+AR51-AS51 -> 14127.022 | AU51: =+L51*E51 -> 7600.15 | AV51: =IFERROR((VLOOKUP(B51,'SUIVI 31.12.24 ALTONEO'!$B$1:$BF$38,48,FALSE())),0) -> 6080.12 | AW51: =+AU51-AV51 -> 1520.03 | AX51: =IF(P51="",J51*E51,P51-Z51) -> 6822.5 | AY51: =IFERROR((VLOOKUP(B51,'SUIVI 31.12.24 ALTONEO'!$B$1:$BF$38,51,FALSE())),0) -> 5458 | AZ51: =+AX51-AY51 -> 1364.5 | BA51: =IF(Q51="",K51*E51,Q51-AB51) -> 1421.6667 | BB51: =IFERROR((VLOOKUP(B51,'SUIVI 31.12.24 ALTONEO'!$B$1:$BF$38,54,FALSE())),0) -> 1137.3333 | BC51: =+BA51-BB51 -> 284.33333 | BD51: =+E51*N51 -> 6000 | BE51: =IFERROR((VLOOKUP(B51,'SUIVI 31.12.24 ALTONEO'!$B$1:$BF$38,57,FALSE())),0) -> 4800 | BF51: =+BD51-BE51 -> 1200
B52: Projet Froger / Saint-Ouen-en-Belin | C52: oui | D52: 9. Réception | E52: =VLOOKUP(D52,'% avancement'!$A$5:$B$17,2,FALSE()) -> 1 | F52: 122333.33 | G52: 5385.84 | H52: =F52+G52-I52 -> 122719.17 | I52: 5000 | J52: 8835.78 | K52: 1840.79 | L52: 7828.15 | M52: 79666.4 | N52: 6000 | O52: 5000 | P52: 7363.15 | Q52: 1533.99 | R52: 7828.15 | S52: 79666.4 | T52: 6000 | U52: =IF(C52="oui","",(H52+I52)*E52) | W52: =IF(O52="",0,(1-E52)*O52) -> 0 | X52: =IF(O52="",I52*(E52),0) -> 0 | Y52: =IF(P52="",+H52*6%*E52,0) -> 0 | Z52: =IF(P52="",0,P52*(1-E52)) -> 0 | AA52: =IF(Q52="",+H52*2.5%*E52,0) -> 0 | AB52: =IF(Q52="",0,Q52*(1-E52)) -> 0 | AC52: =IF(R52="",+L52*E52,(1-E52)*R52) -> 0 | AD52: =IF(S52="",M52*E52,S52*E52) -> 79666.4 | AF52: =IF(E52="",0,+H52-J52-K52-L52-M52-N52) -> 18548.053 | AG52: =IFERROR((VLOOKUP(B52,'SUIVI 31.12.24 ALTONEO'!$B$1:$BF$38,33,FALSE())),0) -> 5077.6367 | AH52: =AF52*E52-AG52 -> 13470.417 | AI52: =IF(E52="",0,H52) -> 122719.17 | AJ52: =IFERROR((VLOOKUP(B52,'SUIVI 31.12.24 ALTONEO'!$B$1:$BF$38,36,FALSE())),0) -> 24466.667 | AK52: =AI52*E52-AJ52 -> 98252.507 | AO52: =AI52-AJ52-AK52 -> 0 | AP52: =IF(E52=0,0,AF52-AG52-AH52) -> 0 | AQ52: =IF(E52="","",+AF52/AI52) -> 0.15114226 | AR52: =IF(S52="",M52*E52,S52*E52) -> 79666.4 | AS52: =IFERROR((VLOOKUP(B52,'SUIVI 31.12.24 ALTONEO'!$B$1:$BF$38,45,FALSE())),0) -> 15789.333 | AT52: =+AR52-AS52 -> 63877.067 | AU52: =+L52*E52 -> 7828.15 | AV52: =IFERROR((VLOOKUP(B52,'SUIVI 31.12.24 ALTONEO'!$B$1:$BF$38,48,FALSE())),0) -> 1520.03 | AW52: =+AU52-AV52 -> 6308.12 | AX52: =IF(P52="",J52*E52,P52-Z52) -> 7363.15 | AY52: =IFERROR((VLOOKUP(B52,'SUIVI 31.12.24 ALTONEO'!$B$1:$BF$38,51,FALSE())),0) -> 1468 | AZ52: =+AX52-AY52 -> 5895.15 | BA52: =IF(Q52="",K52*E52,Q52-AB52) -> 1533.99 | BB52: =IFERROR((VLOOKUP(B52,'SUIVI 31.12.24 ALTONEO'!$B$1:$BF$38,54,FALSE())),0) -> 611.66667 | BC52: =+BA52-BB52 -> 922.32333 | BD52: =+E52*N52 -> 6000 | BE52: =IFERROR((VLOOKUP(B52,'SUIVI 31.12.24 ALTONEO'!$B$1:$BF$38,57,FALSE())),0) -> 0
B53: Chantier Ségouin / Ségouin Vivoin | C53: oui | D53: 9. Réception | E53: =VLOOKUP(D53,'% avancement'!$A$5:$B$17,2,FALSE()) -> 1 | F53: =+H53-G53 -> 132500.65 | G53: =7658/1.2 -> 6381.6667 | H53: 138882.32 | I53: 5000 | J53: 7867.5 | K53: 1639.15 | L53: 7600.15 | M53: 87259 | N53: 6000 | O53: 5000 | P53: 7867.5 | Q53: 1639.15 | R53: 7600 | S53: 87259 | T53: 6000 | U53: =IF(C53="oui","",(H53+I53)*E53) | W53: =IF(O53="",0,(1-E53)*O53) -> 0 | X53: =IF(O53="",I53*(E53),0) -> 0 | Y53: =IF(P53="",+H53*6%*E53,0) -> 0 | Z53: =IF(P53="",0,P53*(1-E53)) -> 0 | AA53: =IF(Q53="",+H53*2.5%*E53,0) -> 0 | AB53: =IF(Q53="",0,Q53*(1-E53)) -> 0 | AC53: =IF(R53="",+L53*E53,(1-E53)*R53) -> 0 | AD53: =IF(S53="",M53*E53,S53*E53) -> 87259 | AF53: =IF(E53="",0,+H53-J53-K53-L53-M53-N53) -> 28516.52 | AG53: =IFERROR((VLOOKUP(B53,'SUIVI 31.12.24 ALTONEO'!$B$1:$BF$38,33,FALSE())),0) -> 11406.608 | AH53: =AF53*E53-AG53 -> 17109.912 | AI53: =IF(E53="",0,H53) -> 138882.32 | AJ53: =IFERROR((VLOOKUP(B53,'SUIVI 31.12.24 ALTONEO'!$B$1:$BF$38,36,FALSE())),0) -> 55552.928 | AK53: =AI53*E53-AJ53 -> 83329.392 | AO53: =AI53-AJ53-AK53 -> 0 | AP53: =IF(E53=0,0,AF53-AG53-AH53) -> 0 | AQ53: =IF(E53="","",+AF53/AI53) -> 0.20532866 | AR53: =IF(S53="",M53*E53,S53*E53) -> 87259 | AS53: =IFERROR((VLOOKUP(B53,'SUIVI 31.12.24 ALTONEO'!$B$1:$BF$38,45,FALSE())),0) -> 34903.6 | AT53: =+AR53-AS53 -> 52355.4 | AU53: =+L53*E53 -> 7600.15 | AV53: =IFERROR((VLOOKUP(B53,'SUIVI 31.12.24 ALTONEO'!$B$1:$BF$38,48,FALSE())),0) -> 3040.06 | AW53: =+AU53-AV53 -> 4560.09 | AX53: =IF(P53="",J53*E53,P53-Z53) -> 7867.5 | AY53: =IFERROR((VLOOKUP(B53,'SUIVI 31.12.24 ALTONEO'!$B$1:$BF$38,51,FALSE())),0) -> 3147 | AZ53: =+AX53-AY53 -> 4720.5 | BA53: =IF(Q53="",K53*E53,Q53-AB53) -> 1639.15 | BB53: =IFERROR((VLOOKUP(B53,'SUIVI 31.12.24 ALTONEO'!$B$1:$BF$38,54,FALSE())),0) -> 655.66 | BC53: =+BA53-BB53 -> 983.49 | BD53: =+E53*N53 -> 6000 | BE53: =IFERROR((VLOOKUP(B53,'SUIVI 31.12.24 ALTONEO'!$B$1:$BF$38,57,FALSE())),0) -> 2400 | BF53: =+BD53-BE53 -> 3600
B54: Chantier Poulio / Mulsanne | C54: oui | D54: 9. Réception | E54: =VLOOKUP(D54,'% avancement'!$A$5:$B$17,2,FALSE()) -> 1 | F54: 102000 | G54: 5440 | H54: =F54+G54-I54 -> 102440 | I54: 5000 | J54: 7375.68 | K54: 1536.6 | L54: 7828.15 | M54: 63184.33 | N54: 6000 | O54: 5000 | P54: 6146.4 | Q54: 1280.5 | R54: 7828.15 | S54: 64712.33 | T54: 6000 | U54: =IF(C54="oui","",(H54+I54)*E54) | W54: =IF(O54="",0,(1-E54)*O54) -> 0 | X54: =IF(O54="",I54*(E54),0) -> 0 | Y54: =IF(P54="",+H54*6%*E54,0) -> 0 | Z54: =IF(P54="",0,P54*(1-E54)) -> 0 | AA54: =IF(Q54="",+H54*2.5%*E54,0) -> 0 | AB54: =IF(Q54="",0,Q54*(1-E54)) -> 0 | AC54: =IF(R54="",+L54*E54,(1-E54)*R54) -> 0 | AD54: =IF(S54="",M54*E54,S54*E54) -> 64712.33 | AF54: =IF(E54="",0,+H54-J54-K54-L54-M54-N54) -> 16515.24 | AG54: =IFERROR((VLOOKUP(B54,'SUIVI 31.12.24 ALTONEO'!$B$1:$BF$38,33,FALSE())),0) -> 0 | AH54: =AF54*E54-AG54 -> 16515.24 | AI54: =IF(E54="",0,H54) -> 102440 | AJ54: =IFERROR((VLOOKUP(B54,'SUIVI 31.12.24 ALTONEO'!$B$1:$BF$38,36,FALSE())),0) -> 0 | AK54: =AI54*E54-AJ54 -> 102440 | AO54: =AI54-AJ54-AK54 -> 0 | AP54: =IF(E54=0,0,AF54-AG54-AH54) -> 0 | AQ54: =IF(E54="","",+AF54/AI54) -> 0.16121866 | AR54: =IF(S54="",M54*E54,S54*E54) -> 64712.33 | AS54: =IFERROR((VLOOKUP(B54,'SUIVI 31.12.24 ALTONEO'!$B$1:$BF$38,45,FALSE())),0) -> 0 | AT54: =+AR54-AS54 -> 64712.33 | AU54: =+L54*E54 -> 7828.15 | AV54: =IFERROR((VLOOKUP(B54,'SUIVI 31.12.24 ALTONEO'!$B$1:$BF$38,48,FALSE())),0) -> 0 | AW54: =+AU54-AV54 -> 7828.15 | AX54: =IF(P54="",J54*E54,P54-Z54) -> 6146.4 | AY54: =IFERROR((VLOOKUP(B54,'SUIVI 31.12.24 ALTONEO'!$B$1:$BF$38,51,FALSE())),0) -> 0 | AZ54: =+AX54-AY54 -> 6146.4 | BA54: =IF(Q54="",K54*E54,Q54-AB54) -> 1280.5 | BB54: =IFERROR((VLOOKUP(B54,'SUIVI 31.12.24 ALTONEO'!$B$1:$BF$38,54,FALSE())),0) -> 0 | BC54: =+BA54-BB54 -> 1280.5 | BD54: =+E54*N54 -> 6000 | BE54: =IFERROR((VLOOKUP(B54,'SUIVI 31.12.24 ALTONEO'!$B$1:$BF$38,57,FALSE())),0) -> 0
B55: Projet Diallo / Diallo Ecommoy | C55: oui | D55: 9. Réception | E55: =VLOOKUP(D55,'% avancement'!$A$5:$B$17,2,FALSE()) -> 1 | F55: 106000 | G55: 7495.83 | H55: =F55+G55-I55 -> 108495.83 | I55: 5000 | J55: 6509.75 | K55: 1356.2 | L55: 7828.15 | M55: 64237.51 | N55: 6000 | O55: 5000 | P55: 6509.75 | Q55: 1356.2 | R55: 7828.15 | S55: 64237.51 | T55: 6000 | U55: =IF(C55="oui","",(H55+I55)*E55) | W55: =IF(O55="",0,(1-E55)*O55) -> 0 | X55: =IF(O55="",I55*(E55),0) -> 0 | Y55: =IF(P55="",+H55*6%*E55,0) -> 0 | Z55: =IF(P55="",0,P55*(1-E55)) -> 0 | AA55: =IF(Q55="",+H55*2.5%*E55,0) -> 0 | AB55: =IF(Q55="",0,Q55*(1-E55)) -> 0 | AC55: =IF(R55="",+L55*E55,(1-E55)*R55) -> 0 | AD55: =IF(S55="",M55*E55,S55*E55) -> 64237.51 | AF55: =IF(E55="",0,+H55-J55-K55-L55-M55-N55) -> 22564.22 | AG55: =IFERROR((VLOOKUP(B55,'SUIVI 31.12.24 ALTONEO'!$B$1:$BF$38,33,FALSE())),0) -> 4113.97 | AH55: =AF55*E55-AG55 -> 18450.25 | AI55: =IF(E55="",0,H55) -> 108495.83 | AK55: =AI55*E55-AJ55 -> 108495.83 | AO55: =AI55-AJ55-AK55 -> 0 | AP55: =IF(E55=0,0,AF55-AG55-AH55) -> 0 | AQ55: =IF(E55="","",+AF55/AI55) -> 0.20797315 | AR55: =IF(S55="",M55*E55,S55*E55) -> 64237.51 | AS55: =IFERROR((VLOOKUP(B55,'SUIVI 31.12.24 ALTONEO'!$B$1:$BF$38,45,FALSE())),0) -> 13764 | AT55: =+AR55-AS55 -> 50473.51 | AU55: =+L55*E55 -> 7828.15 | AV55: =IFERROR((VLOOKUP(B55,'SUIVI 31.12.24 ALTONEO'!$B$1:$BF$38,48,FALSE())),0) -> 1520.03 | AW55: =+AU55-AV55 -> 6308.12 | AX55: =IF(P55="",J55*E55,P55-Z55) -> 6509.75 | AY55: =IFERROR((VLOOKUP(B55,'SUIVI 31.12.24 ALTONEO'!$B$1:$BF$38,51,FALSE())),0) -> 1272 | AZ55: =+AX55-AY55 -> 5237.75 | BA55: =IF(Q55="",K55*E55,Q55-AB55) -> 1356.2 | BB55: =IFERROR((VLOOKUP(B55,'SUIVI 31.12.24 ALTONEO'!$B$1:$BF$38,54,FALSE())),0) -> 530 | BC55: =+BA55-BB55 -> 826.2 | BD55: =+E55*N55 -> 6000 | BE55: =IFERROR((VLOOKUP(B55,'SUIVI 31.12.24 ALTONEO'!$B$1:$BF$38,57,FALSE())),0) -> 0
B56: Projet Huet / Butet La Suze sur Sarthe | C56: oui | D56: 9. Réception | E56: =VLOOKUP(D56,'% avancement'!$A$5:$B$17,2,FALSE()) -> 1 | F56: 117250 | G56: 5940.8333 | H56: =F56+G56-I56 -> 118190.83 | I56: 5000 | J56: =(F56+G56-I56)*0.06 -> 7091.45 | K56: =(F56+G56-I56)*0.025 -> 2954.7708 | L56: 7828.15 | M56: =(F56+G56)*0.62 -> 76378.317 | N56: 6000 | O56: 5000 | P56: 7091.45 | Q56: 2954.77 | T56: 6000 | U56: =IF(C56="oui","",(H56+I56)*E56) | W56: =IF(O56="",0,(1-E56)*O56) -> 0 | X56: =IF(O56="",I56*(E56),0) -> 0 | Y56: =IF(P56="",+H56*6%*E56,0) -> 0 | Z56: =IF(P56="",0,P56*(1-E56)) -> 0 | AA56: =IF(Q56="",+H56*2.5%*E56,0) -> 0 | AB56: =IF(Q56="",0,Q56*(1-E56)) -> 0 | AC56: =IF(R56="",+L56*E56,(1-E56)*R56) -> 7828.15 | AD56: =IF(S56="",M56*E56,S56*E56) -> 76378.317 | AF56: =IF(E56="",0,+H56-J56-K56-L56-M56-N56) -> 17938.146 | AG56: =IFERROR((VLOOKUP(B56,'SUIVI 31.12.24 ALTONEO'!$B$1:$BF$38,33,FALSE())),0) -> 5972.15 | AH56: =AF56*E56-AG56 -> 11965.996 | AI56: =IF(E56="",0,H56) -> 118190.83 | AJ56: =IFERROR((VLOOKUP(B56,'SUIVI 31.12.24 ALTONEO'!$B$1:$BF$38,36,FALSE())),0) -> 29312.5 | AK56: =AI56*E56-AJ56 -> 88878.333 | AO56: =AI56-AJ56-AK56 -> 0 | AP56: =IF(E56=0,0,AF56-AG56-AH56) -> 0 | AQ56: =IF(E56="","",+AF56/AI56) -> 0.15177273 | AR56: =IF(S56="",M56*E56,S56*E56) -> 76378.317 | AS56: =IFERROR((VLOOKUP(B56,'SUIVI 31.12.24 ALTONEO'!$B$1:$BF$38,45,FALSE())),0) -> 18948.75 | AT56: =+AR56-AS56 -> 57429.567 | AU56: =+L56*E56 -> 7828.15 | AV56: =IFERROR((VLOOKUP(B56,'SUIVI 31.12.24 ALTONEO'!$B$1:$BF$38,48,FALSE())),0) -> 1900.0375 | AW56: =+AU56-AV56 -> 5928.1125 | AX56: =IF(P56="",J56*E56,P56-Z56) -> 7091.45 | AY56: =IFERROR((VLOOKUP(B56,'SUIVI 31.12.24 ALTONEO'!$B$1:$BF$38,51,FALSE())),0) -> 1758.75 | AZ56: =+AX56-AY56 -> 5332.7 | BA56: =IF(Q56="",K56*E56,Q56-AB56) -> 2954.77 | BB56: =IFERROR((VLOOKUP(B56,'SUIVI 31.12.24 ALTONEO'!$B$1:$BF$38,54,FALSE())),0) -> 732.8125 | BC56: =+BA56-BB56 -> 2221.9575 | BD56: =+E56*N56 -> 6000 | BE56: =IFERROR((VLOOKUP(B56,'SUIVI 31.12.24 ALTONEO'!$B$1:$BF$38,57,FALSE())),0) -> 0
B57: Projet Hugou / Hugou Villiers sur Loir | C57: non | D57: 6. Mise hors d'eau | E57: =VLOOKUP(D57,'% avancement'!$A$5:$B$17,2,FALSE()) -> 0.8 | F57: 137916.67 | G57: 6700 | H57: =F57+G57-I57 -> 139616.67 | I57: 5000 | J57: 8377 | K57: 3490.42 | L57: 7828.15 | M57: 97661.26 | N57: 6000 | O57: 5000 | P57: 8377 | Q57: 3490.42 | T57: 6000 | U57: =IF(C57="oui","",(H57+I57)*E57) -> 115693.33 | W57: =IF(O57="",0,(1-E57)*O57) -> 1000 | X57: =IF(O57="",I57*(E57),0) -> 0 | Y57: =IF(P57="",+H57*6%*E57,0) -> 0 | Z57: =IF(P57="",0,P57*(1-E57)) -> 1675.4 | AA57: =IF(Q57="",+H57*2.5%*E57,0) -> 0 | AB57: =IF(Q57="",0,Q57*(1-E57)) -> 698.084 | AC57: =IF(R57="",+L57*E57,(1-E57)*R57) -> 6262.52 | AD57: =IF(S57="",M57*E57,S57*E57) -> 78129.008 | AF57: =IF(E57="",0,+H57-J57-K57-L57-M57-N57) -> 16259.837 | AG57: =IFERROR((VLOOKUP(B57,'SUIVI 31.12.24 ALTONEO'!$B$1:$BF$38,33,FALSE())),0) -> 5997.0533 | AH57: =AF57*E57-AG57 -> 7010.816 | AI57: =IF(E57="",0,H57) -> 139616.67 | AJ57: =IFERROR((VLOOKUP(B57,'SUIVI 31.12.24 ALTONEO'!$B$1:$BF$38,36,FALSE())),0) -> 27583.333 | AK57: =AI57*E57-AJ57 -> 84110 | AO57: =AI57-AJ57-AK57 -> 27923.333 | AP57: =IF(E57=0,0,AF57-AG57-AH57) -> 3251.9673 | AQ57: =IF(E57="","",+AF57/AI57) -> 0.11646057 | AR57: =IF(S57="",M57*E57,S57*E57) -> 78129.008 | AS57: =IFERROR((VLOOKUP(B57,'SUIVI 31.12.24 ALTONEO'!$B$1:$BF$38,45,FALSE())),0) -> 17721.667 | AT57: =+AR57-AS57 -> 60407.341 | AU57: =+L57*E57 -> 6262.52 | AV57: =IFERROR((VLOOKUP(B57,'SUIVI 31.12.24 ALTONEO'!$B$1:$BF$38,48,FALSE())),0) -> 1520.03 | AW57: =+AU57-AV57 -> 4742.49 | AX57: =IF(P57="",J57*E57,P57-Z57) -> 6701.6 | AY57: =IFERROR((VLOOKUP(B57,'SUIVI 31.12.24 ALTONEO'!$B$1:$BF$38,51,FALSE())),0) -> 1655 | AZ57: =+AX57-AY57 -> 5046.6 | BA57: =IF(Q57="",K57*E57,Q57-AB57) -> 2792.336 | BB57: =IFERROR((VLOOKUP(B57,'SUIVI 31.12.24 ALTONEO'!$B$1:$BF$38,54,FALSE())),0) -> 689.58333 | BC57: =+BA57-BB57 -> 2102.7527 | BD57: =+E57*N57 -> 4800 | BE57: =IFERROR((VLOOKUP(B57,'SUIVI 31.12.24 ALTONEO'!$B$1:$BF$38,57,FALSE())),0) -> 0
B58: Projet Génot / Sceaux-sur-Huisne | C58: non | D58: 9. Réception | E58: =VLOOKUP(D58,'% avancement'!$A$5:$B$17,2,FALSE()) -> 1 | F58: 98166.667 | G58: 8174.17 | H58: =F58+G58-I58 -> 101340.84 | I58: 5000 | J58: 7296.54 | K58: 1520.11 | L58: 7828.15 | M58: 58750.08 | N58: 6000 | O58: 5000 | P58: 6080.45 | Q58: 1266.76 | R58: 7828.15 | S58: 58750.08 | T58: 6000 | U58: =IF(C58="oui","",(H58+I58)*E58) -> 106340.84 | W58: =IF(O58="",0,(1-E58)*O58) -> 0 | X58: =IF(O58="",I58*(E58),0) -> 0 | Y58: =IF(P58="",+H58*6%*E58,0) -> 0 | Z58: =IF(P58="",0,P58*(1-E58)) -> 0 | AA58: =IF(Q58="",+H58*2.5%*E58,0) -> 0 | AB58: =IF(Q58="",0,Q58*(1-E58)) -> 0 | AC58: =IF(R58="",+L58*E58,(1-E58)*R58) -> 0 | AD58: =IF(S58="",M58*E58,S58*E58) -> 58750.08 | AF58: =IF(E58="",0,+H58-J58-K58-L58-M58-N58) -> 19945.957 | AG58: =IFERROR((VLOOKUP(B58,'SUIVI 31.12.24 ALTONEO'!$B$1:$BF$38,33,FALSE())),0) -> 3651.8033 | AH58: =AF58*E58-AG58 -> 16294.153 | AI58: =IF(E58="",0,H58) -> 101340.84 | AJ58: =IFERROR((VLOOKUP(B58,'SUIVI 31.12.24 ALTONEO'!$B$1:$BF$38,36,FALSE())),0) -> 19633.333 | AK58: =AI58*E58-AJ58 -> 81707.503 | AO58: =AI58-AJ58-AK58 -> 0 | AP58: =IF(E58=0,0,AF58-AG58-AH58) -> 0 | AQ58: =IF(E58="","",+AF58/AI58) -> 0.19682052 | AR58: =IF(S58="",M58*E58,S58*E58) -> 58750.08 | AS58: =IFERROR((VLOOKUP(B58,'SUIVI 31.12.24 ALTONEO'!$B$1:$BF$38,45,FALSE())),0) -> 12792.667 | AT58: =+AR58-AS58 -> 45957.413 | AU58: =+L58*E58 -> 7828.15 | AV58: =IFERROR((VLOOKUP(B58,'SUIVI 31.12.24 ALTONEO'!$B$1:$BF$38,48,FALSE())),0) -> 1520.03 | AW58: =+AU58-AV58 -> 6308.12 | AX58: =IF(P58="",J58*E58,P58-Z58) -> 6080.45 | AY58: =IFERROR((VLOOKUP(B58,'SUIVI 31.12.24 ALTONEO'!$B$1:$BF$38,51,FALSE())),0) -> 1178 | AZ58: =+AX58-AY58 -> 4902.45 | BA58: =IF(Q58="",K58*E58,Q58-AB58) -> 1266.76 | BB58: =IFERROR((VLOOKUP(B58,'SUIVI 31.12.24 ALTONEO'!$B$1:$BF$38,54,FALSE())),0) -> 490.83333 | BC58: =+BA58-BB58 -> 775.92667 | BD58: =+E58*N58 -> 6000 | BE58: =IFERROR((VLOOKUP(B58,'SUIVI 31.12.24 ALTONEO'!$B$1:$BF$38,57,FALSE())),0) -> 0
B59: Chantier Maweze Kimba / Maweze Kimba Alençon | C59: oui | D59: 9. Réception | E59: =VLOOKUP(D59,'% avancement'!$A$5:$B$17,2,FALSE()) -> 1 | F59: 122642.29 | G59: 8687.59 | H59: =122642-I59 -> 117642 | I59: =6000/1.2 -> 5000 | J59: =8322.18/1.2 -> 6935.15 | K59: =1733.78/1.2 -> 1444.8167 | L59: 7600 | M59: 70635 | N59: 6000 | O59: 5000 | P59: 6935.15 | Q59: 1444.8167 | R59: 7600 | S59: 70635 | T59: 6000 | U59: =IF(C59="oui","",(H59+I59)*E59) | W59: =IF(O59="",0,(1-E59)*O59) -> 0 | X59: =IF(O59="",I59*(E59),0) -> 0 | Y59: =IF(P59="",+H59*6%*E59,0) -> 0 | Z59: =IF(P59="",0,P59*(1-E59)) -> 0 | AA59: =IF(Q59="",+H59*2.5%*E59,0) -> 0 | AB59: =IF(Q59="",0,Q59*(1-E59)) -> 0 | AC59: =IF(R59="",+L59*E59,(1-E59)*R59) -> 0 | AD59: =IF(S59="",M59*E59,S59*E59) -> 70635 | AF59: =IF(E59="",0,+H59-J59-K59-L59-M59-N59) -> 25027.033 | AG59: =IFERROR((VLOOKUP(B59,'SUIVI 31.12.24 ALTONEO'!$B$1:$BF$38,33,FALSE())),0) -> 20021.627 | AH59: =AF59*E59-AG59 -> 5005.4067 | AI59: =IF(E59="",0,H59) -> 117642 | AJ59: =IFERROR((VLOOKUP(B59,'SUIVI 31.12.24 ALTONEO'!$B$1:$BF$38,36,FALSE())),0) -> 94113.6 | AK59: =AI59*E59-AJ59 -> 23528.4 | AO59: =AI59-AJ59-AK59 -> 0 | AP59: =AF59-AG59-AH59 -> 0 | AQ59: =IF(E59="","",+AF59/AI59) -> 0.21273893 | AR59: =IF(S59="",M59*E59,S59*E59) -> 70635 | AS59: =IFERROR((VLOOKUP(B59,'SUIVI 31.12.24 ALTONEO'!$B$1:$BF$38,45,FALSE())),0) -> 56508 | AT59: =+AR59-AS59 -> 14127 | AU59: =+L59*E59 -> 7600 | AV59: =IFERROR((VLOOKUP(B59,'SUIVI 31.12.24 ALTONEO'!$B$1:$BF$38,48,FALSE())),0) -> 6080 | AW59: =+AU59-AV59 -> 1520 | AX59: =IF(P59="",J59*E59,P59-Z59) -> 6935.15 | AY59: =IFERROR((VLOOKUP(B59,'SUIVI 31.12.24 ALTONEO'!$B$1:$BF$38,51,FALSE())),0) -> 5548.12 | AZ59: =+AX59-AY59 -> 1387.03 | BA59: =IF(Q59="",K59*E59,Q59-AB59) -> 1444.8167 | BB59: =IFERROR((VLOOKUP(B59,'SUIVI 31.12.24 ALTONEO'!$B$1:$BF$38,54,FALSE())),0) -> 1155.8533 | BC59: =+BA59-BB59 -> 288.96333 | BD59: =+E59*N59 -> 6000 | BE59: =IFERROR((VLOOKUP(B59,'SUIVI 31.12.24 ALTONEO'!$B$1:$BF$38,57,FALSE())),0) -> 4800 | BF59: =+BD59-BE59 -> 1200
B60: Chantier Zai / Zai Alencon | C60: oui | D60: 9. Réception | E60: =VLOOKUP(D60,'% avancement'!$A$5:$B$17,2,FALSE()) -> 1 | F60: 133649 | G60: =10474/1.2 -> 8728.3333 | H60: =133650-I60 -> 128650 | I60: 5000 | J60: 7668 | K60: 1597.5 | L60: 7600.15 | M60: 81747 | N60: 6000 | O60: 5000 | P60: 7668 | Q60: 1597.5 | R60: 7600 | S60: 81747 | T60: 6000 | U60: =IF(C60="oui","",(H60+I60)*E60) | W60: =IF(O60="",0,(1-E60)*O60) -> 0 | X60: =IF(O60="",I60*(E60),0) -> 0 | Y60: =IF(P60="",+H60*6%*E60,0) -> 0 | Z60: =IF(P60="",0,P60*(1-E60)) -> 0 | AA60: =IF(Q60="",+H60*2.5%*E60,0) -> 0 | AB60: =IF(Q60="",0,Q60*(1-E60)) -> 0 | AC60: =IF(R60="",+L60*E60,(1-E60)*R60) -> 0 | AD60: =IF(S60="",M60*E60,S60*E60) -> 81747 | AF60: =IF(E60="",0,+H60-J60-K60-L60-M60-N60) -> 24037.35 | AG60: =IFERROR((VLOOKUP(B60,'SUIVI 31.12.24 ALTONEO'!$B$1:$BF$38,33,FALSE())),0) -> 14422.41 | AH60: =AF60*E60-AG60 -> 9614.94 | AI60: =IF(E60="",0,H60) -> 128650 | AJ60: =IFERROR((VLOOKUP(B60,'SUIVI 31.12.24 ALTONEO'!$B$1:$BF$38,36,FALSE())),0) -> 77190 | AK60: =AI60*E60-AJ60 -> 51460 | AO60: =AI60-AJ60-AK60 -> 0 | AP60: =AF60-AG60-AH60 -> 0 | AQ60: =IF(E60="","",+AF60/AI60) -> 0.18684298 | AR60: =IF(S60="",M60*E60,S60*E60) -> 81747 | AS60: =IFERROR((VLOOKUP(B60,'SUIVI 31.12.24 ALTONEO'!$B$1:$BF$38,45,FALSE())),0) -> 49048.2 | AT60: =+AR60-AS60 -> 32698.8 | AU60: =+L60*E60 -> 7600.15 | AV60: =IFERROR((VLOOKUP(B60,'SUIVI 31.12.24 ALTONEO'!$B$1:$BF$38,48,FALSE())),0) -> 4560.09 | AW60: =+AU60-AV60 -> 3040.06 | AX60: =IF(P60="",J60*E60,P60-Z60) -> 7668 | AY60: =IFERROR((VLOOKUP(B60,'SUIVI 31.12.24 ALTONEO'!$B$1:$BF$38,51,FALSE())),0) -> 4600.8 | AZ60: =+AX60-AY60 -> 3067.2 | BA60: =IF(Q60="",K60*E60,Q60-AB60) -> 1597.5 | BB60: =IFERROR((VLOOKUP(B60,'SUIVI 31.12.24 ALTONEO'!$B$1:$BF$38,54,FALSE())),0) -> 958.5 | BC60: =+BA60-BB60 -> 639 | BD60: =+E60*N60 -> 6000 | BE60: =IFERROR((VLOOKUP(B60,'SUIVI 31.12.24 ALTONEO'!$B$1:$BF$38,57,FALSE())),0) -> 3600 | BF60: =+BD60-BE60 -> 2400
A61: Sous-total | B61: =ROWS(B47:B60) -> 14
A62: Total | B62: =B46+B61 -> 20 | U62: =SUM(U3:U60) -> 1365788.7 | V62: =SUM(V3:V60) -> 0 | W62: =SUM(W3:W60) -> 26500 | X62: =SUM(X3:X60) -> 6250 | Y62: =SUM(Y3:Y60) -> 25118.227 | Z62: =SUM(Z3:Z60) -> 27557.128 | AA62: =SUM(AA3:AA60) -> 10465.928 | AB62: =SUM(AB3:AB60) -> 10469.953 | ... AP62: =SUM(AP3:AP60) -> 209226.26 | AQ62: =+AF62/AI62 -> 0.17318411 | AR62: =SUM(AR3:AR60) -> 1881454 | AS62: 174896.44 | AT62: =SUM(AT3:AT60) -> 1493813.8 | AU62: =SUM(AU3:AU60) -> 188301.08 | AV62: =SUM(AV3:AV60) -> 38380.637 | AW62: =SUM(AW3:AW60) -> 149920.44 | AX62: =SUM(AX3:AX60) -> 187131 | AY62: =SUM(AY3:AY60) -> 36403.662 | AZ62: =SUM(AZ3:AZ61) -> 150727.34 | BA62: =SUM(BA3:BA61) -> 53658.363 | BB62: =SUM(BB3:BB60) -> 10099.88 | BC62: =SUM(BC3:BC61) -> 43558.483 | BD62: =SUM(BD3:BD61) -> 144650 | BE62: =SUM(BE3:BE61) -> 18000 | BF62: =SUM(BF3:BF61) -> 12000
AE63: 2026 | AF63: =AF62-AG62-AH62 -> 654522.37 | AI63: =AI62-AJ62-AK62 -> 3998190.2 | AL63: =AF63-('Projection P&L'!B12*1000*1.1) -> 198827.45

Sheet SUIVI 31.12.24 ALTONEO
F1: Données prévisionnelles ou connues (à mettre à jour ) | O1: Factures en compta (à mettre à jour) | U1: cut-off Chiffre d'affaires | Y1: Cut-off charges | AF1: Marges | AI1: Chiffre d'affaires HT | AL1: Frais de dossiers HT | AO1: Reste à comptabiliser | AQ1: % de marge nette | AR1: Solde compte de charges
A2: Étape ↑ | B2: Nom du projet | C2: Facture vente finale faite | D2: Statut chantier | E2: % Avancement | F2: Prix convenu (chiffre d'affaires) HT | G2: Montant avenants HT | H2: Prix actualisé HT net de SASA | I2: SASA dans le projet HT | J2: Redevances fondations | K2: Redevances Pub | L2: Honoraires MIKIT | M2: Sous-traiance MKT | N2: Honoraires courtage HT | O2: SASA HT | P2: Redevance MIKIT | Q2: Redevance Pub MIKIT | R2: Honoraires MKT | S2: Sous-traitance MKT | T2: Honoraires courtage HT | U2: FAE CA | V2: FAE dossiers assurance | W2: FAE SASA | X2: AAE SASA | Y2: Redevance MIKIT 6% FNP | Z2: Redevance MIKIT CCA | AA2: Redevance pub MIKIT 2.5% FNP | AB2: Redevance pub MIKIT CCA | AC2: Honoraires MIKIT FNP | AD2: Sous-traitance FNP MKT | AE2: Frais courtage CCA | AF2: Marge totale chantier HT | AG2: Marges constatées N-1 | AH2: Marges 2024 HT | AI2: CA Total HT | AJ2: CA constaté N-1 | AK2: CA 2024 HT | AL2: CA Total HT | AM2: CA constaté N-1 | AN2: CA 2024 HT | AO2: CA à comptabiliser € HT | AP2: marge à comptabiliser € HT | AR2: SS MKT | AS2: SS MKT N-1 | AT2: SS MKT N | AU2: Hono MKT | AV2: Hono MKT N-1 | AW2: Hono MKT N | AX2: Fond Mikit | AY2: Fond Mikit N-1 | AZ2: Fond Mikit N | BA2: Pub Mikit | BB2: Pub Mikit N-1 | BC2: Pub Mikit N | BD2: Commissions | BE2: Commissions N-1 | BF2: Commissions N
B3: Projet Hérisson / Mercier La Bruère sur Loir | C3: non | D3: 1. Offre de financement | F3: 128083.33 | G3: 5000 | H3: =F3+G3-I3 -> 128083.33 | I3: 5000 | J3: =(F3+G3-I3)*0.06 -> 7685 | K3: =(F3+G3-I3)*0.025 -> 3202.0833 | L3: 7600.15 | M3: =(F3+G3)*0.62 -> 82511.667 | U3: =IF(C3="oui","",(H3+I3)*E3) -> 0 | W3: =IF(O3="",0,(1-E3)*O3) -> 0 | X3: =IF(O3="",I3*(E3),0) -> 0 | Y3: =IF(P3="",+H3*6%*E3,0) -> 0 | Z3: =IF(P3="",0,P3*(1-E3)) -> 0 | AA3: =IF(Q3="",+H3*2.5%*E3,0) -> 0 | AB3: =IF(Q3="",0,Q3*(1-E3)) -> 0 | AC3: =IF(R3="",+L3*E3,(1-E3)*R3) -> 0 | AD3: =IF(S3="",M3*E3,S3*E3) -> 0 | AF3: =IF(E3="",0,+H3-J3-K3-L3-M3-N3) -> 0 | AH3: =AF3*E3-AG3 -> 0 | AI3: =IF(E3="",0,H3) -> 0 | AK3: =AI3*E3-AJ3 -> 0 | AO3: =AI3-AJ3-AK3 -> 0 | AP3: =AF3-AG3-AH3 -> 0 | AQ3: =IF(E3="","",+AF3/AI3) | AR3: =IF(S3="",M3*E3,S3*E3) -> 0 | AT3: =+AR3-AS3 -> 0 | AU3: =+L3*E3 -> 0 | AW3: =+AU3-AV3 -> 0 | AX3: =IF(P3="",J3*E3,P3-Z3) -> 0 | AZ3: =+AX3-AY3 -> 0 | BA3: =IF(Q3="",K3*E3,Q3-AB3) -> 0 | BC3: =+BA3-BB3 -> 0 | BD3: =+E3*N3 -> 0
B4: Projet Tilliet / Pecqueur Vaas | C4: non | D4: 1. Offre de financement | F4: 133916.67 | G4: 5000 | H4: =F4+G4-I4 -> 133916.67 | I4: 5000 | J4: =(F4+G4-I4)*0.06 -> 8035 | K4: =(F4+G4-I4)*0.025 -> 3347.9167 | L4: 7600.15 | M4: =(F4+G4)*0.62 -> 86128.333 | U4: =IF(C4="oui","",(H4+I4)*E4) -> 0 | W4: =IF(O4="",0,(1-E4)*O4) -> 0 | X4: =IF(O4="",I4*(E4),0) -> 0 | Y4: =IF(P4="",+H4*6%*E4,0) -> 0 | Z4: =IF(P4="",0,P4*(1-E4)) -> 0 | AA4: =IF(Q4="",+H4*2.5%*E4,0) -> 0 | AB4: =IF(Q4="",0,Q4*(1-E4)) -> 0 | AC4: =IF(R4="",+L4*E4,(1-E4)*R4) -> 0 | AD4: =IF(S4="",M4*E4,S4*E4) -> 0 | AF4: =IF(E4="",0,+H4-J4-K4-L4-M4-N4) -> 0 | AH4: =AF4*E4-AG4 -> 0 | AI4: =IF(E4="",0,H4) -> 0 | AK4: =AI4*E4-AJ4 -> 0 | AO4: =AI4-AJ4-AK4 -> 0 | AP4: =AF4-AG4-AH4 -> 0 | AQ4: =IF(E4="","",+AF4/AI4) | AR4: =IF(S4="",M4*E4,S4*E4) -> 0 | AT4: =+AR4-AS4 -> 0 | AU4: =+L4*E4 -> 0 | AW4: =+AU4-AV4 -> 0 | AX4: =IF(P4="",J4*E4,P4-Z4) -> 0 | AZ4: =+AX4-AY4 -> 0 | BA4: =IF(Q4="",K4*E4,Q4-AB4) -> 0 | BC4: =+BA4-BB4 -> 0 | BD4: =+E4*N4 -> 0
B5: Projet Lucas / Huguet Vivoin | C5: non | D5: 1. Offre de financement | F5: 162000 | G5: 5000 | H5: =F5+G5-I5 -> 162000 | I5: 5000 | J5: =(F5+G5-I5)*0.06 -> 9720 | K5: =(F5+G5-I5)*0.025 -> 4050 | L5: 7600.15 | M5: =(F5+G5)*0.62 -> 103540 | U5: =IF(C5="oui","",(H5+I5)*E5) -> 0 | W5: =IF(O5="",0,(1-E5)*O5) -> 0 | X5: =IF(O5="",I5*(E5),0) -> 0 | Y5: =IF(P5="",+H5*6%*E5,0) -> 0 | Z5: =IF(P5="",0,P5*(1-E5)) -> 0 | AA5: =IF(Q5="",+H5*2.5%*E5,0) -> 0 | AB5: =IF(Q5="",0,Q5*(1-E5)) -> 0 | AC5: =IF(R5="",+L5*E5,(1-E5)*R5) -> 0 | AD5: =IF(S5="",M5*E5,S5*E5) -> 0 | AF5: =IF(E5="",0,+H5-J5-K5-L5-M5-N5) -> 0 | AH5: =AF5*E5-AG5 -> 0 | AI5: =IF(E5="",0,H5) -> 0 | AK5: =AI5*E5-AJ5 -> 0 | AO5: =AI5-AJ5-AK5 -> 0 | AP5: =AF5-AG5-AH5 -> 0 | AQ5: =IF(E5="","",+AF5/AI5) | AR5: =IF(S5="",M5*E5,S5*E5) -> 0 | AT5: =+AR5-AS5 -> 0 | AU5: =+L5*E5 -> 0 | AW5: =+AU5-AV5 -> 0 | AX5: =IF(P5="",J5*E5,P5-Z5) -> 0 | AZ5: =+AX5-AY5 -> 0 | BA5: =IF(Q5="",K5*E5,Q5-AB5) -> 0 | BC5: =+BA5-BB5 -> 0 | BD5: =+E5*N5 -> 0
B6: Projet Diallo / Diallo Ecommoy | C6: non | D6: 1. Offre de financement | E6: 0.2 | F6: 106000 | G6: 5000 | H6: =F6+G6-I6 -> 106000 | I6: 5000 | J6: =(F6+G6-I6)*0.06 -> 6360 | K6: =(F6+G6-I6)*0.025 -> 2650 | L6: 7600.15 | M6: =(F6+G6)*0.62 -> 68820 | U6: =IF(C6="oui","",(H6+I6)*E6) -> 22200 | W6: =IF(O6="",0,(1-E6)*O6) -> 0 | X6: =IF(O6="",I6*(E6),0) -> 1000 | Y6: =IF(P6="",+H6*6%*E6,0) -> 1272 | Z6: =IF(P6="",0,P6*(1-E6)) -> 0 | AA6: =IF(Q6="",+H6*2.5%*E6,0) -> 530 | AB6: =IF(Q6="",0,Q6*(1-E6)) -> 0 | AC6: =IF(R6="",+L6*E6,(1-E6)*R6) -> 1520.03 | AD6: =IF(S6="",M6*E6,S6*E6) -> 13764 | AF6: =IF(E6="",0,+H6-J6-K6-L6-M6-N6) -> 20569.85 | AH6: =AF6*E6-AG6 -> 4113.97 | AI6: =IF(E6="",0,H6) -> 106000 | AK6: =AI6*E6-AJ6 -> 21200 | AO6: =AI6-AJ6-AK6 -> 84800 | AP6: =AF6-AG6-AH6 -> 16455.88 | AQ6: =IF(E6="","",+AF6/AI6) -> 0.19405519 | AR6: =IF(S6="",M6*E6,S6*E6) -> 13764 | AT6: =+AR6-AS6 -> 13764 | AU6: =+L6*E6 -> 1520.03 | AW6: =+AU6-AV6 -> 1520.03 | AX6: =IF(P6="",J6*E6,P6-Z6) -> 1272 | AZ6: =+AX6-AY6 -> 1272 | BA6: =IF(Q6="",K6*E6,Q6-AB6) -> 530 | BC6: =+BA6-BB6 -> 530 | BD6: =+E6*N6 -> 0
B7: Projet Ikia / La Ferté Bernard | C7: non | D7: 1. Offre de financement | F7: 98333.333 | G7: 5000 | H7: =F7+G7-I7 -> 98333.333 | I7: 5000 | J7: =(F7+G7-I7)*0.06 -> 5900 | K7: =(F7+G7-I7)*0.025 -> 2458.3333 | L7: 7600.15 | M7: =(F7+G7)*0.62 -> 64066.667 | U7: =IF(C7="oui","",(H7+I7)*E7) -> 0 | W7: =IF(O7="",0,(1-E7)*O7) -> 0 | X7: =IF(O7="",I7*(E7),0) -> 0 | Y7: =IF(P7="",+H7*6%*E7,0) -> 0 | Z7: =IF(P7="",0,P7*(1-E7)) -> 0 | AA7: =IF(Q7="",+H7*2.5%*E7,0) -> 0 | AB7: =IF(Q7="",0,Q7*(1-E7)) -> 0 | AC7: =IF(R7="",+L7*E7,(1-E7)*R7) -> 0 | AD7: =IF(S7="",M7*E7,S7*E7) -> 0 | AF7: =IF(E7="",0,+H7-J7-K7-L7-M7-N7) -> 0 | AH7: =AF7*E7-AG7 -> 0 | AI7: =IF(E7="",0,H7) -> 0 | AK7: =AI7*E7-AJ7 -> 0 | AO7: =AI7-AJ7-AK7 -> 0 | AP7: =AF7-AG7-AH7 -> 0 | AQ7: =IF(E7="","",+AF7/AI7) | AR7: =IF(S7="",M7*E7,S7*E7) -> 0 | AT7: =+AR7-AS7 -> 0 | AU7: =+L7*E7 -> 0 | AW7: =+AU7-AV7 -> 0 | AX7: =IF(P7="",J7*E7,P7-Z7) -> 0 | AZ7: =+AX7-AY7 -> 0 | BA7: =IF(Q7="",K7*E7,Q7-AB7) -> 0 | BC7: =+BA7-BB7 -> 0 | BD7: =+E7*N7 -> 0
B8: Projet Bernard / Bernard Meurcé | C8: non | D8: 1. Offre de financement | F8: 134000 | G8: 5000 | H8: =F8+G8-I8 -> 134000 | I8: 5000 | J8: =(F8+G8-I8)*0.06 -> 8040 | K8: =(F8+G8-I8)*0.025 -> 3350 | L8: 7600.15 | M8: =(F8+G8)*0.62 -> 86180 | U8: =IF(C8="oui","",(H8+I8)*E8) -> 0 | W8: =IF(O8="",0,(1-E8)*O8) -> 0 | X8: =IF(O8="",I8*(E8),0) -> 0 | Y8: =IF(P8="",+H8*6%*E8,0) -> 0 | Z8: =IF(P8="",0,P8*(1-E8)) -> 0 | AA8: =IF(Q8="",+H8*2.5%*E8,0) -> 0 | AB8: =IF(Q8="",0,Q8*(1-E8)) -> 0 | AC8: =IF(R8="",+L8*E8,(1-E8)*R8) -> 0 | AD8: =IF(S8="",M8*E8,S8*E8) -> 0 | AF8: =IF(E8="",0,+H8-J8-K8-L8-M8-N8) -> 0 | AH8: =AF8*E8-AG8 -> 0 | AI8: =IF(E8="",0,H8) -> 0 | AK8: =AI8*E8-AJ8 -> 0 | AO8: =AI8-AJ8-AK8 -> 0 | AP8: =AF8-AG8-AH8 -> 0 | AQ8: =IF(E8="","",+AF8/AI8) | AR8: =IF(S8="",M8*E8,S8*E8) -> 0 | AT8: =+AR8-AS8 -> 0 | AU8: =+L8*E8 -> 0 | AW8: =+AU8-AV8 -> 0 | AX8: =IF(P8="",J8*E8,P8-Z8) -> 0 | AZ8: =+AX8-AY8 -> 0 | BA8: =IF(Q8="",K8*E8,Q8-AB8) -> 0 | BC8: =+BA8-BB8 -> 0 | BD8: =+E8*N8 -> 0
B9: Projet Froger / Saint-Ouen-en-Belin | C9: non | D9: 1. Offre de financement | E9: 0.2 | F9: 122333.33 | G9: 5000 | H9: =F9+G9-I9 -> 122333.33 | I9: 5000 | J9: =(F9+G9-I9)*0.06 -> 7340 | K9: =(F9+G9-I9)*0.025 -> 3058.3333 | L9: 7600.15 | M9: =(F9+G9)*0.62 -> 78946.667 | U9: =IF(C9="oui","",(H9+I9)*E9) -> 25466.667 | W9: =IF(O9="",0,(1-E9)*O9) -> 0 | X9: =IF(O9="",I9*(E9),0) -> 1000 | Y9: =IF(P9="",+H9*6%*E9,0) -> 1468 | Z9: =IF(P9="",0,P9*(1-E9)) -> 0 | AA9: =IF(Q9="",+H9*2.5%*E9,0) -> 611.66667 | AB9: =IF(Q9="",0,Q9*(1-E9)) -> 0 | AC9: =IF(R9="",+L9*E9,(1-E9)*R9) -> 1520.03 | AD9: =IF(S9="",M9*E9,S9*E9) -> 15789.333 | AF9: =IF(E9="",0,+H9-J9-K9-L9-M9-N9) -> 25388.183 | AH9: =AF9*E9-AG9 -> 5077.6367 | AI9: =IF(E9="",0,H9) -> 122333.33 | AK9: =AI9*E9-AJ9 -> 24466.667 | AO9: =AI9-AJ9-AK9 -> 97866.667 | AP9: =AF9-AG9-AH9 -> 20310.547 | AQ9: =IF(E9="","",+AF9/AI9) -> 0.20753283 | AR9: =IF(S9="",M9*E9,S9*E9) -> 15789.333 | AT9: =+AR9-AS9 -> 15789.333 | AU9: =+L9*E9 -> 1520.03 | AW9: =+AU9-AV9 -> 1520.03 | AX9: =IF(P9="",J9*E9,P9-Z9) -> 1468 | AZ9: =+AX9-AY9 -> 1468 | BA9: =IF(Q9="",K9*E9,Q9-AB9) -> 611.66667 | BC9: =+BA9-BB9 -> 611.66667 | BD9: =+E9*N9 -> 0
B10: Projet Pluquin / Girard Valframbert | C10: non | D10: 1. Offre de financement | F10: 134333.33 | G10: 5000 | H10: =F10+G10-I10 -> 134333.33 | I10: 5000 | J10: =(F10+G10-I10)*0.06 -> 8060 | K10: =(F10+G10-I10)*0.025 -> 3358.3333 | L10: 7600.15 | M10: =(F10+G10)*0.62 -> 86386.667 | U10: =IF(C10="oui","",(H10+I10)*E10) -> 0 | W10: =IF(O10="",0,(1-E10)*O10) -> 0 | X10: =IF(O10="",I10*(E10),0) -> 0 | Y10: =IF(P10="",+H10*6%*E10,0) -> 0 | Z10: =IF(P10="",0,P10*(1-E10)) -> 0 | AA10: =IF(Q10="",+H10*2.5%*E10,0) -> 0 | AB10: =IF(Q10="",0,Q10*(1-E10)) -> 0 | AC10: =IF(R10="",+L10*E10,(1-E10)*R10) -> 0 | AD10: =IF(S10="",M10*E10,S10*E10) -> 0 | AF10: =IF(E10="",0,+H10-J10-K10-L10-M10-N10) -> 0 | AH10: =AF10*E10-AG10 -> 0 | AI10: =IF(E10="",0,H10) -> 0 | AK10: =AI10*E10-AJ10 -> 0 | AO10: =AI10-AJ10-AK10 -> 0 | AP10: =AF10-AG10-AH10 -> 0 | AQ10: =IF(E10="","",+AF10/AI10) | AR10: =IF(S10="",M10*E10,S10*E10) -> 0 | AT10: =+AR10-AS10 -> 0 | AU10: =+L10*E10 -> 0 | AW10: =+AU10-AV10 -> 0 | AX10: =IF(P10="",J10*E10,P10-Z10) -> 0 | AZ10: =+AX10-AY10 -> 0 | BA10: =IF(Q10="",K10*E10,Q10-AB10) -> 0 | BC10: =+BA10-BB10 -> 0 | BD10: =+E10*N10 -> 0
B11: Projet Lemaire / Gueranger Yvré-le-Pôlin | C11: non | D11: 1. Offre de financement | F11: 128916.67 | G11: 5000 | H11: =F11+G11-I11 -> 128916.67 | I11: 5000 | J11: =(F11+G11-I11)*0.06 -> 7735 | K11: =(F11+G11-I11)*0.025 -> 3222.9167 | L11: 7600.15 | M11: =(F11+G11)*0.62 -> 83028.333 | U11: =IF(C11="oui","",(H11+I11)*E11) -> 0 | W11: =IF(O11="",0,(1-E11)*O11) -> 0 | X11: =IF(O11="",I11*(E11),0) -> 0 | Y11: =IF(P11="",+H11*6%*E11,0) -> 0 | Z11: =IF(P11="",0,P11*(1-E11)) -> 0 | AA11: =IF(Q11="",+H11*2.5%*E11,0) -> 0 | AB11: =IF(Q11="",0,Q11*(1-E11)) -> 0 | AC11: =IF(R11="",+L11*E11,(1-E11)*R11) -> 0 | AD11: =IF(S11="",M11*E11,S11*E11) -> 0 | AF11: =IF(E11="",0,+H11-J11-K11-L11-M11-N11) -> 0 | AH11: =AF11*E11-AG11 -> 0 | AI11: =IF(E11="",0,H11) -> 0 | AK11: =AI11*E11-AJ11 -> 0 | AO11: =AI11-AJ11-AK11 -> 0 | AP11: =AF11-AG11-AH11 -> 0 | AQ11: =IF(E11="","",+AF11/AI11) | AR11: =IF(S11="",M11*E11,S11*E11) -> 0 | AT11: =+AR11-AS11 -> 0 | AU11: =+L11*E11 -> 0 | AW11: =+AU11-AV11 -> 0 | AX11: =IF(P11="",J11*E11,P11-Z11) -> 0 | AZ11: =+AX11-AY11 -> 0 | BA11: =IF(Q11="",K11*E11,Q11-AB11) -> 0 | BC11: =+BA11-BB11 -> 0 | BD11: =+E11*N11 -> 0
B12: Projet Cordola / Ouvrard Longnes | C12: non | D12: 1. Offre de financement | F12: 113166.67 | G12: 5000 | H12: =F12+G12-I12 -> 113166.67 | I12: 5000 | J12: =(F12+G12-I12)*0.06 -> 6790 | K12: =(F12+G12-I12)*0.025 -> 2829.1667 | L12: 7600.15 | M12: =(F12+G12)*0.62 -> 73263.333 | U12: =IF(C12="oui","",(H12+I12)*E12) -> 0 | W12: =IF(O12="",0,(1-E12)*O12) -> 0 | X12: =IF(O12="",I12*(E12),0) -> 0 | Y12: =IF(P12="",+H12*6%*E12,0) -> 0 | Z12: =IF(P12="",0,P12*(1-E12)) -> 0 | AA12: =IF(Q12="",+H12*2.5%*E12,0) -> 0 | AB12: =IF(Q12="",0,Q12*(1-E12)) -> 0 | AC12: =IF(R12="",+L12*E12,(1-E12)*R12) -> 0 | AD12: =IF(S12="",M12*E12,S12*E12) -> 0 | AF12: =IF(E12="",0,+H12-J12-K12-L12-M12-N12) -> 0 | AH12: =AF12*E12-AG12 -> 0 | AI12: =IF(E12="",0,H12) -> 0 | AK12: =AI12*E12-AJ12 -> 0 | AO12: =AI12-AJ12-AK12 -> 0 | AP12: =AF12-AG12-AH12 -> 0 | AQ12: =IF(E12="","",+AF12/AI12) | AR12: =IF(S12="",M12*E12,S12*E12) -> 0 | AT12: =+AR12-AS12 -> 0 | AU12: =+L12*E12 -> 0 | AW12: =+AU12-AV12 -> 0 | AX12: =IF(P12="",J12*E12,P12-Z12) -> 0 | AZ12: =+AX12-AY12 -> 0 | BA12: =IF(Q12="",K12*E12,Q12-AB12) -> 0 | BC12: =+BA12-BB12 -> 0 | BD12: =+E12*N12 -> 0
B13: Projet Da Fonseca / Lamento Mulsanne | C13: non | D13: 1. Offre de financement | F13: 98166.667 | G13: 5000 | H13: =F13+G13-I13 -> 98166.667 | I13: 5000 | J13: =(F13+G13-I13)*0.06 -> 5890 | K13: =(F13+G13-I13)*0.025 -> 2454.1667 | L13: 7600.15 | M13: =(F13+G13)*0.62 -> 63963.333 | U13: =IF(C13="oui","",(H13+I13)*E13) -> 0 | W13: =IF(O13="",0,(1-E13)*O13) -> 0 | X13: =IF(O13="",I13*(E13),0) -> 0 | Y13: =IF(P13="",+H13*6%*E13,0) -> 0 | Z13: =IF(P13="",0,P13*(1-E13)) -> 0 | AA13: =IF(Q13="",+H13*2.5%*E13,0) -> 0 | AB13: =IF(Q13="",0,Q13*(1-E13)) -> 0 | AC13: =IF(R13="",+L13*E13,(1-E13)*R13) -> 0 | AD13: =IF(S13="",M13*E13,S13*E13) -> 0 | AF13: =IF(E13="",0,+H13-J13-K13-L13-M13-N13) -> 0 | AH13: =AF13*E13-AG13 -> 0 | AI13: =IF(E13="",0,H13) -> 0 | AK13: =AI13*E13-AJ13 -> 0 | AO13: =AI13-AJ13-AK13 -> 0 | AP13: =AF13-AG13-AH13 -> 0 | AQ13: =IF(E13="","",+AF13/AI13) | AR13: =IF(S13="",M13*E13,S13*E13) -> 0 | AT13: =+AR13-AS13 -> 0 | AU13: =+L13*E13 -> 0 | AW13: =+AU13-AV13 -> 0 | AX13: =IF(P13="",J13*E13,P13-Z13) -> 0 | AZ13: =+AX13-AY13 -> 0 | BA13: =IF(Q13="",K13*E13,Q13-AB13) -> 0 | BC13: =+BA13-BB13 -> 0 | BD13: =+E13*N13 -> 0
B14: Projet Génot / Sceaux-sur-Huisne | C14: non | D14: 1. Offre de financement | E14: 0.2 | F14: 98166.667 | G14: 5000 | H14: =F14+G14-I14 -> 98166.667 | I14: 5000 | J14: =(F14+G14-I14)*0.06 -> 5890 | K14: =(F14+G14-I14)*0.025 -> 2454.1667 | L14: 7600.15 | M14: =(F14+G14)*0.62 -> 63963.333 | U14: =IF(C14="oui","",(H14+I14)*E14) -> 20633.333 | W14: =IF(O14="",0,(1-E14)*O14) -> 0 | X14: =IF(O14="",I14*(E14),0) -> 1000 | Y14: =IF(P14="",+H14*6%*E14,0) -> 1178 | Z14: =IF(P14="",0,P14*(1-E14)) -> 0 | AA14: =IF(Q14="",+H14*2.5%*E14,0) -> 490.83333 | AB14: =IF(Q14="",0,Q14*(1-E14)) -> 0 | AC14: =IF(R14="",+L14*E14,(1-E14)*R14) -> 1520.03 | AD14: =IF(S14="",M14*E14,S14*E14) -> 12792.667 | AF14: =IF(E14="",0,+H14-J14-K14-L14-M14-N14) -> 18259.017 | AH14: =AF14*E14-AG14 -> 3651.8033 | AI14: =IF(E14="",0,H14) -> 98166.667 | AK14: =AI14*E14-AJ14 -> 19633.333 | AO14: =AI14-AJ14-AK14 -> 78533.333 | AP14: =AF14-AG14-AH14 -> 14607.213 | AQ14: =IF(E14="","",+AF14/AI14) -> 0.18600017 | AR14: =IF(S14="",M14*E14,S14*E14) -> 12792.667 | AT14: =+AR14-AS14 -> 12792.667 | AU14: =+L14*E14 -> 1520.03 | AW14: =+AU14-AV14 -> 1520.03 | AX14: =IF(P14="",J14*E14,P14-Z14) -> 1178 | AZ14: =+AX14-AY14 -> 1178 | BA14: =IF(Q14="",K14*E14,Q14-AB14) -> 490.83333 | BC14: =+BA14-BB14 -> 490.83333 | BD14: =+E14*N14 -> 0
B15: Chantier Baujard / Denis La Suze sur Sarthe | C15: non | D15: 1. Offre de financement | F15: 98166.667 | G15: 5000 | H15: =F15+G15-I15 -> 98166.667 | I15: 5000 | J15: =(F15+G15-I15)*0.06 -> 5890 | K15: =(F15+G15-I15)*0.025 -> 2454.1667 | L15: 7600.15 | M15: =(F15+G15)*0.62 -> 63963.333 | U15: =IF(C15="oui","",(H15+I15)*E15) -> 0 | W15: =IF(O15="",0,(1-E15)*O15) -> 0 | X15: =IF(O15="",I15*(E15),0) -> 0 | Y15: =IF(P15="",+H15*6%*E15,0) -> 0 | Z15: =IF(P15="",0,P15*(1-E15)) -> 0 | AA15: =IF(Q15="",+H15*2.5%*E15,0) -> 0 | AB15: =IF(Q15="",0,Q15*(1-E15)) -> 0 | AC15: =IF(R15="",+L15*E15,(1-E15)*R15) -> 0 | AD15: =IF(S15="",M15*E15,S15*E15) -> 0 | AF15: =IF(E15="",0,+H15-J15-K15-L15-M15-N15) -> 0 | AH15: =AF15*E15-AG15 -> 0 | AI15: =IF(E15="",0,H15) -> 0 | AK15: =AI15*E15-AJ15 -> 0 | AO15: =AI15-AJ15-AK15 -> 0 | AP15: =AF15-AG15-AH15 -> 0 | AQ15: =IF(E15="","",+AF15/AI15) | AR15: =IF(S15="",M15*E15,S15*E15) -> 0 | AT15: =+AR15-AS15 -> 0 | AU15: =+L15*E15 -> 0 | AW15: =+AU15-AV15 -> 0 | AX15: =IF(P15="",J15*E15,P15-Z15) -> 0 | AZ15: =+AX15-AY15 -> 0 | BA15: =IF(Q15="",K15*E15,Q15-AB15) -> 0 | BC15: =+BA15-BB15 -> 0 | BD15: =+E15*N15 -> 0
B16: Chantier Adame / Saïd Neuville sur Sarthe | C16: non | D16: 1. Offre de financement | F16: 129333.33 | G16: 5000 | H16: =F16+G16-I16 -> 129333.33 | I16: 5000 | J16: =(F16+G16-I16)*0.06 -> 7760 | K16: =(F16+G16-I16)*0.025 -> 3233.3333 | L16: 7600.15 | M16: =(F16+G16)*0.62 -> 83286.667 | U16: =IF(C16="oui","",(H16+I16)*E16) -> 0 | W16: =IF(O16="",0,(1-E16)*O16) -> 0 | X16: =IF(O16="",I16*(E16),0) -> 0 | Y16: =IF(P16="",+H16*6%*E16,0) -> 0 | Z16: =IF(P16="",0,P16*(1-E16)) -> 0 | AA16: =IF(Q16="",+H16*2.5%*E16,0) -> 0 | AB16: =IF(Q16="",0,Q16*(1-E16)) -> 0 | AC16: =IF(R16="",+L16*E16,(1-E16)*R16) -> 0 | AD16: =IF(S16="",M16*E16,S16*E16) -> 0 | AF16: =IF(E16="",0,+H16-J16-K16-L16-M16-N16) -> 0 | AH16: =AF16*E16-AG16 -> 0 | AI16: =IF(E16="",0,H16) -> 0 | AK16: =AI16*E16-AJ16 -> 0 | AO16: =AI16-AJ16-AK16 -> 0 | AP16: =AF16-AG16-AH16 -> 0 | AQ16: =IF(E16="","",+AF16/AI16) | AR16: =IF(S16="",M16*E16,S16*E16) -> 0 | AT16: =+AR16-AS16 -> 0 | AU16: =+L16*E16 -> 0 | AW16: =+AU16-AV16 -> 0 | AX16: =IF(P16="",J16*E16,P16-Z16) -> 0 | AZ16: =+AX16-AY16 -> 0 | BA16: =IF(Q16="",K16*E16,Q16-AB16) -> 0 | BC16: =+BA16-BB16 -> 0 | BD16: =+E16*N16 -> 0
B17: Projet Hugou / Hugou Villiers sur Loir | C17: non | D17: 1. Offre de financement | E17: 0.2 | F17: 137916.67 | G17: 5000 | H17: =F17+G17-I17 -> 137916.67 | I17: 5000 | J17: =(F17+G17-I17)*0.06 -> 8275 | K17: =(F17+G17-I17)*0.025 -> 3447.9167 | L17: 7600.15 | M17: =(F17+G17)*0.62 -> 88608.333 | U17: =IF(C17="oui","",(H17+I17)*E17) -> 28583.333 | W17: =IF(O17="",0,(1-E17)*O17) -> 0 | X17: =IF(O17="",I17*(E17),0) -> 1000 | Y17: =IF(P17="",+H17*6%*E17,0) -> 1655 | Z17: =IF(P17="",0,P17*(1-E17)) -> 0 | AA17: =IF(Q17="",+H17*2.5%*E17,0) -> 689.58333 | AB17: =IF(Q17="",0,Q17*(1-E17)) -> 0 | AC17: =IF(R17="",+L17*E17,(1-E17)*R17) -> 1520.03 | AD17: =IF(S17="",M17*E17,S17*E17) -> 17721.667 | AF17: =IF(E17="",0,+H17-J17-K17-L17-M17-N17) -> 29985.267 | AH17: =AF17*E17-AG17 -> 5997.0533 | AI17: =IF(E17="",0,H17) -> 137916.67 | AK17: =AI17*E17-AJ17 -> 27583.333 | AO17: =AI17-AJ17-AK17 -> 110333.33 | AP17: =AF17-AG17-AH17 -> 23988.213 | AQ17: =IF(E17="","",+AF17/AI17) -> 0.21741583 | AR17: =IF(S17="",M17*E17,S17*E17) -> 17721.667 | AT17: =+AR17-AS17 -> 17721.667 | AU17: =+L17*E17 -> 1520.03 | AW17: =+AU17-AV17 -> 1520.03 | AX17: =IF(P17="",J17*E17,P17-Z17) -> 1655 | AZ17: =+AX17-AY17 -> 1655 | BA17: =IF(Q17="",K17*E17,Q17-AB17) -> 689.58333 | BC17: =+BA17-BB17 -> 689.58333 | BD17: =+E17*N17 -> 0
B18: Projet Huet / Butet La Suze sur Sarthe | C18: non | D18: 1. Offre de financement | E18: 0.25 | F18: 117250 | G18: 5000 | H18: =F18+G18-I18 -> 117250 | I18: 5000 | J18: =(F18+G18-I18)*0.06 -> 7035 | K18: =(F18+G18-I18)*0.025 -> 2931.25 | L18: 7600.15 | M18: =(F18+G18)*0.62 -> 75795 | U18: =IF(C18="oui","",(H18+I18)*E18) -> 30562.5 | W18: =IF(O18="",0,(1-E18)*O18) -> 0 | X18: =IF(O18="",I18*(E18),0) -> 1250 | Y18: =IF(P18="",+H18*6%*E18,0) -> 1758.75 | Z18: =IF(P18="",0,P18*(1-E18)) -> 0 | AA18: =IF(Q18="",+H18*2.5%*E18,0) -> 732.8125 | AB18: =IF(Q18="",0,Q18*(1-E18)) -> 0 | AC18: =IF(R18="",+L18*E18,(1-E18)*R18) -> 1900.0375 | AD18: =IF(S18="",M18*E18,S18*E18) -> 18948.75 | AF18: =IF(E18="",0,+H18-J18-K18-L18-M18-N18) -> 23888.6 | AH18: =AF18*E18-AG18 -> 5972.15 | AI18: =IF(E18="",0,H18) -> 117250 | AK18: =AI18*E18-AJ18 -> 29312.5 | AO18: =AI18-AJ18-AK18 -> 87937.5 | AP18: =AF18-AG18-AH18 -> 17916.45 | AQ18: =IF(E18="","",+AF18/AI18) -> 0.20374072 | AR18: =IF(S18="",M18*E18,S18*E18) -> 18948.75 | AT18: =+AR18-AS18 -> 18948.75 | AU18: =+L18*E18 -> 1900.0375 | AW18: =+AU18-AV18 -> 1900.0375 | AX18: =IF(P18="",J18*E18,P18-Z18) -> 1758.75 | AZ18: =+AX18-AY18 -> 1758.75 | BA18: =IF(Q18="",K18*E18,Q18-AB18) -> 732.8125 | BC18: =+BA18-BB18 -> 732.8125 | BD18: =+E18*N18 -> 0
B19: Projet Poulio / Mulsanne | C19: non | D19: 1. Offre de financement | E19: 0.2 | F19: 102000 | G19: 5000 | H19: =F19+G19-I19 -> 102000 | I19: 5000 | J19: =(F19+G19-I19)*0.06 -> 6120 | K19: =(F19+G19-I19)*0.025 -> 2550 | L19: 7600.15 | M19: =(F19+G19)*0.62 -> 66340 | U19: =IF(C19="oui","",(H19+I19)*E19) -> 21400 | W19: =IF(O19="",0,(1-E19)*O19) -> 0 | X19: =IF(O19="",I19*(E19),0) -> 1000 | Y19: =IF(P19="",+H19*6%*E19,0) -> 1224 | Z19: =IF(P19="",0,P19*(1-E19)) -> 0 | AA19: =IF(Q19="",+H19*2.5%*E19,0) -> 510 | AB19: =IF(Q19="",0,Q19*(1-E19)) -> 0 | AC19: =IF(R19="",+L19*E19,(1-E19)*R19) -> 1520.03 | AD19: =IF(S19="",M19*E19,S19*E19) -> 13268 | AF19: =IF(E19="",0,+H19-J19-K19-L19-M19-N19) -> 19389.85 | AH19: =AF19*E19-AG19 -> 3877.97 | AI19: =IF(E19="",0,H19) -> 102000 | AK19: =AI19*E19-AJ19 -> 20400 | AO19: =AI19-AJ19-AK19 -> 81600 | AP19: =AF19-AG19-AH19 -> 15511.88 | AQ19: =IF(E19="","",+AF19/AI19) -> 0.19009657 | AR19: =IF(S19="",M19*E19,S19*E19) -> 13268 | AT19: =+AR19-AS19 -> 13268 | AU19: =+L19*E19 -> 1520.03 | AW19: =+AU19-AV19 -> 1520.03 | AX19: =IF(P19="",J19*E19,P19-Z19) -> 1224 | AZ19: =+AX19-AY19 -> 1224 | BA19: =IF(Q19="",K19*E19,Q19-AB19) -> 510 | BC19: =+BA19-BB19 -> 510 | BD19: =+E19*N19 -> 0
B20: Chantier Renard Volnay | C20: non | D20: 1. Offre de financement | E20: 0.2 | F20: 118666.67 | G20: 5000 | H20: =F20+G20-I20 -> 123666.67 | I20: 0 | J20: =(F20+G20-I20)*0.06 -> 7420 | K20: =(F20+G20-I20)*0.025 -> 3091.6667 | L20: 7600.15 | M20: =(F20+G20)*0.62 -> 76673.333 | U20: =IF(C20="oui","",(H20+I20)*E20) -> 24733.333 | W20: =IF(O20="",0,(1-E20)*O20) -> 0 | X20: =IF(O20="",I20*(E20),0) -> 0 | Y20: =IF(P20="",+H20*6%*E20,0) -> 1484 | Z20: =IF(P20="",0,P20*(1-E20)) -> 0 | AA20: =IF(Q20="",+H20*2.5%*E20,0) -> 618.33333 | AB20: =IF(Q20="",0,Q20*(1-E20)) -> 0 | AC20: =IF(R20="",+L20*E20,(1-E20)*R20) -> 1520.03 | AD20: =IF(S20="",M20*E20,S20*E20) -> 15334.667 | AF20: =IF(E20="",0,+H20-J20-K20-L20-M20-N20) -> 28881.517 | AH20: =AF20*E20-AG20 -> 5776.3033 | AI20: =IF(E20="",0,H20) -> 123666.67 | AK20: =AI20*E20-AJ20 -> 24733.333 | AO20: =AI20-AJ20-AK20 -> 98933.333 | AP20: =AF20-AG20-AH20 -> 23105.213 | AQ20: =IF(E20="","",+AF20/AI20) -> 0.23354326 | AR20: =IF(S20="",M20*E20,S20*E20) -> 15334.667 | AT20: =+AR20-AS20 -> 15334.667 | AU20: =+L20*E20 -> 1520.03 | AW20: =+AU20-AV20 -> 1520.03 | AX20: =IF(P20="",J20*E20,P20-Z20) -> 1484 | AZ20: =+AX20-AY20 -> 1484 | BA20: =IF(Q20="",K20*E20,Q20-AB20) -> 618.33333 | BC20: =+BA20-BB20 -> 618.33333 | BD20: =+E20*N20 -> 0
B21: Chantier Furia / Vivoin | C21: non | D21: 3. Fondations coulées | E21: =VLOOKUP(D21,'% avancement'!$E$5:$F$11,2,FALSE()) -> 0.4 | F21: 117916.67 | G21: 5000 | H21: =F21+G21-I21 -> 117916.67 | I21: 5000 | J21: =(F21+G21-I21)*0.06 -> 7075 | K21: =(F21+G21-I21)*0.025 -> 2947.9167 | L21: 7600.15 | M21: =(F21+G21)*0.62 -> 76208.333 | P21: 7121.65 | Q21: 1483.68 | U21: =IF(C21="oui","",(H21+I21)*E21) -> 49166.667 | W21: =IF(O21="",0,(1-E21)*O21) -> 0 | X21: =IF(O21="",I21*(E21),0) -> 2000 | Y21: =IF(P21="",+H21*6%*E21,0) -> 0 | Z21: =IF(P21="",0,P21*(1-E21)) -> 4272.99 | AA21: =IF(Q21="",+H21*2.5%*E21,0) -> 0 | AB21: =IF(Q21="",0,Q21*(1-E21)) -> 890.208 | AC21: =IF(R21="",+L21*E21,(1-E21)*R21) -> 3040.06 | AD21: =IF(S21="",M21*E21,S21*E21) -> 30483.333 | AF21: =IF(E21="",0,+H21-J21-K21-L21-M21-N21) -> 24085.267 | AH21: =AF21*E21-AG21 -> 9634.1067 | AI21: =IF(E21="",0,H21) -> 117916.67 | AK21: =AI21*E21-AJ21 -> 47166.667 | AO21: =AI21-AJ21-AK21 -> 70750 | AP21: =AF21-AG21-AH21 -> 14451.16 | AQ21: =IF(E21="","",+AF21/AI21) -> 0.20425668 | AR21: =IF(S21="",M21*E21,S21*E21) -> 30483.333 | AT21: =+AR21-AS21 -> 30483.333 | AU21: =+L21*E21 -> 3040.06 | AW21: =+AU21-AV21 -> 3040.06 | AX21: =IF(P21="",J21*E21,P21-Z21) -> 2848.66 | AZ21: =+AX21-AY21 -> 2848.66 | BA21: =IF(Q21="",K21*E21,Q21-AB21) -> 593.472 | BC21: =+BA21-BB21 -> 593.472 | BD21: =+E21*N21 -> 0
B22: Chantier Lepetit / Ménagé Fercé sur Sarthe | C22: non | D22: 3. Fondations coulées | E22: =VLOOKUP(D22,'% avancement'!$E$5:$F$11,2,FALSE()) -> 0.4 | F22: 135750 | G22: 5000 | H22: =F22+G22-I22 -> 135750 | I22: 5000 | J22: =(F22+G22-I22)*0.06 -> 8145 | K22: =(F22+G22-I22)*0.025 -> 3393.75 | L22: 7600.15 | M22: =(F22+G22)*0.62 -> 87265 | T22: 6000 | U22: =IF(C22="oui","",(H22+I22)*E22) -> 56300 | W22: =IF(O22="",0,(1-E22)*O22) -> 0 | X22: =IF(O22="",I22*(E22),0) -> 2000 | Y22: =IF(P22="",+H22*6%*E22,0) -> 3258 | Z22: =IF(P22="",0,P22*(1-E22)) -> 0 | AA22: =IF(Q22="",+H22*2.5%*E22,0) -> 1357.5 | AB22: =IF(Q22="",0,Q22*(1-E22)) -> 0 | AC22: =IF(R22="",+L22*E22,(1-E22)*R22) -> 3040.06 | AD22: =IF(S22="",M22*E22,S22*E22) -> 34906 | AF22: =IF(E22="",0,+H22-J22-K22-L22-M22-N22) -> 29346.1 | AH22: =AF22*E22-AG22 -> 11738.44 | AI22: =IF(E22="",0,H22) -> 135750 | AK22: =AI22*E22-AJ22 -> 54300 | AO22: =AI22-AJ22-AK22 -> 81450 | AP22: =AF22-AG22-AH22 -> 17607.66 | AQ22: =IF(E22="","",+AF22/AI22) -> 0.21617753 | AR22: =IF(S22="",M22*E22,S22*E22) -> 34906 | AT22: =+AR22-AS22 -> 34906 | AU22: =+L22*E22 -> 3040.06 | AW22: =+AU22-AV22 -> 3040.06 | AX22: =IF(P22="",J22*E22,P22-Z22) -> 3258 | AZ22: =+AX22-AY22 -> 3258 | BA22: =IF(Q22="",K22*E22,Q22-AB22) -> 1357.5 | BC22: =+BA22-BB22 -> 1357.5 | BD22: =+E22*N22 -> 0
B23: Chantier Attané / Attané Ecommoy | C23: non | D23: 3. Fondations coulées | E23: =VLOOKUP(D23,'% avancement'!$E$5:$F$11,2,FALSE()) -> 0.4 | F23: 119002 | G23: 5723 | H23: =F23+G23-I23 -> 119725 | I23: 5000 | J23: 6818.33 | K23: 1420.83 | L23: 7600.15 | M23: =(F23+G23)*0.62 -> 77329.5 | N23: 6000 | P23: 6818.33 | Q23: 1420.83 | T23: 6000 | U23: =IF(C23="oui","",(H23+I23)*E23) -> 49890 | W23: =IF(O23="",0,(1-E23)*O23) -> 0 | X23: =IF(O23="",I23*(E23),0) -> 2000 | Y23: =IF(P23="",+H23*6%*E23,0) -> 0 | Z23: =IF(P23="",0,P23*(1-E23)) -> 4090.998 | AA23: =IF(Q23="",+H23*2.5%*E23,0) -> 0 | AB23: =IF(Q23="",0,Q23*(1-E23)) -> 852.498 | AC23: =IF(R23="",+L23*E23,(1-E23)*R23) -> 3040.06 | AD23: =IF(S23="",M23*E23,S23*E23) -> 30931.8 | AF23: =IF(E23="",0,+H23-J23-K23-L23-M23-N23) -> 20556.19 | AH23: =AF23*E23-AG23 -> 8222.476 | AI23: =IF(E23="",0,H23) -> 119725 | AK23: =AI23*E23-AJ23 -> 47890 | AO23: =AI23-AJ23-AK23 -> 71835 | AP23: =AF23-AG23-AH23 -> 12333.714 | AQ23: =IF(E23="","",+AF23/AI23) -> 0.17169505 | AR23: =IF(S23="",M23*E23,S23*E23) -> 30931.8 | AT23: =+AR23-AS23 -> 30931.8 | AU23: =+L23*E23 -> 3040.06 | AW23: =+AU23-AV23 -> 3040.06 | AX23: =IF(P23="",J23*E23,P23-Z23) -> 2727.332 | AZ23: =+AX23-AY23 -> 2727.332 | BA23: =IF(Q23="",K23*E23,Q23-AB23) -> 568.332 | BC23: =+BA23-BB23 -> 568.332 | BD23: =+E23*N23 -> 2400 | BF23: =+BD23-BE23 -> 2400
B24: Chantier Kong / Luy Vivoin | C24: non | D24: 5. Mise hors d'eau | E24: =VLOOKUP(D24,'% avancement'!$E$5:$F$11,2,FALSE()) -> 0.8 | F24: 120621.96 | G24: 6664.41 | H24: =120622-I24 -> 115622 | I24: 5000 | J24: =8187/1.2 -> 6822.5 | K24: =1706/1.2 -> 1421.6667 | L24: 7600.15 | M24: 70635.11 | N24: 6000 | O24: 5000 | P24: 6822.5 | Q24: 1421.6667 | T24: 6000 | U24: =IF(C24="oui","",(H24+I24)*E24) -> 96497.6 | W24: =IF(O24="",0,(1-E24)*O24) -> 1000 | X24: =IF(O24="",I24*(E24),0) -> 0 | Y24: =IF(P24="",+H24*6%*E24,0) -> 0 | Z24: =IF(P24="",0,P24*(1-E24)) -> 1364.5 | AA24: =IF(Q24="",+H24*2.5%*E24,0) -> 0 | AB24: =IF(Q24="",0,Q24*(1-E24)) -> 284.33333 | AC24: =IF(R24="",+L24*E24,(1-E24)*R24) -> 6080.12 | AD24: =IF(S24="",M24*E24,S24*E24) -> 56508.088 | AF24: =IF(E24="",0,+H24-J24-K24-L24-M24-N24) -> 23142.573 | AH24: =AF24*E24-AG24 -> 18514.059 | AI24: =IF(E24="",0,H24) -> 115622 | AK24: =AI24*E24-AJ24 -> 92497.6 | AO24: =AI24-AJ24-AK24 -> 23124.4 | AP24: =AF24-AG24-AH24 -> 4628.5147 | AQ24: =IF(E24="","",+AF24/AI24) -> 0.20015718 | AR24: =IF(S24="",M24*E24,S24*E24) -> 56508.088 | AT24: =+AR24-AS24 -> 56508.088 | AU24: =+L24*E24 -> 6080.12 | AW24: =+AU24-AV24 -> 6080.12 | AX24: =IF(P24="",J24*E24,P24-Z24) -> 5458 | AZ24: =+AX24-AY24 -> 5458 | BA24: =IF(Q24="",K24*E24,Q24-AB24) -> 1137.3333 | BC24: =+BA24-BB24 -> 1137.3333 | BD24: =+E24*N24 -> 4800 | BF24: =+BD24-BE24 -> 4800
B25: Chantier Ségouin / Ségouin Vivoin | C25: non | D25: 3. Fondations coulées | E25: =VLOOKUP(D25,'% avancement'!$E$5:$F$11,2,FALSE()) -> 0.4 | F25: =+H25-G25 -> 132500.65 | G25: =7658/1.2 -> 6381.6667 | H25: 138882.32 | I25: 5000 | J25: 7867.5 | K25: 1639.15 | L25: 7600.15 | M25: 87259 | N25: 6000 | P25: 7867.5 | Q25: 1639.15 | T25: 6000 | U25: =IF(C25="oui","",(H25+I25)*E25) -> 57552.928 | W25: =IF(O25="",0,(1-E25)*O25) -> 0 | X25: =IF(O25="",I25*(E25),0) -> 2000 | Y25: =IF(P25="",+H25*6%*E25,0) -> 0 | Z25: =IF(P25="",0,P25*(1-E25)) -> 4720.5 | AA25: =IF(Q25="",+H25*2.5%*E25,0) -> 0 | AB25: =IF(Q25="",0,Q25*(1-E25)) -> 983.49 | AC25: =IF(R25="",+L25*E25,(1-E25)*R25) -> 3040.06 | AD25: =IF(S25="",M25*E25,S25*E25) -> 34903.6 | AF25: =IF(E25="",0,+H25-J25-K25-L25-M25-N25) -> 28516.52 | AH25: =AF25*E25-AG25 -> 11406.608 | AI25: =IF(E25="",0,H25) -> 138882.32 | AK25: =AI25*E25-AJ25 -> 55552.928 | AO25: =AI25-AJ25-AK25 -> 83329.392 | AP25: =AF25-AG25-AH25 -> 17109.912 | AQ25: =IF(E25="","",+AF25/AI25) -> 0.20532866 | AR25: =IF(S25="",M25*E25,S25*E25) -> 34903.6 | AT25: =+AR25-AS25 -> 34903.6 | AU25: =+L25*E25 -> 3040.06 | AW25: =+AU25-AV25 -> 3040.06 | AX25: =IF(P25="",J25*E25,P25-Z25) -> 3147 | AZ25: =+AX25-AY25 -> 3147 | BA25: =IF(Q25="",K25*E25,Q25-AB25) -> 655.66 | BC25: =+BA25-BB25 -> 655.66 | BD25: =+E25*N25 -> 2400 | BF25: =+BD25-BE25 -> 2400
B26: Chantier Maweze Kimba / Maweze Kimba Alençon | C26: non | D26: 5. Mise hors d'eau | E26: =VLOOKUP(D26,'% avancement'!$E$5:$F$11,2,FALSE()) -> 0.8 | F26: 122642.29 | G26: 8687.59 | H26: =122642-I26 -> 117642 | I26: =6000/1.2 -> 5000 | J26: =8322.18/1.2 -> 6935.15 | K26: =1733.78/1.2 -> 1444.8167 | L26: 7600 | M26: 70635 | N26: 6000 | O26: 5000 | P26: 6935.15 | Q26: 1444.8167 | T26: 6000 | U26: =IF(C26="oui","",(H26+I26)*E26) -> 98113.6 | W26: =IF(O26="",0,(1-E26)*O26) -> 1000 | X26: =IF(O26="",I26*(E26),0) -> 0 | Y26: =IF(P26="",+H26*6%*E26,0) -> 0 | Z26: =IF(P26="",0,P26*(1-E26)) -> 1387.03 | AA26: =IF(Q26="",+H26*2.5%*E26,0) -> 0 | AB26: =IF(Q26="",0,Q26*(1-E26)) -> 288.96333 | AC26: =IF(R26="",+L26*E26,(1-E26)*R26) -> 6080 | AD26: =IF(S26="",M26*E26,S26*E26) -> 56508 | AF26: =IF(E26="",0,+H26-J26-K26-L26-M26-N26) -> 25027.033 | AH26: =AF26*E26-AG26 -> 20021.627 | AI26: =IF(E26="",0,H26) -> 117642 | AK26: =AI26*E26-AJ26 -> 94113.6 | AO26: =AI26-AJ26-AK26 -> 23528.4 | AP26: =AF26-AG26-AH26 -> 5005.4067 | AQ26: =IF(E26="","",+AF26/AI26) -> 0.21273893 | AR26: =IF(S26="",M26*E26,S26*E26) -> 56508 | AT26: =+AR26-AS26 -> 56508 | AU26: =+L26*E26 -> 6080 | AW26: =+AU26-AV26 -> 6080 | AX26: =IF(P26="",J26*E26,P26-Z26) -> 5548.12 | AZ26: =+AX26-AY26 -> 5548.12 | BA26: =IF(Q26="",K26*E26,Q26-AB26) -> 1155.8533 | BC26: =+BA26-BB26 -> 1155.8533 | BD26: =+E26*N26 -> 4800 | BF26: =+BD26-BE26 -> 4800
B27: Chantier Zai / Zai Alencon | C27: non | D27: 4. Achèvement des murs | E27: =VLOOKUP(D27,'% avancement'!$E$5:$F$11,2,FALSE()) -> 0.6 | F27: 133649 | G27: =10474/1.2 -> 8728.3333 | H27: =133650-I27 -> 128650 | I27: 5000 | J27: 7668 | K27: 1597.5 | L27: 7600.15 | M27: 81747 | N27: 6000 | O27: 5000 | P27: 7668 | Q27: 1597.5 | T27: 6000 | U27: =IF(C27="oui","",(H27+I27)*E27) -> 80190 | W27: =IF(O27="",0,(1-E27)*O27) -> 2000 | X27: =IF(O27="",I27*(E27),0) -> 0 | Y27: =IF(P27="",+H27*6%*E27,0) -> 0 | Z27: =IF(P27="",0,P27*(1-E27)) -> 3067.2 | AA27: =IF(Q27="",+H27*2.5%*E27,0) -> 0 | AB27: =IF(Q27="",0,Q27*(1-E27)) -> 639 | AC27: =IF(R27="",+L27*E27,(1-E27)*R27) -> 4560.09 | AD27: =IF(S27="",M27*E27,S27*E27) -> 49048.2 | AF27: =IF(E27="",0,+H27-J27-K27-L27-M27-N27) -> 24037.35 | AH27: =AF27*E27-AG27 -> 14422.41 | AI27: =IF(E27="",0,H27) -> 128650 | AK27: =AI27*E27-AJ27 -> 77190 | AO27: =AI27-AJ27-AK27 -> 51460 | AP27: =AF27-AG27-AH27 -> 9614.94 | AQ27: =IF(E27="","",+AF27/AI27) -> 0.18684298 | AR27: =IF(S27="",M27*E27,S27*E27) -> 49048.2 | AT27: =+AR27-AS27 -> 49048.2 | AU27: =+L27*E27 -> 4560.09 | AW27: =+AU27-AV27 -> 4560.09 | AX27: =IF(P27="",J27*E27,P27-Z27) -> 4600.8 | AZ27: =+AX27-AY27 -> 4600.8 | BA27: =IF(Q27="",K27*E27,Q27-AB27) -> 958.5 | BC27: =+BA27-BB27 -> 958.5 | BD27: =+E27*N27 -> 3600 | BF27: =+BD27-BE27 -> 3600
B28: =+ROWS(B3:B27) -> 25
A29: Chantiers livrés | B29: Chantier Moussa / Mouhamadi Sidi Mari Fercé-sur-Sarthe | C29: oui | D29: 7. Réceptions | E29: =VLOOKUP(D29,'% avancement'!$E$5:$F$11,2,FALSE()) -> 1 | F29: 127823.33 | H29: =F29+G29-I29 -> 119490 | I29: =10000/1.2 -> 8333.3333 | J29: 7169.4 | K29: 1493.62 | L29: 7600.15 | M29: 77412.74 | N29: 0 | O29: =+I29 -> 8333.3333 | P29: =+J29 -> 7169.4 | Q29: =+K29 -> 1493.62 | R29: =+L29 -> 7600.15 | S29: =+M29 -> 77412.74 | T29: =+N29 -> 0 | U29: =+H29+I29 -> 127823.33 | V29: -60.71 | W29: =IF(O29="",0,(1-E29)*O29) -> 0 | X29: =IF(O29="",I29*(E29),0) -> 0 | Y29: =IF(P29=0,+H29*6%*E29,0) -> 0 | Z29: =IF(P29=0,0,P29*(1-E29)) -> 0 | AA29: =IF(Q29=0,+H29*2.5%*E29,0) -> 0 | AB29: =IF(Q29="",0,Q29*(1-E29)) -> 0 | AC29: =IF(R29="",+L29*E29,(1-E29)*R29) -> 0 | AD29: =IF(S29="",+M29*E29,(1-E29)*S29) -> 0 | AF29: =+H29-J29-K29-L29-M29-N29 -> 25814.087 | AG29: =VLOOKUP($B29,'SUIVI 30.06.24'!$D:$BE,32,FALSE()) -> 5735.7767 | AH29: =AF29*E29-AG29 -> 20078.31 | AI29: =H29 -> 119490 | AJ29: =VLOOKUP($B29,'SUIVI 30.06.24'!$D:$BE,35,FALSE()) -> 12141.667 | AK29: =AI29*E29-AJ29 -> 107348.33 | AL29: -60.71 | AM29: 0 | AN29: =+AL29 -> -60.71 | AO29: =AI29-AJ29-AK29 -> 0 | AP29: =AF29-AG29-AH29 -> 0 | AQ29: =+AF29/AI29 -> 0.21603555 | AR29: =IF(S29="",M29*E29,S29*E29) -> 77412.74 | AS29: =VLOOKUP($B29,'SUIVI 30.06.24'!$D:$BE,41,FALSE()) -> 4613.8333 | AT29: =+AR29-AS29 -> 72798.907 | AU29: =+L29*E29 -> 7600.15 | AV29: =VLOOKUP($B29,'SUIVI 30.06.24'!$D:$BE,44,FALSE()) -> 760.015 | AW29: =+AU29-AV29 -> 6840.135 | AX29: =IF(P29="",J29*E29,P29-Z29) -> 7169.4 | AY29: 728.5 | AZ29: =+AX29-AY29 -> 6440.9 | BA29: =IF(Q29="",K29*E29,Q29-AB29) -> 1493.62 | BB29: 303.54 | BC29: =+BA29-BB29 -> 1190.08 | BD29: =+E29*N29 -> 0 | BF29: =+BD29-BE29 -> 0
B30: Chantier Berthe / Evuort Vivoin | C30: oui | D30: 7. Réceptions | E30: =VLOOKUP(D30,'% avancement'!$E$5:$F$11,2,FALSE()) -> 1 | F30: 127839.17 | H30: =F30+G30-I30 -> 121172.5 | I30: =8000/1.2 -> 6666.6667 | J30: 7170.35 | K30: 1493.82 | L30: 7600.15 | M30: 80785.89 | N30: 2000 | O30: =+I30 -> 6666.6667 | P30: =+J30 -> 7170.35 | Q30: =+K30 -> 1493.82 | R30: =+L30 -> 7600.15 | S30: =+M30 -> 80785.89 | T30: 0 | U30: =+H30+I30 -> 127839.17 | V30: 869.74 | W30: =IF(O30="",0,(1-E30)*O30) -> 0 | X30: =IF(O30="",I30*(E30),0) -> 0 | Y30: =IF(P30="",+H30*6%*E30,0) -> 0 | Z30: =IF(P30="",0,P30*(1-E30)) -> 0 | AA30: =IF(Q30="",+H30*2.5%*E30,0) -> 0 | AB30: =IF(Q30="",0,Q30*(1-E30)) -> 0 | AC30: =IF(R30="",+L30*E30,(1-E30)*R30) -> 0 | AD30: =IF(S30="",+M30*E30,(1-E30)*S30) -> 0 | AF30: =+H30-J30-K30-L30-M30-N30 -> 22122.293 | AG30: =VLOOKUP(B30,'SUIVI 30.06.24'!D:BE,32,FALSE()) -> 12184.887 | AH30: =AF30*E30-AG30 -> 9937.4067 | AI30: =H30+625 -> 121797.5 | AJ30: =VLOOKUP($B30,'SUIVI 30.06.24'!$D:$BE,35,FALSE()) -> 25616.667 | AK30: =AI30*E30-AJ30 -> 96180.837 | AL30: 869.74 | AM30: 0 | AN30: =+AL30 -> 869.74 | AO30: =AI30-AJ30-AK30 -> 0 | AP30: =AF30-AG30-AH30 -> 0 | AQ30: =+AF30/AI30 -> 0.18163175 | AR30: =IF(S30="",M30*E30,S30*E30) -> 80785.89 | AS30: =VLOOKUP($B30,'SUIVI 30.06.24'!$D:$BE,41,FALSE()) -> 9734.3333 | AT30: =+AR30-AS30 -> 71051.557 | AU30: =+L30*E30 -> 7600.15 | AV30: =VLOOKUP($B30,'SUIVI 30.06.24'!$D:$BE,44,FALSE()) -> 1520.03 | AW30: =+AU30-AV30 -> 6080.12 | AX30: =IF(P30="",J30*E30,P30-Z30) -> 7170.35 | AY30: 1537 | AZ30: =+AX30-AY30 -> 5633.35 | BA30: =IF(Q30="",K30*E30,Q30-AB30) -> 1493.82 | BB30: 640.42 | BC30: =+BA30-BB30 -> 853.4 | BD30: =+E30*N30 -> 2000 | BF30: =+BD30-BE30 -> 2000
B31: Chantier Tamisier / Tronchet Neufchâtel-en-Saosnois | C31: oui | D31: 7. Réceptions | E31: =VLOOKUP(D31,'% avancement'!$E$5:$F$11,2,FALSE()) -> 1 | F31: 142761.67 | H31: =F31+G31-I31 -> 137761.67 | I31: =6000/1.2 -> 5000 | J31: 8065.7 | K31: 1680.35 | L31: 7600.15 | M31: 81922.01 | N31: 2000 | O31: =+I31 -> 5000 | P31: =+J31 -> 8065.7 | Q31: =+K31 -> 1680.35 | R31: =+L31 -> 7600.15 | S31: =+M31 -> 81922.01 | T31: 4000 | U31: =IF(C31="oui","",(H31+I31)*E31) | W31: =IF(O31="",0,(1-E31)*O31) -> 0 | X31: =IF(O31="",I31*(E31),0) -> 0 | Y31: =IF(P31="",+H31*6%*E31,0) -> 0 | Z31: =IF(P31="",0,P31*(1-E31)) -> 0 | AA31: =IF(Q31="",+H31*2.5%*E31,0) -> 0 | AB31: =IF(Q31="",0,Q31*(1-E31)) -> 0 | AC31: =IF(R31="",+L31*E31,(1-E31)*R31) -> 0 | AD31: =IF(S31="",+M31*E31,(1-E31)*S31) -> 0 | AF31: =+H31-J31-K31-L31-M31-N31 -> 36493.46 | AG31: =VLOOKUP(B31,'SUIVI 30.06.24'!D:BE,32,FALSE()) -> 6226.1933 | AH31: =AF31*E31-AG31 -> 30267.267 | AI31: =H31 -> 137761.67 | AJ31: =VLOOKUP($B31,'SUIVI 30.06.24'!$D:$BE,35,FALSE()) -> 13058.333 | AK31: =AI31*E31-AJ31 -> 124703.34 | AL31: -65.29 | AM31: 0 | AN31: =+AL31 -> -65.29 | AO31: =AI31-AJ31-AK31 -> 0 | AP31: =AF31-AG31-AH31 -> 0 | AQ31: =+AF31/AI31 -> 0.26490286 | AR31: =IF(S31="",M31*E31,S31*E31) -> 81922.01 | AS31: =VLOOKUP($B31,'SUIVI 30.06.24'!$D:$BE,41,FALSE()) -> 4962.1667 | AT31: =+AR31-AS31 -> 76959.843 | AU31: =+L31*E31 -> 7600.15 | AV31: =VLOOKUP($B31,'SUIVI 30.06.24'!$D:$BE,44,FALSE()) -> 760.015 | AW31: =+AU31-AV31 -> 6840.135 | AX31: =IF(P31="",J31*E31,P31-Z31) -> 8065.7 | AY31: 783.5 | AZ31: =+AX31-AY31 -> 7282.2 | BA31: =IF(Q31="",K31*E31,Q31-AB31) -> 1680.35 | BB31: 326.46 | BC31: =+BA31-BB31 -> 1353.89 | BD31: =+E31*N31 -> 2000 | BF31: =+BD31-BE31 -> 2000
B32: Chantier Garcia / Garcia La Suze sur Sarthe | C32: oui | D32: 7. Réceptions | E32: =VLOOKUP(D32,'% avancement'!$E$5:$F$11,2,FALSE()) -> 1 | F32: 126492.65 | H32: =F32+G32-I32 -> 121492.65 | I32: =6000/1.2 -> 5000 | J32: 7085.7 | K32: 1476.19 | L32: 7600.15 | M32: 74584.6 | N32: 0 | O32: =+I32 -> 5000 | P32: =+J32 -> 7085.7 | Q32: =+K32 -> 1476.19 | R32: =+L32 -> 7600.15 | S32: =+M32 -> 74584.6 | T32: =+N32 -> 0 | U32: =IF(C32="oui","",(H32+I32)*E32) | W32: =IF(O32="",0,(1-E32)*O32) -> 0 | X32: =IF(O32="",I32*(E32),0) -> 0 | Y32: =IF(P32="",+H32*6%*E32,0) -> 0 | Z32: =IF(P32="",0,P32*(1-E32)) -> 0 | AA32: =IF(Q32="",+H32*2.5%*E32,0) -> 0 | AB32: =IF(Q32="",0,Q32*(1-E32)) -> 0 | AC32: =IF(R32="",+L32*E32,(1-E32)*R32) -> 0 | AD32: =IF(S32="",+M32*E32,(1-E32)*S32) -> 0 | AF32: =+H32-J32-K32-L32-M32-N32 -> 30746.01 | AG32: =VLOOKUP(B32,'SUIVI 30.06.24'!D:BE,32,FALSE()) -> 5943.2675 | AH32: =AF32*E32-AG32 -> 24802.742 | AI32: =H32 -> 121492.65 | AJ32: =VLOOKUP($B32,'SUIVI 30.06.24'!$D:$BE,35,FALSE()) -> 28666.667 | AK32: =AI32*E32-AJ32 -> 92825.983 | AL32: 384.4 | AM32: 0 | AN32: =+AL32 -> 384.4 | AO32: =AI32-AJ32-AK32 -> 0 | AP32: =AF32-AG32-AH32 -> 0 | AQ32: =+AF32/AI32 -> 0.25306889 | AR32: =IF(S32="",M32*E32,S32*E32) -> 74584.6 | AS32: =VLOOKUP($B32,'SUIVI 30.06.24'!$D:$BE,41,FALSE()) -> 18386.695 | AT32: =+AR32-AS32 -> 56197.905 | AU32: =+L32*E32 -> 7600.15 | AV32: =VLOOKUP($B32,'SUIVI 30.06.24'!$D:$BE,44,FALSE()) -> 1900.0375 | AW32: =+AU32-AV32 -> 5700.1125 | AX32: =IF(P32="",J32*E32,P32-Z32) -> 7085.7 | AY32: 1720 | AZ32: =+AX32-AY32 -> 5365.7 | BA32: =IF(Q32="",K32*E32,Q32-AB32) -> 1476.19 | BB32: 716.67 | BC32: =+BA32-BB32 -> 759.52 | BD32: =+E32*N32 -> 0 | BF32: =+BD32-BE32 -> 0
B33: Chantier Vanier Breillon / Vanier Breillon La Chapelle d'Aligné | C33: oui | D33: 7. Réceptions | E33: =VLOOKUP(D33,'% avancement'!$E$5:$F$11,2,FALSE()) -> 1 | F33: 124735 | H33: =F33+G33-I33 -> 118901.67 | I33: =7000/1.2 -> 5833.3333 | J33: 6834.1 | K33: 1423.77 | L33: 7600.15 | M33: 70637.64 | N33: 3500 | O33: =+I33 -> 5833.3333 | P33: =+J33 -> 6834.1 | Q33: =+K33 -> 1423.77 | R33: =+L33 -> 7600.15 | S33: =+M33 -> 70637.64 | T33: =+N33 -> 3500 | U33: =IF(C33="oui","",(H33+I33)*E33) | W33: =IF(O33="",0,(1-E33)*O33) -> 0 | X33: =IF(O33="",I33*(E33),0) -> 0 | Y33: =IF(P33="",+H33*6%*E33,0) -> 0 | Z33: =IF(P33="",0,P33*(1-E33)) -> 0 | AA33: =IF(Q33="",+H33*2.5%*E33,0) -> 0 | AB33: =IF(Q33="",0,Q33*(1-E33)) -> 0 | AC33: =IF(R33="",+L33*E33,(1-E33)*R33) -> 0 | AD33: =IF(S33="",+M33*E33,(1-E33)*S33) -> 0 | AF33: =+H33-J33-K33-L33-M33-N33 -> 28906.007 | AG33: =VLOOKUP(B33,'SUIVI 30.06.24'!D:BE,32,FALSE()) -> 5330.0683 | AH33: =AF33*E33-AG33 -> 23575.938 | AI33: =H33 -> 118901.67 | AJ33: =VLOOKUP($B33,'SUIVI 30.06.24'!$D:$BE,35,FALSE()) -> 11383.333 | AK33: =AI33*E33-AJ33 -> 107518.33 | AL33: -56.92 | AM33: 0 | AN33: =+AL33 -> -56.92 | AO33: =AI33-AJ33-AK33 -> 0 | AP33: =AF33-AG33-AH33 -> 0 | AQ33: =+AF33/AI33 -> 0.24310851 | AR33: =IF(S33="",M33*E33,S33*E33) -> 70637.64 | AS33: =VLOOKUP($B33,'SUIVI 30.06.24'!$D:$BE,41,FALSE()) -> 4325.6667 | AT33: =+AR33-AS33 -> 66311.973 | AU33: =+L33*E33 -> 7600.15 | AV33: =VLOOKUP($B33,'SUIVI 30.06.24'!$D:$BE,44,FALSE()) -> 760.015 | AW33: =+AU33-AV33 -> 6840.135 | AX33: =IF(P33="",J33*E33,P33-Z33) -> 6834.1 | AY33: 683 | AZ33: =+AX33-AY33 -> 6151.1 | BA33: =IF(Q33="",K33*E33,Q33-AB33) -> 1423.77 | BB33: 284.58 | BC33: =+BA33-BB33 -> 1139.19 | BD33: =+E33*N33 -> 3500 | BF33: =+BD33-BE33 -> 3500
B34: Chantier Tessier - 72 Luce sous Ballon | C34: oui | D34: 7. Réceptions | E34: =VLOOKUP(D34,'% avancement'!$E$5:$F$11,2,FALSE()) -> 1 | F34: 119182.5 | H34: =F34+G34-I34 -> 119182.5 | I34: 0 | J34: 6900 | K34: 2875 | L34: 7378.79 | M34: 80258.37 | N34: 0 | O34: =+I34 -> 0 | P34: =+J34 -> 6900 | Q34: =+K34 -> 2875 | R34: =+L34 -> 7378.79 | S34: =+M34 -> 80258.37 | T34: =+N34 -> 0 | U34: =IF(C34="oui","",(H34+I34)*E34) | W34: =IF(O34="",0,(1-E34)*O34) -> 0 | X34: =IF(O34="",I34*(E34),0) -> 0 | Y34: =IF(P34="",+H34*6%*E34,0) -> 0 | Z34: =IF(P34="",0,P34*(1-E34)) -> 0 | AA34: =IF(Q34="",+H34*2.5%*E34,0) -> 0 | AB34: =IF(Q34="",0,Q34*(1-E34)) -> 0 | AC34: =IF(R34="",+L34*E34,(1-E34)*R34) -> 0 | AD34: =IF(S34="",+M34*E34,(1-E34)*S34) -> 0 | AF34: =+H34-J34-K34-L34-M34-N34 -> 21770.34 | AG34: =VLOOKUP(B34,'SUIVI 30.06.24'!D:BE,32,FALSE()) -> 16283.895 | AH34: =AF34*E34-AG34 -> 5486.445 | AI34: =H34 -> 119182.5 | AJ34: =VLOOKUP($B34,'SUIVI 30.06.24'!$D:$BE,35,FALSE()) -> 89343.015 | AK34: =AI34*E34-AJ34 -> 29839.485 | AL34: -58.48 | AM34: 0 | AN34: =+AL34 -> -58.48 | AO34: =AI34-AJ34-AK34 -> 0 | AP34: =AF34-AG34-AH34 -> 0 | AQ34: =+AF34/AI34 -> 0.1826639 | AR34: =IF(S34="",M34*E34,S34*E34) -> 80258.37 | AS34: =VLOOKUP($B34,'SUIVI 30.06.24'!$D:$BE,41,FALSE()) -> 60193.777 | AT34: =+AR34-AS34 -> 20064.592 | AU34: =+L34*E34 -> 7378.79 | AV34: =VLOOKUP($B34,'SUIVI 30.06.24'!$D:$BE,44,FALSE()) -> 5534.0925 | AW34: =+AU34-AV34 -> 1844.6975 | AX34: =IF(P34="",J34*E34,P34-Z34) -> 6900 | AY34: =+AX34-1725 -> 5175 | AZ34: =+AX34-AY34 -> 1725 | BA34: =IF(Q34="",K34*E34,Q34-AB34) -> 2875 | BB34: =+BA34-718.75 -> 2156.25 | BC34: =+BA34-BB34 -> 718.75 | BD34: =+E34*N34 -> 0 | BF34: =+BD34-BE34 -> 0
B35: Chantier Ridony / Jean-Charles - 72 Ecommoy | C35: oui | D35: 7. Réceptions | E35: =VLOOKUP(D35,'% avancement'!$E$5:$F$11,2,FALSE()) -> 1 | F35: 128711.54 | H35: =F35+G35-I35 -> 126128.21 | I35: 2583.33 | J35: 7313.95 | K35: 3047.48 | L35: 7378.79 | M35: 83972.54 | N35: 0 | O35: =+I35 -> 2583.33 | P35: =+J35 -> 7313.95 | Q35: =+K35 -> 3047.48 | R35: =+L35 -> 7378.79 | S35: =+M35 -> 83972.54 | T35: =+N35 -> 0 | U35: =IF(C35="oui","",(H35+I35)*E35) | W35: =IF(O35="",0,(1-E35)*O35) -> 0 | X35: =IF(O35="",I35*(E35),0) -> 0 | Y35: =IF(P35="",+H35*6%*E35,0) -> 0 | Z35: =IF(P35="",0,P35*(1-E35)) -> 0 | AA35: =IF(Q35="",+H35*2.5%*E35,0) -> 0 | AB35: =IF(Q35="",0,Q35*(1-E35)) -> 0 | AC35: =IF(R35="",+L35*E35,(1-E35)*R35) -> 0 | AD35: =IF(S35="",+M35*E35,(1-E35)*S35) -> 0 | AF35: =+H35-J35-K35-L35-M35-N35 -> 24415.45 | AG35: =VLOOKUP(B35,'SUIVI 30.06.24'!D:BE,32,FALSE()) -> 15830.293 | AH35: =AF35*E35-AG35 -> 8585.157 | AI35: =H35 -> 126128.21 | AJ35: =VLOOKUP($B35,'SUIVI 30.06.24'!$D:$BE,35,FALSE()) -> 81943.587 | AK35: =AI35*E35-AJ35 -> 44184.623 | AL35: -61.16 | AM35: 0 | AN35: =+AL35 -> -61.16 | AO35: =AI35-AJ35-AK35 -> 0 | AP35: =AF35-AG35-AH35 -> 0 | AQ35: =+AF35/AI35 -> 0.19357644 | AR35: =IF(S35="",M35*E35,S35*E35) -> 83972.54 | AS35: =VLOOKUP($B35,'SUIVI 30.06.24'!$D:$BE,41,FALSE()) -> 54582.151 | AT35: =+AR35-AS35 -> 29390.389 | AU35: =+L35*E35 -> 7378.79 | AV35: =VLOOKUP($B35,'SUIVI 30.06.24'!$D:$BE,44,FALSE()) -> 4796.2135 | AW35: =+AU35-AV35 -> 2582.5765 | AX35: =IF(P35="",J35*E35,P35-Z35) -> 7313.95 | AY35: =+AX35-2559.88 -> 4754.07 | AZ35: =+AX35-AY35 -> 2559.88 | BA35: =IF(Q35="",K35*E35,Q35-AB35) -> 3047.48 | BB35: =+BA35-1066.62 -> 1980.86 | BC35: =+BA35-BB35 -> 1066.62 | BD35: =+E35*N35 -> 0 | BF35: =+BD35-BE35 -> 0
B36: Chantier Rajoel / Rojo Prévelle | C36: oui | D36: 7. Réceptions | E36: =VLOOKUP(D36,'% avancement'!$E$5:$F$11,2,FALSE()) -> 1 | F36: 115625 | H36: =F36+G36-I36 -> 111458.33 | I36: =5000/1.2 -> 4166.6667 | J36: 7137.5 | K36: 1486.98 | L36: 7600.15 | M36: 73603.47 | N36: 0 | O36: =+I36 -> 4166.6667 | P36: =+J36 -> 7137.5 | Q36: =+K36 -> 1486.98 | R36: =+L36 -> 7600.15 | S36: =+M36 -> 73603.47 | T36: =+N36 -> 0 | U36: =IF(C36="oui","",(H36+I36)*E36) | W36: =IF(O36="",0,(1-E36)*O36) -> 0 | X36: =IF(O36="",I36*(E36),0) -> 0 | Y36: =IF(P36="",+H36*6%*E36,0) -> 0 | Z36: =IF(P36="",0,P36*(1-E36)) -> 0 | AA36: =IF(Q36="",+H36*2.5%*E36,0) -> 0 | AB36: =IF(Q36="",0,Q36*(1-E36)) -> 0 | AC36: =IF(R36="",+L36*E36,(1-E36)*R36) -> 0 | AD36: =IF(S36="",+M36*E36,(1-E36)*S36) -> 0 | AF36: =+H36-J36-K36-L36-M36-N36 -> 21630.233 | AG36: =VLOOKUP(B36,'SUIVI 30.06.24'!D:BE,32,FALSE()) -> 6289.3325 | AH36: =AF36*E36-AG36 -> 15340.901 | AI36: =H36 -> 111458.33 | AJ36: =VLOOKUP($B36,'SUIVI 30.06.24'!$D:$BE,35,FALSE()) -> 28729.167 | AK36: =AI36*E36-AJ36 -> 82729.167 | AL36: 249.67 | AM36: 0 | AN36: =+AL36 -> 249.67 | AO36: =AI36-AJ36-AK36 -> 0 | AP36: =AF36-AG36-AH36 -> 0 | AQ36: =+AF36/AI36 -> 0.19406564 | AR36: =IF(S36="",M36*E36,S36*E36) -> 73603.47 | AS36: =VLOOKUP($B36,'SUIVI 30.06.24'!$D:$BE,41,FALSE()) -> 18097.818 | AT36: =+AR36-AS36 -> 55505.652 | AU36: =+L36*E36 -> 7600.15 | AV36: =VLOOKUP($B36,'SUIVI 30.06.24'!$D:$BE,44,FALSE()) -> 1900.0375 | AW36: =+AU36-AV36 -> 5700.1125 | AX36: =IF(P36="",J36*E36,P36-Z36) -> 7137.5 | AY36: 1723.75 | AZ36: =+AX36-AY36 -> 5413.75 | BA36: =IF(Q36="",K36*E36,Q36-AB36) -> 1486.98 | BB36: 718.23 | BC36: =+BA36-BB36 -> 768.75 | BD36: =+E36*N36 -> 0 | BF36: =+BD36-BE36 -> 0
B37: Chantier Beaujeon / Blot La Flèche | C37: oui | D37: 7. Réceptions | E37: =VLOOKUP(D37,'% avancement'!$E$5:$F$11,2,FALSE()) -> 1 | F37: 121445 | H37: =F37+G37-I37 -> 117278.33 | I37: =5000/1.2 -> 4166.6667 | J37: 6836.7 | K37: 1424.31 | L37: 7600.15 | M37: 71316.1 | N37: 3000 | O37: =+I37 -> 4166.6667 | P37: =+J37 -> 6836.7 | Q37: =+K37 -> 1424.31 | R37: =+L37 -> 7600.15 | S37: =+M37 -> 71316.1 | T37: =+N37 -> 3000 | U37: =IF(C37="oui","",(H37+I37)*E37) | W37: =IF(O37="",0,(1-E37)*O37) -> 0 | X37: =IF(O37="",I37*(E37),0) -> 0 | Y37: =IF(P37="",+H37*6%*E37,0) -> 0 | Z37: =IF(P37="",0,P37*(1-E37)) -> 0 | AA37: =IF(Q37="",+H37*2.5%*E37,0) -> 0 | AB37: =IF(Q37="",0,Q37*(1-E37)) -> 0 | AC37: =IF(R37="",+L37*E37,(1-E37)*R37) -> 0 | AD37: =IF(S37="",+M37*E37,(1-E37)*S37) -> 0 | AF37: =+H37-J37-K37-L37-M37-N37 -> 27101.073 | AH37: =AF37*E37-AG37 -> 27101.073 | AI37: =H37 -> 117278.33 | AJ37: =VLOOKUP($B37,'SUIVI 30.06.24'!$D:$BE,35,FALSE()) -> 0 | AK37: =AI37*E37-AJ37 -> 117278.33 | AL37: -56.08 | AM37: 0 | AN37: =+AL37 -> -56.08 | AO37: =AI37-AJ37-AK37 -> 0 | AP37: =AF37-AG37-AH37 -> 0 | AQ37: =+AF37/AI37 -> 0.23108338 | AR37: =IF(S37="",M37*E37,S37*E37) -> 71316.1 | AS37: =VLOOKUP($B37,'SUIVI 30.06.24'!$D:$BE,41,FALSE()) -> 0 | AT37: =+AR37-AS37 -> 71316.1 | AU37: =+L37*E37 -> 7600.15 | AV37: =VLOOKUP($B37,'SUIVI 30.06.24'!$D:$BE,44,FALSE()) -> 0 | AW37: =+AU37-AV37 -> 7600.15 | AX37: =IF(P37="",J37*E37,P37-Z37) -> 6836.7 | AZ37: =+AX37-AY37 -> 6836.7 | BA37: =IF(Q37="",K37*E37,Q37-AB37) -> 1424.31 | BB37: =VLOOKUP($B37,'SUIVI 30.06.24'!$D:$BE,50,FALSE()) -> 0 | BC37: =+BA37-BB37 -> 1424.31 | BD37: =+E37*N37 -> 3000 | BF37: =+BD37-BE37 -> 3000
B38: Chantier Renard / Renard La Flèche | C38: oui | D38: 7. Réceptions | E38: =VLOOKUP(D38,'% avancement'!$E$5:$F$11,2,FALSE()) -> 1 | F38: 120024.98 | H38: =F38+G38-I38 -> 115024.98 | I38: 5000 | J38: 6801.5 | K38: 1416.98 | L38: 7600.15 | M38: 68691.72 | N38: 3500 | O38: =+I38 -> 5000 | P38: =+J38 -> 6801.5 | Q38: =+K38 -> 1416.98 | T38: =+N38 -> 3500 | U38: =+H38+I38 -> 120024.98 | V38: 284.79 | W38: =IF(O38="",0,(1-E38)*O38) -> 0 | X38: =IF(O38="",I38*(E38),0) -> 0 | Y38: =IF(P38="",+H38*6%*E38,0) -> 0 | Z38: =IF(P38="",0,P38*(1-E38)) -> 0 | AA38: =IF(Q38="",+H38*2.5%*E38,0) -> 0 | AB38: =IF(Q38="",0,Q38*(1-E38)) -> 0 | AC38: =IF(R38="",+L38*E38,(1-E38)*R38) -> 7600.15 | AD38: =IF(S38="",+M38*E38,(1-E38)*S38) -> 68691.72 | AF38: =+H38-J38-K38-L38-M38-N38 -> 27014.63 | AH38: =AF38*E38-AG38 -> 27014.63 | AI38: =H38 -> 115024.98 | AJ38: =VLOOKUP($B38,'SUIVI 30.06.24'!$D:$BE,35,FALSE()) -> 0 | AK38: =AI38*E38-AJ38 -> 115024.98 | AL38: 284.79 | AM38: 0 | AN38: =+AL38 -> 284.79 | AO38: =AI38-AJ38-AK38 -> 0 | AP38: =AF38-AG38-AH38 -> 0 | AQ38: =+AF38/AI38 -> 0.23485881 | AR38: =IF(S38="",M38*E38,S38*E38) -> 68691.72 | AS38: =VLOOKUP($B38,'SUIVI 30.06.24'!$D:$BE,41,FALSE()) -> 0 | AT38: =+AR38-AS38 -> 68691.72 | AU38: =+L38*E38 -> 7600.15 | AV38: =VLOOKUP($B38,'SUIVI 30.06.24'!$D:$BE,44,FALSE()) -> 0 | AW38: =+AU38-AV38 -> 7600.15 | AX38: =IF(P38="",J38*E38,P38-Z38) -> 6801.5 | AZ38: =+AX38-AY38 -> 6801.5 | BA38: =IF(Q38="",K38*E38,Q38-AB38) -> 1416.98 | BB38: =VLOOKUP($B38,'SUIVI 30.06.24'!$D:$BE,50,FALSE()) -> 0 | BC38: =+BA38-BB38 -> 1416.98 | BD38: =+E38*N38 -> 3500 | BF38: =+BD38-BE38 -> 3500
A39: Sous-total | B39: =ROWS(B29:B38) -> 10
A40: Total | B40: =B28+B39 -> 35 | U40: =SUM(U3:U38) -> 1036977.4 | V40: =SUM(V3:V38) -> 1093.82 | W40: =SUM(W3:W38) -> 4000 | X40: =SUM(X3:X38) -> 14250 | Y40: =SUM(Y3:Y38) -> 13297.75 | Z40: =SUM(Z3:Z38) -> 18903.218 | AA40: =SUM(AA3:AA38) -> 5540.7292 | AB40: =SUM(AB3:AB38) -> 3938.4927 | ... AP40: =SUM(AP3:AP38) -> 212646.7 | AQ40: =+AF40/AI40 -> 0.21006197 | AR40: =SUM(AR3:AR38) -> 1164093.2 | AS40: 174896.44 | AT40: =SUM(AT3:AT38) -> 989196.74 | AU40: =SUM(AU3:AU38) -> 115459.45 | AV40: =SUM(AV3:AV38) -> 17930.456 | AW40: =SUM(AW3:AW38) -> 97528.991 | AX40: =SUM(AX3:AX38) -> 108942.56 | AY40: =SUM(AY3:AY38) -> 17104.82 | AZ40: =SUM(AZ3:AZ39) -> 91837.742 | BA40: =SUM(BA3:BA39) -> 28428.38 | BB40: =SUM(BB3:BB38) -> 7127.01 | BC40: =SUM(BC3:BC39) -> 21301.37 | BD40: =SUM(BD3:BD39) -> 32000 | BE40: =SUM(BE3:BE39) -> 0 | BF40: =SUM(BF3:BF39) -> 32000
U41: OK | V41: OK | W41: OK | X41: OK | Y41: OK | Z41: OK | AA41: OK | AB41: OK | AC41: OK | AD41: OK | AK41: OK | AN41: OK | AT41: OK | AW41: OK | AZ41: OK | BC41: OK

Sheet SUIVI 31.12.24
F1: Données prévisionnelles ou connues (à mettre à jour ) | O1: Factures en compta (à mettre à jour) | U1: cut-off Chiffre d'affaires | X1: Cut-off charges | AE1: Marges | AH1: Chiffre d'affaires HT | AK1: Reste à comptabiliser | AM1: % de marge nette | AN1: Solde compte de charges
A2: Étape ↑ | B2: Nom du projet | C2: Facture vente finale faite | D2: Statut chantier | E2: % Avancement | F2: Prix convenu (chiffre d'affaires) HT | G2: Montant avenants HT | H2: Prix actualisé HT net de SASA | I2: SASA dans le projet HT | J2: Redevances fondations | K2: Redevances Pub | L2: Honoraires MIKIT | M2: Sous-traiance MKT | N2: Honoraires courtage HT | O2: SASA HT | P2: Redevance MIKIT | Q2: Redevance Pub MIKIT | R2: Honoraires MKT | S2: Sous-traitance MKT | T2: Honoraires courtage HT | U2: FAE CA | V2: FAE SASA | W2: AAE SASA | X2: Redevance MIKIT 6% FNP | Y2: Redevance MIKIT CCA | Z2: Redevance pub MIKIT 2.5% FNP | AA2: Redevance pub MIKIT CCA | AB2: Honoraires MIKIT FNP | AC2: Sous-traitance FNP MKT | AD2: Frais courtage CCA | AE2: Marge totale chantier HT | AF2: Marges constatées N-1 | AG2: Marges 2024 HT | AH2: CA Total HT | AI2: CA constaté N-1 | AJ2: CA 2024 HT | AK2: CA à comptabiliser € HT | AL2: marge à comptabiliser € HT | AN2: SS MKT | AO2: SS MKT N-1 | AP2: SS MKT N | AQ2: Hono MKT | AR2: Hono MKT N-1 | AS2: Hono MKT N | AT2: Fond Mikit | AU2: Fond Mikit N-1 | AV2: Fond Mikit N | AW2: Pub Mikit | AX2: Pub Mikit N-1 | AY2: Pub Mikit N | AZ2: Commissions | BA2: Commissions N-1 | BB2: Commissions N
B3: Projet Hérisson / Mercier La Bruère sur Loir | C3: non | D3: 1. Offre de financement | F3: 128083.33 | G3: 5000 | H3: =F3+G3-I3 -> 128083.33 | I3: 5000 | J3: =(F3+G3-I3)*0.06 -> 7685 | K3: =(F3+G3-I3)*0.025 -> 3202.0833 | L3: 7600.15 | M3: =(F3+G3)*0.62 -> 82511.667 | U3: =IF(C3="oui","",(H3+I3)*E3) -> 0 | V3: =IF(O3="",0,(1-E3)*O3) -> 0 | W3: =IF(O3="",I3*(E3),0) -> 0 | X3: =IF(P3="",+H3*6%*E3,0) -> 0 | Y3: =IF(P3="",0,P3*(1-E3)) -> 0 | Z3: =IF(Q3="",+H3*2.5%*E3,0) -> 0 | AA3: =IF(Q3="",0,Q3*(1-E3)) -> 0 | AB3: =IF(R3="",+L3*E3,(1-E3)*R3) -> 0 | AC3: =IF(S3="",M3*E3,S3*E3) -> 0 | AD3: =IF(T3="",0,T3*(1-E3)) -> 0 | AE3: =IF(E3="",0,+H3-J3-K3-L3-M3-N3) -> 0 | AG3: =AE3*E3-AF3 -> 0 | AH3: =IF(E3="",0,H3) -> 0 | AJ3: =AH3*E3-AI3 -> 0 | AK3: =AH3-AI3-AJ3 -> 0 | AL3: =AE3-AF3-AG3 -> 0 | AM3: =IF(E3="","",+AE3/AH3) | AN3: =IF(S3="",M3*E3,S3*E3) -> 0 | AP3: =+AN3-AO3 -> 0 | AQ3: =+L3*E3 -> 0 | AS3: =+AQ3-AR3 -> 0 | AT3: =IF(P3="",J3*E3,P3*E3) -> 0 | AV3: =+AT3-AU3 -> 0 | AW3: =IF(Q3="",K3*E3,Q3*E3) -> 0 | AY3: =+AW3-AX3 -> 0 | AZ3: =+E3*N3 -> 0
B4: Projet Tilliet / Pecqueur Vaas | C4: non | D4: 1. Offre de financement | F4: 133916.67 | G4: 5000 | H4: =F4+G4-I4 -> 133916.67 | I4: 5000 | J4: =(F4+G4-I4)*0.06 -> 8035 | K4: =(F4+G4-I4)*0.025 -> 3347.9167 | L4: 7600.15 | M4: =(F4+G4)*0.62 -> 86128.333 | U4: =IF(C4="oui","",(H4+I4)*E4) -> 0 | V4: =IF(O4="",0,(1-E4)*O4) -> 0 | W4: =IF(O4="",I4*(E4),0) -> 0 | X4: =IF(P4="",+H4*6%*E4,0) -> 0 | Y4: =IF(P4="",0,P4*(1-E4)) -> 0 | Z4: =IF(Q4="",+H4*2.5%*E4,0) -> 0 | AA4: =IF(Q4="",0,Q4*(1-E4)) -> 0 | AB4: =IF(R4="",+L4*E4,(1-E4)*R4) -> 0 | AC4: =IF(S4="",M4*E4,S4*E4) -> 0 | AD4: =IF(T4="",0,T4*(1-E4)) -> 0 | AE4: =IF(E4="",0,+H4-J4-K4-L4-M4-N4) -> 0 | AG4: =AE4*E4-AF4 -> 0 | AH4: =IF(E4="",0,H4) -> 0 | AJ4: =AH4*E4-AI4 -> 0 | AK4: =AH4-AI4-AJ4 -> 0 | AL4: =AE4-AF4-AG4 -> 0 | AM4: =IF(E4="","",+AE4/AH4) | AN4: =IF(S4="",M4*E4,S4*E4) -> 0 | AP4: =+AN4-AO4 -> 0 | AQ4: =+L4*E4 -> 0 | AS4: =+AQ4-AR4 -> 0 | AT4: =IF(P4="",J4*E4,P4*E4) -> 0 | AV4: =+AT4-AU4 -> 0 | AW4: =IF(Q4="",K4*E4,Q4*E4) -> 0 | AY4: =+AW4-AX4 -> 0 | AZ4: =+E4*N4 -> 0
B5: Projet Lucas / Huguet Vivoin | C5: non | D5: 1. Offre de financement | F5: 162000 | G5: 5000 | H5: =F5+G5-I5 -> 162000 | I5: 5000 | J5: =(F5+G5-I5)*0.06 -> 9720 | K5: =(F5+G5-I5)*0.025 -> 4050 | L5: 7600.15 | M5: =(F5+G5)*0.62 -> 103540 | U5: =IF(C5="oui","",(H5+I5)*E5) -> 0 | V5: =IF(O5="",0,(1-E5)*O5) -> 0 | W5: =IF(O5="",I5*(E5),0) -> 0 | X5: =IF(P5="",+H5*6%*E5,0) -> 0 | Y5: =IF(P5="",0,P5*(1-E5)) -> 0 | Z5: =IF(Q5="",+H5*2.5%*E5,0) -> 0 | AA5: =IF(Q5="",0,Q5*(1-E5)) -> 0 | AB5: =IF(R5="",+L5*E5,(1-E5)*R5) -> 0 | AC5: =IF(S5="",M5*E5,S5*E5) -> 0 | AD5: =IF(T5="",0,T5*(1-E5)) -> 0 | AE5: =IF(E5="",0,+H5-J5-K5-L5-M5-N5) -> 0 | AG5: =AE5*E5-AF5 -> 0 | AH5: =IF(E5="",0,H5) -> 0 | AJ5: =AH5*E5-AI5 -> 0 | AK5: =AH5-AI5-AJ5 -> 0 | AL5: =AE5-AF5-AG5 -> 0 | AM5: =IF(E5="","",+AE5/AH5) | AN5: =IF(S5="",M5*E5,S5*E5) -> 0 | AP5: =+AN5-AO5 -> 0 | AQ5: =+L5*E5 -> 0 | AS5: =+AQ5-AR5 -> 0 | AT5: =IF(P5="",J5*E5,P5*E5) -> 0 | AV5: =+AT5-AU5 -> 0 | AW5: =IF(Q5="",K5*E5,Q5*E5) -> 0 | AY5: =+AW5-AX5 -> 0 | AZ5: =+E5*N5 -> 0
B6: Projet Diallo / Diallo Ecommoy | C6: non | D6: 1. Offre de financement | F6: 106000 | G6: 5000 | H6: =F6+G6-I6 -> 106000 | I6: 5000 | J6: =(F6+G6-I6)*0.06 -> 6360 | K6: =(F6+G6-I6)*0.025 -> 2650 | L6: 7600.15 | M6: =(F6+G6)*0.62 -> 68820 | U6: =IF(C6="oui","",(H6+I6)*E6) -> 0 | V6: =IF(O6="",0,(1-E6)*O6) -> 0 | W6: =IF(O6="",I6*(E6),0) -> 0 | X6: =IF(P6="",+H6*6%*E6,0) -> 0 | Y6: =IF(P6="",0,P6*(1-E6)) -> 0 | Z6: =IF(Q6="",+H6*2.5%*E6,0) -> 0 | AA6: =IF(Q6="",0,Q6*(1-E6)) -> 0 | AB6: =IF(R6="",+L6*E6,(1-E6)*R6) -> 0 | AC6: =IF(S6="",M6*E6,S6*E6) -> 0 | AD6: =IF(T6="",0,T6*(1-E6)) -> 0 | AE6: =IF(E6="",0,+H6-J6-K6-L6-M6-N6) -> 0 | AG6: =AE6*E6-AF6 -> 0 | AH6: =IF(E6="",0,H6) -> 0 | AJ6: =AH6*E6-AI6 -> 0 | AK6: =AH6-AI6-AJ6 -> 0 | AL6: =AE6-AF6-AG6 -> 0 | AM6: =IF(E6="","",+AE6/AH6) | AN6: =IF(S6="",M6*E6,S6*E6) -> 0 | AP6: =+AN6-AO6 -> 0 | AQ6: =+L6*E6 -> 0 | AS6: =+AQ6-AR6 -> 0 | AT6: =IF(P6="",J6*E6,P6*E6) -> 0 | AV6: =+AT6-AU6 -> 0 | AW6: =IF(Q6="",K6*E6,Q6*E6) -> 0 | AY6: =+AW6-AX6 -> 0 | AZ6: =+E6*N6 -> 0
B7: Projet Ikia / La Ferté Bernard | C7: non | D7: 1. Offre de financement | F7: 98333.333 | G7: 5000 | H7: =F7+G7-I7 -> 98333.333 | I7: 5000 | J7: =(F7+G7-I7)*0.06 -> 5900 | K7: =(F7+G7-I7)*0.025 -> 2458.3333 | L7: 7600.15 | M7: =(F7+G7)*0.62 -> 64066.667 | U7: =IF(C7="oui","",(H7+I7)*E7) -> 0 | V7: =IF(O7="",0,(1-E7)*O7) -> 0 | W7: =IF(O7="",I7*(E7),0) -> 0 | X7: =IF(P7="",+H7*6%*E7,0) -> 0 | Y7: =IF(P7="",0,P7*(1-E7)) -> 0 | Z7: =IF(Q7="",+H7*2.5%*E7,0) -> 0 | AA7: =IF(Q7="",0,Q7*(1-E7)) -> 0 | AB7: =IF(R7="",+L7*E7,(1-E7)*R7) -> 0 | AC7: =IF(S7="",M7*E7,S7*E7) -> 0 | AD7: =IF(T7="",0,T7*(1-E7)) -> 0 | AE7: =IF(E7="",0,+H7-J7-K7-L7-M7-N7) -> 0 | AG7: =AE7*E7-AF7 -> 0 | AH7: =IF(E7="",0,H7) -> 0 | AJ7: =AH7*E7-AI7 -> 0 | AK7: =AH7-AI7-AJ7 -> 0 | AL7: =AE7-AF7-AG7 -> 0 | AM7: =IF(E7="","",+AE7/AH7) | AN7: =IF(S7="",M7*E7,S7*E7) -> 0 | AP7: =+AN7-AO7 -> 0 | AQ7: =+L7*E7 -> 0 | AS7: =+AQ7-AR7 -> 0 | AT7: =IF(P7="",J7*E7,P7*E7) -> 0 | AV7: =+AT7-AU7 -> 0 | AW7: =IF(Q7="",K7*E7,Q7*E7) -> 0 | AY7: =+AW7-AX7 -> 0 | AZ7: =+E7*N7 -> 0
